01_basics/07_fsm/seq_detect_moore.v
// ==================================================
//	[ VLSISYS Lab. ]
//	* Author		: Woong Choi (woongchoi@sm.ac.kr)
//	* Filename		: seq_detect_moore.v
//	* Description	: 
//		- '1011' Sequence Detect Using Moore FSM
// ==================================================
module seq_detect_moore
(	
	output reg					o_out,
	input						i_seq,
	input						i_clk,
	input						i_rstn
);

	reg		[2:0]	cState;
	reg		[2:0]	nState;
	reg				seq;
	
	// States
	localparam	S_IDLE	=	3'b000;
	localparam	S_H		=	3'b001;
	localparam	S_HL	=   3'b010;
	localparam	S_HLH	=   3'b011;
	localparam	S_HLHH	=   3'b100;

	// State Register
	always @(posedge i_clk or negedge i_rstn) begin
		if(!i_rstn) begin
			cState	<= S_IDLE;
			seq		<= 1'b0;
		end else begin
			cState	<= nState;
			seq		<= i_seq;
		end
	end

	// 'Next State' Comb. Logic
	always @(*) begin
		if(seq == 1'b0) begin
			case(cState)
				S_IDLE	:	nState	= S_IDLE;
				S_H		:	nState	= S_HL;
				S_HL	:   nState	= S_IDLE;
				S_HLH	:   nState	= S_HL;
				S_HLHH	:   nState	= S_IDLE;
			endcase
		end else begin
			case(cState)
				S_IDLE	:	nState	= S_H;
				S_H		:	nState	= S_H;
				S_HL	:   nState	= S_HLH;
				S_HLH	:   nState	= S_HLHH;
				S_HLHH	:   nState	= S_H;
			endcase
		end
	end
	
	// 'Output' Comb. Logic
	always @(*) begin
		case(cState)
			S_HLHH	:   o_out	= 1'b1;
			default	:	o_out	= 1'b0;
		endcase
	end

endmodule

01_basics/07_fsm/seq_detect_moore_tb.v
// ==================================================
//	[ VLSISYS Lab. ]
//	* Author		: Woong Choi (woongchoi@sm.ac.kr)
//	* Filename		: seq_detect_moore_tb.v
//	* Description	: 
// ==================================================

// --------------------------------------------------
//	Define Global Variables
// --------------------------------------------------
`define	CLKFREQ		100		// Clock Freq. (Unit: MHz)
`define	SIMCYCLE	100		// Sim. Cycles

// --------------------------------------------------
//	Includes
// --------------------------------------------------
`include	"seq_detect_moore.v"

module seq_detect_moore_tb;
// --------------------------------------------------
//	DUT Signals & Instantiate
// --------------------------------------------------
	wire					o_out;
	reg						i_seq;
	reg						i_clk;
	reg						i_rstn;

	seq_detect_moore
	u_seq_detect_moore(
		.o_out			(o_out			),
		.i_seq			(i_seq			),
		.i_clk			(i_clk			),
		.i_rstn			(i_rstn			)
	);

// --------------------------------------------------
//	Clock
// --------------------------------------------------
//	reg							i_clk = 0;
	always	#(500/`CLKFREQ)		i_clk = ~i_clk;

// --------------------------------------------------
//	Tasks
// --------------------------------------------------
	reg		[4*32-1:0] taskState;	// Length is limitted to 32

	task init;
		begin
			i_seq			= 0;
			i_clk			= 0;
			i_rstn			= 0;
		end
	endtask

	task resetReleaseAfterNCycles;
		input	[  9:0]		n;
		begin
			taskState	= "Reset";
			i_rstn = 1'b0;
			#(n*1000/`CLKFREQ);
			i_rstn = 1'b1;
		end
	endtask

// --------------------------------------------------
//	Test Stimulus
// --------------------------------------------------
	integer		i, j;
	initial begin
		init();
		resetReleaseAfterNCycles(4);

		for (i=0; i<`SIMCYCLE; i++) begin
			i_seq	= $random;
			#(1000/`CLKFREQ);
		end
		$finish;
	end

// --------------------------------------------------
//	Dump VCD
// --------------------------------------------------
	reg	[8*32-1:0]	vcd_file;
	initial begin
		if ($value$plusargs("vcd_file=%s", vcd_file)) begin
			$dumpfile(vcd_file);
			$dumpvars;
		end else begin
			$dumpfile("seq_detect_moore_tb.vcd");
			$dumpvars;
		end
	end

endmodule

01_basics/07_fsm/vcd/seq_detect_moore.vcd
$date
	Thu May 16 21:43:31 2024
$end
$version
	Icarus Verilog
$end
$timescale
	1ps
$end
$scope module seq_detect_moore_tb $end
$var wire 1 ! o_out $end
$var reg 1 " i_clk $end
$var reg 1 # i_rstn $end
$var reg 1 $ i_seq $end
$var reg 128 % taskState [127:0] $end
$var reg 256 & vcd_file [255:0] $end
$var integer 32 ' i [31:0] $end
$scope module u_seq_detect_moore $end
$var wire 1 " i_clk $end
$var wire 1 # i_rstn $end
$var wire 1 $ i_seq $end
$var reg 3 ( cState [2:0] $end
$var reg 3 ) nState [2:0] $end
$var reg 1 ! o_out $end
$var reg 1 * seq $end
$upscope $end
$scope task init $end
$upscope $end
$scope task resetReleaseAfterNCycles $end
$var reg 10 + n [9:0] $end
$upscope $end
$upscope $end
$enddefinitions $end
#0
$dumpvars
b100 +
0*
b0 )
b0 (
bx '
b10111000101111011101100110001101100100001011110111001101100101011100010101111101100100011001010111010001100101011000110111010001011111011011010110111101101111011100100110010100101110011101100110001101100100 &
b101001001100101011100110110010101110100 %
0$
0#
1"
0!
$end
#5000
0"
#10000
1"
#15000
0"
#20000
1"
#25000
0"
#30000
1"
#35000
0"
#40000
1"
b0 '
1#
#45000
0"
#50000
b1 )
1*
1"
1$
b1 '
#55000
0"
#60000
b1 (
1"
b10 '
#65000
0"
#70000
1"
b11 '
#75000
0"
#80000
1"
b100 '
#85000
0"
#90000
1"
b101 '
#95000
0"
#100000
1"
b110 '
#105000
0"
#110000
b10 )
0*
1"
0$
b111 '
#115000
0"
#120000
b11 )
1*
b10 (
1"
1$
b1000 '
#125000
0"
#130000
b100 )
b11 (
1"
b1001 '
#135000
0"
#140000
1!
b0 )
0*
b100 (
1"
0$
b1010 '
#145000
0"
#150000
0!
b1 )
1*
b0 (
1"
1$
b1011 '
#155000
0"
#160000
b1 (
1"
b1100 '
#165000
0"
#170000
b10 )
0*
1"
0$
b1101 '
#175000
0"
#180000
b11 )
1*
b10 (
1"
1$
b1110 '
#185000
0"
#190000
b10 )
0*
b11 (
1"
0$
b1111 '
#195000
0"
#200000
b11 )
1*
b10 (
1"
1$
b10000 '
#205000
0"
#210000
b10 )
0*
b11 (
1"
0$
b10001 '
#215000
0"
#220000
b11 )
1*
b10 (
1"
1$
b10010 '
#225000
0"
#230000
b100 )
b11 (
1"
b10011 '
#235000
0"
#240000
1!
b0 )
0*
b100 (
1"
0$
b10100 '
#245000
0"
#250000
0!
b1 )
1*
b0 (
1"
1$
b10101 '
#255000
0"
#260000
b10 )
0*
b1 (
1"
0$
b10110 '
#265000
0"
#270000
b0 )
b10 (
1"
b10111 '
#275000
0"
#280000
b0 (
1"
b11000 '
#285000
0"
#290000
b1 )
1*
1"
1$
b11001 '
#295000
0"
#300000
b10 )
0*
b1 (
1"
0$
b11010 '
#305000
0"
#310000
b11 )
1*
b10 (
1"
1$
b11011 '
#315000
0"
#320000
b100 )
b11 (
1"
b11100 '
#325000
0"
#330000
1!
b1 )
b100 (
1"
b11101 '
#335000
0"
#340000
0!
b1 (
1"
b11110 '
#345000
0"
#350000
b10 )
0*
1"
0$
b11111 '
#355000
0"
#360000
b0 )
b10 (
1"
b100000 '
#365000
0"
#370000
b0 (
1"
b100001 '
#375000
0"
#380000
1"
b100010 '
#385000
0"
#390000
b1 )
1*
1"
1$
b100011 '
#395000
0"
#400000
b10 )
0*
b1 (
1"
0$
b100100 '
#405000
0"
#410000
b11 )
1*
b10 (
1"
1$
b100101 '
#415000
0"
#420000
b100 )
b11 (
1"
b100110 '
#425000
0"
#430000
1!
b1 )
b100 (
1"
b100111 '
#435000
0"
#440000
0!
b1 (
1"
b101000 '
#445000
0"
#450000
1"
b101001 '
#455000
0"
#460000
b10 )
0*
1"
0$
b101010 '
#465000
0"
#470000
b0 )
b10 (
1"
b101011 '
#475000
0"
#480000
b1 )
1*
b0 (
1"
1$
b101100 '
#485000
0"
#490000
b1 (
1"
b101101 '
#495000
0"
#500000
1"
b101110 '
#505000
0"
#510000
b10 )
0*
1"
0$
b101111 '
#515000
0"
#520000
b0 )
b10 (
1"
b110000 '
#525000
0"
#530000
b0 (
1"
b110001 '
#535000
0"
#540000
1"
b110010 '
#545000
0"
#550000
1"
b110011 '
#555000
0"
#560000
b1 )
1*
1"
1$
b110100 '
#565000
0"
#570000
b10 )
0*
b1 (
1"
0$
b110101 '
#575000
0"
#580000
b0 )
b10 (
1"
b110110 '
#585000
0"
#590000
b1 )
1*
b0 (
1"
1$
b110111 '
#595000
0"
#600000
b1 (
1"
b111000 '
#605000
0"
#610000
b10 )
0*
1"
0$
b111001 '
#615000
0"
#620000
b0 )
b10 (
1"
b111010 '
#625000
0"
#630000
b0 (
1"
b111011 '
#635000
0"
#640000
1"
b111100 '
#645000
0"
#650000
1"
b111101 '
#655000
0"
#660000
b1 )
1*
1"
1$
b111110 '
#665000
0"
#670000
b1 (
1"
b111111 '
#675000
0"
#680000
1"
b1000000 '
#685000
0"
#690000
1"
b1000001 '
#695000
0"
#700000
1"
b1000010 '
#705000
0"
#710000
b10 )
0*
1"
0$
b1000011 '
#715000
0"
#720000
b0 )
b10 (
1"
b1000100 '
#725000
0"
#730000
b1 )
1*
b0 (
1"
1$
b1000101 '
#735000
0"
#740000
b1 (
1"
b1000110 '
#745000
0"
#750000
1"
b1000111 '
#755000
0"
#760000
b10 )
0*
1"
0$
b1001000 '
#765000
0"
#770000
b0 )
b10 (
1"
b1001001 '
#775000
0"
#780000
b1 )
1*
b0 (
1"
1$
b1001010 '
#785000
0"
#790000
b1 (
1"
b1001011 '
#795000
0"
#800000
b10 )
0*
1"
0$
b1001100 '
#805000
0"
#810000
b11 )
1*
b10 (
1"
1$
b1001101 '
#815000
0"
#820000
b100 )
b11 (
1"
b1001110 '
#825000
0"
#830000
1!
b0 )
0*
b100 (
1"
0$
b1001111 '
#835000
0"
#840000
0!
b1 )
1*
b0 (
1"
1$
b1010000 '
#845000
0"
#850000
b1 (
1"
b1010001 '
#855000
0"
#860000
1"
b1010010 '
#865000
0"
#870000
b10 )
0*
1"
0$
b1010011 '
#875000
0"
#880000
b11 )
1*
b10 (
1"
1$
b1010100 '
#885000
0"
#890000
b100 )
b11 (
1"
b1010101 '
#895000
0"
#900000
1!
b0 )
0*
b100 (
1"
0$
b1010110 '
#905000
0"
#910000
0!
b0 (
1"
b1010111 '
#915000
0"
#920000
1"
b1011000 '
#925000
0"
#930000
1"
b1011001 '
#935000
0"
#940000
b1 )
1*
1"
1$
b1011010 '
#945000
0"
#950000
b1 (
1"
b1011011 '
#955000
0"
#960000
b10 )
0*
1"
0$
b1011100 '
#965000
0"
#970000
b0 )
b10 (
1"
b1011101 '
#975000
0"
#980000
b1 )
1*
b0 (
1"
1$
b1011110 '
#985000
0"
#990000
b1 (
1"
b1011111 '
#995000
0"
#1000000
1"
b1100000 '
#1005000
0"
#1010000
1"
b1100001 '
#1015000
0"
#1020000
1"
b1100010 '
#1025000
0"
#1030000
b10 )
0*
1"
0$
b1100011 '
#1035000
0"
#1040000
b0 )
b10 (
1"
b1100100 '
