03_riscv/riscv_params.v
// ==================================================
//	[ VLSISYS Lab. ]
//	* Author		: Woong Choi (woongchoi@sm.ac.kr)
//	* Filename		: riscv_params.v
//	* Description	: 
// ==================================================





// --------------------------------------------------
//	MUX
// --------------------------------------------------
`define	MUX_DATA_BIT		32
`define	MUX_DATA_BUS		`MUX_DATA_BIT-1:0

// --------------------------------------------------
//	Adder
// --------------------------------------------------
`define	ADD_DATA_BIT		32
`define	ADD_DATA_BUS		`ADD_DATA_BIT-1:0

// --------------------------------------------------
//	DFF
// --------------------------------------------------
`define	DFF_DATA_BIT		32
`define	DFF_DATA_BUS		`DFF_DATA_BIT-1:0

// --------------------------------------------------
//	Register File
// --------------------------------------------------
`define	REG_DATA_BIT		32
`define	REG_ADDR_BIT		5
`define	REG_DATA_BUS		`REG_DATA_BIT-1:0
`define	REG_ADDR_BUS		`REG_ADDR_BIT-1:0

// --------------------------------------------------
//	Instruction Memory
// --------------------------------------------------
`define	IMEM_DATA_BIT		32
`define	IMEM_ADDR_BIT		5
`define	IMEM_DATA_BUS		`IMEM_DATA_BIT-1:0
`define	IMEM_ADDR_BUS		`IMEM_ADDR_BIT-1:0
`define	IMEM_INIT_FILE		""

// --------------------------------------------------
//	Data Memory
// --------------------------------------------------
`define	DMEM_DATA_BIT		32
`define	DMEM_ADDR_BIT		32
`define	DMEM_DATA_BUS		`DMEM_DATA_BIT-1:0
`define	DMEM_ADDR_BUS		`DMEM_ADDR_BIT-1:0
`define	DMEM_INIT_FILE		""

// --------------------------------------------------
//	ALU (Arithmetic & Logical Unit)
// --------------------------------------------------
`define	ALU_DATA_BIT		32
`define	ALU_CTRL_BIT		4
`define	ALU_DATA_BUS		`ALU_DATA_BIT-1:0
`define	ALU_CTRL_BUS		`ALU_CTRL_BIT-1:0
//							{func7[5], fucn3}
`define	ALU_OP_ADD			4'b0000
`define	ALU_OP_SUB			4'b1000
`define	ALU_OP_SLL			4'b0001	// Shift Left Logical
`define	ALU_OP_SLT			4'b0010	// Set on Less Than
`define	ALU_OP_SLTU			4'b0011	// Set on Less Than Unsigned
`define	ALU_OP_XOR			4'b0100
`define	ALU_OP_SRL			4'b0101	// Shift Right Logical / Arithmetic
`define	ALU_OP_SRA			4'b1101	// Shift Right Logical / Arithmetic
`define	ALU_OP_OR			4'b0110
`define	ALU_OP_AND			4'b0111

// --------------------------------------------------
//	Immidiate Generate
// --------------------------------------------------
`define	IMM_DATA_BIT		32
`define	IMM_CTRL_BIT		3
`define	IMM_DATA_BUS		`IMM_DATA_BIT-1:0
`define	IMM_CTRL_BUS		`IMM_CTRL_BIT-1:0
`define	IMM_INST_BUS		31:7
//	IMM Type
`define	IMM_TYPE_I			3'b000
`define	IMM_TYPE_S			3'b001
`define	IMM_TYPE_B			3'b010
`define	IMM_TYPE_U			3'b011
`define	IMM_TYPE_J			3'b100

03_riscv/riscv_regfile.v
// ==================================================
//	[ VLSISYS Lab. ]
//	* Author		: Woong Choi (woongchoi@sm.ac.kr)
//	* Filename		: riscv_regfile.v
//	* Description	: 
// ==================================================

`include		"riscv_params.v"

module riscv_regfile
(
	output		[`REG_DATA_BUS]	o_reg_rd_data0,
	output		[`REG_DATA_BUS]	o_reg_rd_data1,
	input		[`REG_ADDR_BUS]	i_reg_rd_addr0,
	input		[`REG_ADDR_BUS]	i_reg_rd_addr1,
	input		[`REG_DATA_BUS]	i_reg_wr_data,
	input		[`REG_ADDR_BUS]	i_reg_wr_addr,
	input						i_reg_wr_en,
	input						i_clk,
	input						i_rstn
);

	reg			[`REG_DATA_BUS]	reg_arr[0:2**`REG_ADDR_BIT-1];

	// Async. Read 
	assign		o_reg_rd_data0	= reg_arr[i_reg_rd_addr0];
	assign		o_reg_rd_data1	= reg_arr[i_reg_rd_addr1];

	integer		i;
	always @(posedge i_clk or negedge i_rstn) begin
		if(!i_rstn) begin
			for (i=0; i<2**`REG_ADDR_BIT-1; i++) begin
				reg_arr[i_reg_wr_addr] <= 0;
			end
		end else begin
			//	"Write" and  "Write Address != 0"
			if (i_reg_wr_en && (i_reg_wr_addr != 0)) begin
				reg_arr[i_reg_wr_addr] <= i_reg_wr_data;
			//	Hold Data
			end else begin
				reg_arr[i_reg_wr_addr] <= reg_arr[i_reg_wr_addr];
			end
		end
	end

endmodule

03_riscv/riscv_regfile_tb.v
// ==================================================
//	[ VLSISYS Lab. ]
//	* Author		: Woong Choi (woongchoi@sm.ac.kr)
//	* Filename		: riscv_regfile_tb.v
//	* Description	: 
// ==================================================

// --------------------------------------------------
//	Define Global Variables
// --------------------------------------------------
`define	CLKFREQ		100				// Clock Freq. (Unit: MHz)
`define	SIMCYCLE	2**`REG_ADDR_BIT	// Sim. Cycles

`include	"riscv_regfile.v"

module	riscv_regfile_tb;
// --------------------------------------------------
//	DUT Signals & Instantiate
// --------------------------------------------------

	wire	[`REG_DATA_BUS]	o_reg_rd_data0;
	wire	[`REG_DATA_BUS]	o_reg_rd_data1;
	reg		[`REG_ADDR_BUS]	i_reg_rd_addr0;
	reg		[`REG_ADDR_BUS]	i_reg_rd_addr1;
	reg		[`REG_DATA_BUS]	i_reg_wr_data;
	reg		[`REG_ADDR_BUS]	i_reg_wr_addr;
	reg						i_reg_wr_en;
	reg						i_clk;
	reg						i_rstn;

	riscv_regfile
	u_riscv_regfile(
		.o_reg_rd_data0		(o_reg_rd_data0		),
		.o_reg_rd_data1		(o_reg_rd_data1		),
		.i_reg_rd_addr0		(i_reg_rd_addr0		),
		.i_reg_rd_addr1		(i_reg_rd_addr1		),
		.i_reg_wr_data		(i_reg_wr_data		),
		.i_reg_wr_addr		(i_reg_wr_addr		),
		.i_reg_wr_en		(i_reg_wr_en		),
		.i_clk				(i_clk			),
		.i_rstn				(i_rstn			)
	);

// --------------------------------------------------
//	Clock
// --------------------------------------------------
	always	#(500/`CLKFREQ)	i_clk = ~i_clk;

// --------------------------------------------------
//	Tasks
// --------------------------------------------------
	reg		[4*32-1:0] taskState;	// Length is limitted to 32

	task init;
		begin
			i_reg_rd_addr0	= 0;
			i_reg_rd_addr1	= 0;
			i_reg_wr_data	= 0;
			i_reg_wr_addr	= 0;
			i_reg_wr_en		= 0;
			i_clk			= 0;
			i_rstn			= 0;
		end
	endtask

	task resetReleaseAfterNCycles;
		input	[  9:0]		n;
		begin
			taskState	= "Reset";
			i_rstn = 1'b0;
			#(n*1000/`CLKFREQ);
			i_rstn = 1'b1;
		end
	endtask

	task regWR;
		input	[`REG_ADDR_BUS]	ti_reg_wr_addr;
		input	[`REG_DATA_BUS]	ti_reg_wr_data;
		begin
			taskState	= "WR";
			@(negedge i_clk) begin
			//	$display ("==================================================");
				$display ("%8g Write (%d) @ #(%d) of ResisterFile", $time, ti_reg_wr_data, ti_reg_wr_addr);
				i_reg_wr_data	= ti_reg_wr_data;
				i_reg_wr_addr	= ti_reg_wr_addr;
				i_reg_wr_en		= 1;
			end
		end
	endtask

	task regRD;
		input	[`REG_ADDR_BUS]	ti_reg_rd_addr0;
		input	[`REG_ADDR_BUS]	ti_reg_rd_addr1;
		begin
			taskState	= "RD";
			@(negedge i_clk) begin
				i_reg_rd_addr0	= ti_reg_rd_addr0;
				i_reg_rd_addr1	= ti_reg_rd_addr1;
				i_reg_wr_en		= 0;
			end
			@(posedge i_clk) begin
//				$display ("==================================================");
				$display ("%8g  Read (%d) @ #(%d) of ResisterFile", $time, o_reg_rd_data0, i_reg_rd_addr0);
				$display ("%8g  Read (%d) @ #(%d) of ResisterFile", $time, o_reg_rd_data1, i_reg_rd_addr1);
			end
		end
	endtask

	task singleCycle;
		begin
			#(1000/`CLKFREQ);
		end
	endtask

// --------------------------------------------------
//	Test Stimulus
// --------------------------------------------------
	integer		i, j;
	initial begin
		init();
		resetReleaseAfterNCycles(4);
		for (i=0; i<`SIMCYCLE; i++) begin
			regWR(i, i);
			singleCycle;
		end
		for (i=0; i<`SIMCYCLE; i++) begin
			regRD($urandom_range(0, 31), $urandom_range(0, 31));
			#(1000/`CLKFREQ);
		end
		resetReleaseAfterNCycles(4);
		for (i=0; i<`SIMCYCLE; i++) begin
			regWR(i, $urandom_range(0, 2**31-1));	// 2**32 is not supported
			#(1000/`CLKFREQ);
			regRD(i, i);
			#(1000/`CLKFREQ);
		end
		$finish;
	end

// --------------------------------------------------
//	Dump VCD
// --------------------------------------------------
	reg	[8*32-1:0]	vcd_file;
	initial begin
		if ($value$plusargs("vcd_file=%s", vcd_file)) begin
			$dumpfile(vcd_file);
			$dumpvars;
			for (i=0; i<2**`REG_ADDR_BIT; i++) begin
				$dumpvars(0, u_riscv_regfile.reg_arr[i]);
			end
			$dumpvars;
		end else begin
			$dumpfile("regfile_tb.vcd");
			$dumpvars;
		end
	end

endmodule

03_riscv/vcd/riscv_regfile.vcd
$date
	Mon May 13 17:27:53 2024
$end
$version
	Icarus Verilog
$end
$timescale
	1ps
$end
$scope module riscv_regfile_tb $end
$var wire 32 ! o_reg_rd_data1 [31:0] $end
$var wire 32 " o_reg_rd_data0 [31:0] $end
$var reg 1 # i_clk $end
$var reg 5 $ i_reg_rd_addr0 [4:0] $end
$var reg 5 % i_reg_rd_addr1 [4:0] $end
$var reg 5 & i_reg_wr_addr [4:0] $end
$var reg 32 ' i_reg_wr_data [31:0] $end
$var reg 1 ( i_reg_wr_en $end
$var reg 1 ) i_rstn $end
$var reg 128 * taskState [127:0] $end
$var reg 256 + vcd_file [255:0] $end
$var integer 32 , i [31:0] $end
$scope module u_riscv_regfile $end
$var wire 1 # i_clk $end
$var wire 5 - i_reg_rd_addr0 [4:0] $end
$var wire 5 . i_reg_rd_addr1 [4:0] $end
$var wire 5 / i_reg_wr_addr [4:0] $end
$var wire 32 0 i_reg_wr_data [31:0] $end
$var wire 1 ( i_reg_wr_en $end
$var wire 1 ) i_rstn $end
$var wire 32 1 o_reg_rd_data0 [31:0] $end
$var wire 32 2 o_reg_rd_data1 [31:0] $end
$var integer 32 3 i [31:0] $end
$upscope $end
$scope task init $end
$upscope $end
$scope task regRD $end
$var reg 5 4 ti_reg_rd_addr0 [4:0] $end
$var reg 5 5 ti_reg_rd_addr1 [4:0] $end
$upscope $end
$scope task regWR $end
$var reg 5 6 ti_reg_wr_addr [4:0] $end
$var reg 32 7 ti_reg_wr_data [31:0] $end
$upscope $end
$scope task resetReleaseAfterNCycles $end
$var reg 10 8 n [9:0] $end
$upscope $end
$scope task singleCycle $end
$upscope $end
$upscope $end
$scope module riscv_regfile_tb $end
$scope module u_riscv_regfile $end
$var reg 32 9 \reg_arr[0] [31:0] $end
$upscope $end
$upscope $end
$scope module riscv_regfile_tb $end
$scope module u_riscv_regfile $end
$var reg 32 : \reg_arr[1] [31:0] $end
$upscope $end
$upscope $end
$scope module riscv_regfile_tb $end
$scope module u_riscv_regfile $end
$var reg 32 ; \reg_arr[2] [31:0] $end
$upscope $end
$upscope $end
$scope module riscv_regfile_tb $end
$scope module u_riscv_regfile $end
$var reg 32 < \reg_arr[3] [31:0] $end
$upscope $end
$upscope $end
$scope module riscv_regfile_tb $end
$scope module u_riscv_regfile $end
$var reg 32 = \reg_arr[4] [31:0] $end
$upscope $end
$upscope $end
$scope module riscv_regfile_tb $end
$scope module u_riscv_regfile $end
$var reg 32 > \reg_arr[5] [31:0] $end
$upscope $end
$upscope $end
$scope module riscv_regfile_tb $end
$scope module u_riscv_regfile $end
$var reg 32 ? \reg_arr[6] [31:0] $end
$upscope $end
$upscope $end
$scope module riscv_regfile_tb $end
$scope module u_riscv_regfile $end
$var reg 32 @ \reg_arr[7] [31:0] $end
$upscope $end
$upscope $end
$scope module riscv_regfile_tb $end
$scope module u_riscv_regfile $end
$var reg 32 A \reg_arr[8] [31:0] $end
$upscope $end
$upscope $end
$scope module riscv_regfile_tb $end
$scope module u_riscv_regfile $end
$var reg 32 B \reg_arr[9] [31:0] $end
$upscope $end
$upscope $end
$scope module riscv_regfile_tb $end
$scope module u_riscv_regfile $end
$var reg 32 C \reg_arr[10] [31:0] $end
$upscope $end
$upscope $end
$scope module riscv_regfile_tb $end
$scope module u_riscv_regfile $end
$var reg 32 D \reg_arr[11] [31:0] $end
$upscope $end
$upscope $end
$scope module riscv_regfile_tb $end
$scope module u_riscv_regfile $end
$var reg 32 E \reg_arr[12] [31:0] $end
$upscope $end
$upscope $end
$scope module riscv_regfile_tb $end
$scope module u_riscv_regfile $end
$var reg 32 F \reg_arr[13] [31:0] $end
$upscope $end
$upscope $end
$scope module riscv_regfile_tb $end
$scope module u_riscv_regfile $end
$var reg 32 G \reg_arr[14] [31:0] $end
$upscope $end
$upscope $end
$scope module riscv_regfile_tb $end
$scope module u_riscv_regfile $end
$var reg 32 H \reg_arr[15] [31:0] $end
$upscope $end
$upscope $end
$scope module riscv_regfile_tb $end
$scope module u_riscv_regfile $end
$var reg 32 I \reg_arr[16] [31:0] $end
$upscope $end
$upscope $end
$scope module riscv_regfile_tb $end
$scope module u_riscv_regfile $end
$var reg 32 J \reg_arr[17] [31:0] $end
$upscope $end
$upscope $end
$scope module riscv_regfile_tb $end
$scope module u_riscv_regfile $end
$var reg 32 K \reg_arr[18] [31:0] $end
$upscope $end
$upscope $end
$scope module riscv_regfile_tb $end
$scope module u_riscv_regfile $end
$var reg 32 L \reg_arr[19] [31:0] $end
$upscope $end
$upscope $end
$scope module riscv_regfile_tb $end
$scope module u_riscv_regfile $end
$var reg 32 M \reg_arr[20] [31:0] $end
$upscope $end
$upscope $end
$scope module riscv_regfile_tb $end
$scope module u_riscv_regfile $end
$var reg 32 N \reg_arr[21] [31:0] $end
$upscope $end
$upscope $end
$scope module riscv_regfile_tb $end
$scope module u_riscv_regfile $end
$var reg 32 O \reg_arr[22] [31:0] $end
$upscope $end
$upscope $end
$scope module riscv_regfile_tb $end
$scope module u_riscv_regfile $end
$var reg 32 P \reg_arr[23] [31:0] $end
$upscope $end
$upscope $end
$scope module riscv_regfile_tb $end
$scope module u_riscv_regfile $end
$var reg 32 Q \reg_arr[24] [31:0] $end
$upscope $end
$upscope $end
$scope module riscv_regfile_tb $end
$scope module u_riscv_regfile $end
$var reg 32 R \reg_arr[25] [31:0] $end
$upscope $end
$upscope $end
$scope module riscv_regfile_tb $end
$scope module u_riscv_regfile $end
$var reg 32 S \reg_arr[26] [31:0] $end
$upscope $end
$upscope $end
$scope module riscv_regfile_tb $end
$scope module u_riscv_regfile $end
$var reg 32 T \reg_arr[27] [31:0] $end
$upscope $end
$upscope $end
$scope module riscv_regfile_tb $end
$scope module u_riscv_regfile $end
$var reg 32 U \reg_arr[28] [31:0] $end
$upscope $end
$upscope $end
$scope module riscv_regfile_tb $end
$scope module u_riscv_regfile $end
$var reg 32 V \reg_arr[29] [31:0] $end
$upscope $end
$upscope $end
$scope module riscv_regfile_tb $end
$scope module u_riscv_regfile $end
$var reg 32 W \reg_arr[30] [31:0] $end
$upscope $end
$upscope $end
$scope module riscv_regfile_tb $end
$scope module u_riscv_regfile $end
$var reg 32 X \reg_arr[31] [31:0] $end
$upscope $end
$upscope $end
$scope module riscv_regfile_tb $end
$scope module u_riscv_regfile $end
$upscope $end
$scope task init $end
$upscope $end
$scope task regRD $end
$upscope $end
$scope task regWR $end
$upscope $end
$scope task resetReleaseAfterNCycles $end
$upscope $end
$scope task singleCycle $end
$upscope $end
$upscope $end
$enddefinitions $end
#0
$dumpvars
bx X
bx W
bx V
bx U
bx T
bx S
bx R
bx Q
bx P
bx O
bx N
bx M
bx L
bx K
bx J
bx I
bx H
bx G
bx F
bx E
bx D
bx C
bx B
bx A
bx @
bx ?
bx >
bx =
bx <
bx ;
bx :
b0 9
b100 8
bx 7
bx 6
bx 5
bx 4
b11111 3
b0 2
b0 1
b0 0
b0 /
b0 .
b0 -
b100000 ,
b10111000101111011101100110001101100100001011110111001001101001011100110110001101110110010111110111001001100101011001110110011001101001011011000110010100101110011101100110001101100100 +
b101001001100101011100110110010101110100 *
0)
0(
b0 '
b0 &
b0 %
b0 $
0#
b0 "
b0 !
$end
#5000
b0 9
b11111 3
1#
#10000
0#
#15000
b0 9
b11111 3
1#
#20000
0#
#25000
b0 9
b11111 3
1#
#30000
0#
#35000
b0 9
b11111 3
1#
#40000
1(
0#
b101011101010010 *
b0 7
b0 6
b0 ,
1)
#45000
b0 9
1#
#50000
b1 &
b1 /
b1 '
b1 0
0#
b1 7
b1 6
b1 ,
#55000
b1 :
1#
#60000
b10 &
b10 /
b10 '
b10 0
0#
b10 7
b10 6
b10 ,
#65000
b10 ;
1#
#70000
b11 &
b11 /
b11 '
b11 0
0#
b11 7
b11 6
b11 ,
#75000
b11 <
1#
#80000
b100 &
b100 /
b100 '
b100 0
0#
b100 7
b100 6
b100 ,
#85000
b100 =
1#
#90000
b101 &
b101 /
b101 '
b101 0
0#
b101 7
b101 6
b101 ,
#95000
b101 >
1#
#100000
b110 &
b110 /
b110 '
b110 0
0#
b110 7
b110 6
b110 ,
#105000
b110 ?
1#
#110000
b111 &
b111 /
b111 '
b111 0
0#
b111 7
b111 6
b111 ,
#115000
b111 @
1#
#120000
b1000 &
b1000 /
b1000 '
b1000 0
0#
b1000 7
b1000 6
b1000 ,
#125000
b1000 A
1#
#130000
b1001 &
b1001 /
b1001 '
b1001 0
0#
b1001 7
b1001 6
b1001 ,
#135000
b1001 B
1#
#140000
b1010 &
b1010 /
b1010 '
b1010 0
0#
b1010 7
b1010 6
b1010 ,
#145000
b1010 C
1#
#150000
b1011 &
b1011 /
b1011 '
b1011 0
0#
b1011 7
b1011 6
b1011 ,
#155000
b1011 D
1#
#160000
b1100 &
b1100 /
b1100 '
b1100 0
0#
b1100 7
b1100 6
b1100 ,
#165000
b1100 E
1#
#170000
b1101 &
b1101 /
b1101 '
b1101 0
0#
b1101 7
b1101 6
b1101 ,
#175000
b1101 F
1#
#180000
b1110 &
b1110 /
b1110 '
b1110 0
0#
b1110 7
b1110 6
b1110 ,
#185000
b1110 G
1#
#190000
b1111 &
b1111 /
b1111 '
b1111 0
0#
b1111 7
b1111 6
b1111 ,
#195000
b1111 H
1#
#200000
b10000 &
b10000 /
b10000 '
b10000 0
0#
b10000 7
b10000 6
b10000 ,
#205000
b10000 I
1#
#210000
b10001 &
b10001 /
b10001 '
b10001 0
0#
b10001 7
b10001 6
b10001 ,
#215000
b10001 J
1#
#220000
b10010 &
b10010 /
b10010 '
b10010 0
0#
b10010 7
b10010 6
b10010 ,
#225000
b10010 K
1#
#230000
b10011 &
b10011 /
b10011 '
b10011 0
0#
b10011 7
b10011 6
b10011 ,
#235000
b10011 L
1#
#240000
b10100 &
b10100 /
b10100 '
b10100 0
0#
b10100 7
b10100 6
b10100 ,
#245000
b10100 M
1#
#250000
b10101 &
b10101 /
b10101 '
b10101 0
0#
b10101 7
b10101 6
b10101 ,
#255000
b10101 N
1#
#260000
b10110 &
b10110 /
b10110 '
b10110 0
0#
b10110 7
b10110 6
b10110 ,
#265000
b10110 O
1#
#270000
b10111 &
b10111 /
b10111 '
b10111 0
0#
b10111 7
b10111 6
b10111 ,
#275000
b10111 P
1#
#280000
b11000 &
b11000 /
b11000 '
b11000 0
0#
b11000 7
b11000 6
b11000 ,
#285000
b11000 Q
1#
#290000
b11001 &
b11001 /
b11001 '
b11001 0
0#
b11001 7
b11001 6
b11001 ,
#295000
b11001 R
1#
#300000
b11010 &
b11010 /
b11010 '
b11010 0
0#
b11010 7
b11010 6
b11010 ,
#305000
b11010 S
1#
#310000
b11011 &
b11011 /
b11011 '
b11011 0
0#
b11011 7
b11011 6
b11011 ,
#315000
b11011 T
1#
#320000
b11100 &
b11100 /
b11100 '
b11100 0
0#
b11100 7
b11100 6
b11100 ,
#325000
b11100 U
1#
#330000
b11101 &
b11101 /
b11101 '
b11101 0
0#
b11101 7
b11101 6
b11101 ,
#335000
b11101 V
1#
#340000
b11110 &
b11110 /
b11110 '
b11110 0
0#
b11110 7
b11110 6
b11110 ,
#345000
b11110 W
1#
#350000
b11111 &
b11111 /
b11111 '
b11111 0
0#
b11111 7
b11111 6
b11111 ,
#355000
b11111 X
1#
#360000
0(
b1000 !
b1000 2
b1000 %
b1000 .
b10010 "
b10010 1
b10010 $
b10010 -
0#
b101001001000100 *
b1000 5
b10010 4
b0 ,
#365000
b11111 X
1#
#370000
0#
#375000
b11111 X
1#
b110 5
b0 4
b1 ,
#380000
b110 !
b110 2
b110 %
b110 .
b0 "
b0 1
b0 $
b0 -
0#
#385000
b11111 X
1#
#390000
0#
#395000
b11111 X
1#
b11000 5
b10000 4
b10 ,
#400000
b11000 !
b11000 2
b11000 %
b11000 .
b10000 "
b10000 1
b10000 $
b10000 -
0#
#405000
b11111 X
1#
#410000
0#
#415000
b11111 X
1#
b1 5
b110 4
b11 ,
#420000
b1 !
b1 2
b1 %
b1 .
b110 "
b110 1
b110 $
b110 -
0#
#425000
b11111 X
1#
#430000
0#
#435000
b11111 X
1#
b10000 5
b10000 4
b100 ,
#440000
b10000 !
b10000 2
b10000 %
b10000 .
b10000 "
b10000 1
b10000 $
b10000 -
0#
#445000
b11111 X
1#
#450000
0#
#455000
b11111 X
1#
b10011 5
b10111 4
b101 ,
#460000
b10011 !
b10011 2
b10011 %
b10011 .
b10111 "
b10111 1
b10111 $
b10111 -
0#
#465000
b11111 X
1#
#470000
0#
#475000
b11111 X
1#
b11000 5
b11110 4
b110 ,
#480000
b11000 !
b11000 2
b11000 %
b11000 .
b11110 "
b11110 1
b11110 $
b11110 -
0#
#485000
b11111 X
1#
#490000
0#
#495000
b11111 X
1#
b1100 5
b11111 4
b111 ,
#500000
b1100 !
b1100 2
b1100 %
b1100 .
b11111 "
b11111 1
b11111 $
b11111 -
0#
#505000
b11111 X
1#
#510000
0#
#515000
b11111 X
1#
b1010 5
b1100 4
b1000 ,
#520000
b1010 !
b1010 2
b1010 %
b1010 .
b1100 "
b1100 1
b1100 $
b1100 -
0#
#525000
b11111 X
1#
#530000
0#
#535000
b11111 X
1#
b111 5
b11110 4
b1001 ,
#540000
b111 !
b111 2
b111 %
b111 .
b11110 "
b11110 1
b11110 $
b11110 -
0#
#545000
b11111 X
1#
#550000
0#
#555000
b11111 X
1#
b11000 5
b1 4
b1010 ,
#560000
b11000 !
b11000 2
b11000 %
b11000 .
b1 "
b1 1
b1 $
b1 -
0#
#565000
b11111 X
1#
#570000
0#
#575000
b11111 X
1#
b1100 5
b11111 4
b1011 ,
#580000
b1100 !
b1100 2
b1100 %
b1100 .
b11111 "
b11111 1
b11111 $
b11111 -
0#
#585000
b11111 X
1#
#590000
0#
#595000
b11111 X
1#
b1110 4
b1100 ,
#600000
b1110 "
b1110 1
b1110 $
b1110 -
0#
#605000
b11111 X
1#
#610000
0#
#615000
b11111 X
1#
b1011 5
b10101 4
b1101 ,
#620000
b1011 !
b1011 2
b1011 %
b1011 .
b10101 "
b10101 1
b10101 $
b10101 -
0#
#625000
b11111 X
1#
#630000
0#
#635000
b11111 X
1#
b110 5
b10 4
b1110 ,
#640000
b110 !
b110 2
b110 %
b110 .
b10 "
b10 1
b10 $
b10 -
0#
#645000
b11111 X
1#
#650000
0#
#655000
b11111 X
1#
b10000 5
b110 4
b1111 ,
#660000
b10000 !
b10000 2
b10000 %
b10000 .
b110 "
b110 1
b110 $
b110 -
0#
#665000
b11111 X
1#
#670000
0#
#675000
b11111 X
1#
b10010 5
b1000 4
b10000 ,
#680000
b10010 !
b10010 2
b10010 %
b10010 .
b1000 "
b1000 1
b1000 $
b1000 -
0#
#685000
b11111 X
1#
#690000
0#
#695000
b11111 X
1#
b1001 5
b11010 4
b10001 ,
#700000
b1001 !
b1001 2
b1001 %
b1001 .
b11010 "
b11010 1
b11010 $
b11010 -
0#
#705000
b11111 X
1#
#710000
0#
#715000
b11111 X
1#
b1 5
b1001 4
b10010 ,
#720000
b1 !
b1 2
b1 %
b1 .
b1001 "
b1001 1
b1001 $
b1001 -
0#
#725000
b11111 X
1#
#730000
0#
#735000
b11111 X
1#
b101 5
b0 4
b10011 ,
#740000
b101 !
b101 2
b101 %
b101 .
b0 "
b0 1
b0 $
b0 -
0#
#745000
b11111 X
1#
#750000
0#
#755000
b11111 X
1#
b1101 5
b10110 4
b10100 ,
#760000
b1101 !
b1101 2
b1101 %
b1101 .
b10110 "
b10110 1
b10110 $
b10110 -
0#
#765000
b11111 X
1#
#770000
0#
#775000
b11111 X
1#
b1010 5
b0 4
b10101 ,
#780000
b1010 !
b1010 2
b1010 %
b1010 .
b0 "
b0 1
b0 $
b0 -
0#
#785000
b11111 X
1#
#790000
0#
#795000
b11111 X
1#
b1100 5
b10001 4
b10110 ,
#800000
b1100 !
b1100 2
b1100 %
b1100 .
b10001 "
b10001 1
b10001 $
b10001 -
0#
#805000
b11111 X
1#
#810000
0#
#815000
b11111 X
1#
b10000 5
b10010 4
b10111 ,
#820000
b10000 !
b10000 2
b10000 %
b10000 .
b10010 "
b10010 1
b10010 $
b10010 -
0#
#825000
b11111 X
1#
#830000
0#
#835000
b11111 X
1#
b11 5
b1100 4
b11000 ,
#840000
b11 !
b11 2
b11 %
b11 .
b1100 "
b1100 1
b1100 $
b1100 -
0#
#845000
b11111 X
1#
#850000
0#
#855000
b11111 X
1#
b11000 5
b11111 4
b11001 ,
#860000
b11000 !
b11000 2
b11000 %
b11000 .
b11111 "
b11111 1
b11111 $
b11111 -
0#
#865000
b11111 X
1#
#870000
0#
#875000
b11111 X
1#
b1101 5
b10100 4
b11010 ,
#880000
b1101 !
b1101 2
b1101 %
b1101 .
b10100 "
b10100 1
b10100 $
b10100 -
0#
#885000
b11111 X
1#
#890000
0#
#895000
b11111 X
1#
b1000 5
b10111 4
b11011 ,
#900000
b1000 !
b1000 2
b1000 %
b1000 .
b10111 "
b10111 1
b10111 $
b10111 -
0#
#905000
b11111 X
1#
#910000
0#
#915000
b11111 X
1#
b11011 5
b11110 4
b11100 ,
#920000
b11011 !
b11011 2
b11011 %
b11011 .
b11110 "
b11110 1
b11110 $
b11110 -
0#
#925000
b11111 X
1#
#930000
0#
#935000
b11111 X
1#
b11010 5
b11100 4
b11101 ,
#940000
b11010 !
b11010 2
b11010 %
b11010 .
b11100 "
b11100 1
b11100 $
b11100 -
0#
#945000
b11111 X
1#
#950000
0#
#955000
b11111 X
1#
b10010 5
b1011 4
b11110 ,
#960000
b10010 !
b10010 2
b10010 %
b10010 .
b1011 "
b1011 1
b1011 $
b1011 -
0#
#965000
b11111 X
1#
#970000
0#
#975000
b11111 X
1#
b111 5
b0 4
b11111 ,
#980000
b111 !
b111 2
b111 %
b111 .
b0 "
b0 1
b0 $
b0 -
0#
#985000
b11111 X
1#
#990000
0#
#995000
b0 X
b11111 3
1#
0)
b101001001100101011100110110010101110100 *
b100000 ,
#1000000
0#
#1005000
b0 X
b11111 3
1#
#1010000
0#
#1015000
b0 X
b11111 3
1#
#1020000
0#
#1025000
b0 X
b11111 3
1#
#1030000
0#
#1035000
b0 X
1#
b101011101010010 *
b1100001011110010010000011000010 7
b0 6
b0 ,
1)
#1040000
1(
b0 &
b0 /
b1100001011110010010000011000010 '
b1100001011110010010000011000010 0
0#
#1045000
b0 9
1#
#1050000
0(
b0 !
b0 2
b0 %
b0 .
0#
b101001001000100 *
b0 5
#1055000
b0 9
1#
#1060000
0#
#1065000
b0 9
1#
b101011101010010 *
b1010011111110010010101010100111 7
b1 6
b1 ,
#1070000
1(
b1 &
b1 /
b1010011111110010010101010100111 '
b1010011111110010010101010100111 0
0#
#1075000
b1010011111110010010101010100111 :
1#
#1080000
0(
b1010011111110010010101010100111 !
b1010011111110010010101010100111 2
b1 %
b1 .
b1010011111110010010101010100111 "
b1010011111110010010101010100111 1
b1 $
b1 -
0#
b101001001000100 *
b1 5
b1 4
#1085000
b1010011111110010010101010100111 :
1#
#1090000
0#
#1095000
b1010011111110010010101010100111 :
1#
b101011101010010 *
b1110111001100011000000011101 7
b10 6
b10 ,
#1100000
1(
b10 &
b10 /
b1110111001100011000000011101 '
b1110111001100011000000011101 0
0#
#1105000
b1110111001100011000000011101 ;
1#
#1110000
0(
b1110111001100011000000011101 !
b1110111001100011000000011101 2
b10 %
b10 .
b1110111001100011000000011101 "
b1110111001100011000000011101 1
b10 $
b10 -
0#
b101001001000100 *
b10 5
b10 4
#1115000
b1110111001100011000000011101 ;
1#
#1120000
0#
#1125000
b1110111001100011000000011101 ;
1#
b101011101010010 *
b1001110100000110001100110011101 7
b11 6
b11 ,
#1130000
1(
b11 &
b11 /
b1001110100000110001100110011101 '
b1001110100000110001100110011101 0
0#
#1135000
b1001110100000110001100110011101 <
1#
#1140000
0(
b1001110100000110001100110011101 !
b1001110100000110001100110011101 2
b11 %
b11 .
b1001110100000110001100110011101 "
b1001110100000110001100110011101 1
b11 $
b11 -
0#
b101001001000100 *
b11 5
b11 4
#1145000
b1001110100000110001100110011101 <
1#
#1150000
0#
#1155000
b1001110100000110001100110011101 <
1#
b101011101010010 *
b11111100100011001100100111111 7
b100 6
b100 ,
#1160000
1(
b100 &
b100 /
b11111100100011001100100111111 '
b11111100100011001100100111111 0
0#
#1165000
b11111100100011001100100111111 =
1#
#1170000
0(
b11111100100011001100100111111 !
b11111100100011001100100111111 2
b100 %
b100 .
b11111100100011001100100111111 "
b11111100100011001100100111111 1
b100 $
b100 -
0#
b101001001000100 *
b100 5
b100 4
#1175000
b11111100100011001100100111111 =
1#
#1180000
0#
#1185000
b11111100100011001100100111111 =
1#
b101011101010010 *
b1000101010101010010010110001010 7
b101 6
b101 ,
#1190000
1(
b101 &
b101 /
b1000101010101010010010110001010 '
b1000101010101010010010110001010 0
0#
#1195000
b1000101010101010010010110001010 >
1#
