03_riscv/core/common/riscv_configs.v
// ==================================================
//	[ VLSISYS Lab. ]
//	* Author		: Woong Choi (woongchoi@sm.ac.kr)
//	* Filename		: riscv_configs.v
//	* Description	: 
// ==================================================

// --------------------------------------------------
// Instruction opcodes
// --------------------------------------------------
`define	OPCODE_LUI			7'b0110111	//	U-Type, x[rd] = sext(imm[31:12] << 12)
`define	OPCODE_AUIPC		7'b0010111	//	U-Type, x[rd] = pc + sext(imm[31:12] << 12)
`define	OPCODE_JAL			7'b1101111	//	J-Type, x[rd] = pc + 4; pc += sext(offset)
`define	OPCODE_JALR			7'b1100111	//	J-Type, x[rd] = pc + 4; pc = (x[rs1] + sext(offset)) & ~1
`define	OPCODE_BRANCH		7'b1100011	//	B-Type, if (rs1 'op' rs2) pc += sext(offset)
`define	OPCODE_LOAD			7'b0000011	//	I-Type, x[rd] = sext(M[x[rs1] + sext(offset)][31:0])
`define	OPCODE_STORE		7'b0100011	//	S-Type, M[x[rs1] + sext(offset)] = x[rs2][31:0]
`define	OPCODE_OP_IMM		7'b0010011	//	I-Type, x[rd] = x[rs1] 'op' sext(imm)
`define	OPCODE_OP			7'b0110011	//	R-Type, x[rd] = x[rd] = x[rs1] 'op' x[rs2]
`define	OPCODE_FENCE		7'b0001111	//	I-Type, 
`define	OPCODE_SYSTEM		7'b1110011	//	I-Type, 

// --------------------------------------------------
// Result Source (Register Write Data)
// --------------------------------------------------
`define	RES_SRC_ALU   		2'b00		//	From ALU
`define	RES_SRC_DME   		2'b01		//	From Data Memory
`define	RES_SRC_PC4			2'b10		//	From PC + 4
`define	RES_SRC_NOP			2'b11		//	Don't Care

// --------------------------------------------------
//	Immidiate Generate
// --------------------------------------------------
`define	INSTR_R_TYPE		3'b000
`define	INSTR_I_TYPE		3'b001
`define	INSTR_S_TYPE		3'b010
`define	INSTR_B_TYPE		3'b011
`define	INSTR_U_TYPE		3'b100
`define	INSTR_J_TYPE		3'b101

// --------------------------------------------------
//	ALU (Arithmetic & Logical Unit)
// --------------------------------------------------
//							{funct7[5], funct3}
`define	ALU_CTRL_ADD		4'b0000
`define	ALU_CTRL_SUB		4'b1000
`define	ALU_CTRL_SLL		4'b0001	// Shift Left Logical
`define	ALU_CTRL_SLT		4'b0010	// Set on Less Than
`define	ALU_CTRL_SLTU		4'b0011	// Set on Less Than Unsigned
`define	ALU_CTRL_XOR		4'b0100
`define	ALU_CTRL_SRL		4'b0101	// Shift Right Logical / Arithmetic
`define	ALU_CTRL_SRA		4'b1101	// Shift Right Logical / Arithmetic
`define	ALU_CTRL_OR			4'b0110
`define	ALU_CTRL_AND		4'b0111
`define	ALU_CTRL_NOP		4'b1111

// --------------------------------------------------
//	ALUOP
// --------------------------------------------------
`define	ALUOP_AUIPC_LOAD_STORE	2'b00
`define	ALUOP_BRANCH			2'b01
`define	ALUOP_RTYPE_ITYPE		2'b10
`define	ALUOP_NOP				2'b11

// --------------------------------------------------
//	Memory (Instruction / Data)
// --------------------------------------------------
`define	IME_ADDR_BIT		5
`define	DME_ADDR_BIT		32
`define	IME_ADDR_BUS		`IME_ADDR_BIT-1:0
`define	DME_ADDR_BUS		`DME_ADDR_BIT-1:0
`define	IME_INIT_FILE		""
`define	DME_INIT_FILE		""

03_riscv/core/common/riscv_alu.v
// ==================================================
//	[ VLSISYS Lab. ]
//	* Author		: Woong Choi (woongchoi@sm.ac.kr)
//	* Filename		: riscv_alu.v
//	* Description	: 
// ==================================================

`include	"riscv_configs.v"

module riscv_alu
#(	
	parameter	BW_DATA	= 32,
	parameter	BW_CTRL	= 4
)
(	
	output reg	[BW_DATA-1:0]	o_alu_result,
	output						o_alu_zero,
	input		[BW_DATA-1:0]	i_alu_a,
	input		[BW_DATA-1:0]	i_alu_b,
	input		[BW_CTRL-1:0]	i_alu_ctrl
);

	always @(*) begin
		case (i_alu_ctrl)
			`ALU_CTRL_ADD	:	o_alu_result = i_alu_a +  i_alu_b;
			`ALU_CTRL_SUB	:	o_alu_result = i_alu_a -  i_alu_b;
			`ALU_CTRL_SLL	:	o_alu_result = i_alu_a << i_alu_b[4:0];
			`ALU_CTRL_SLT	:	o_alu_result = $signed(i_alu_a) < $signed(i_alu_b);
			`ALU_CTRL_SLTU	:	o_alu_result = i_alu_a <  i_alu_b;
			`ALU_CTRL_XOR	:	o_alu_result = i_alu_a ^  i_alu_b;
			`ALU_CTRL_SRL	:	o_alu_result = i_alu_a >> i_alu_b[4:0];
			`ALU_CTRL_SRA	:	o_alu_result = $signed(i_alu_a) >>> $signed(i_alu_b[4:0]);
			`ALU_CTRL_OR	:	o_alu_result = i_alu_a |  i_alu_b;
			`ALU_CTRL_AND	:	o_alu_result = i_alu_a &  i_alu_b;
		endcase
	end

	assign	o_alu_zero	= (o_alu_result == 0);

endmodule

03_riscv/core/common/riscv_alu_tb.v
// ==================================================
//	[ VLSISYS Lab. ]
//	* Author		: Woong Choi (woongchoi@sm.ac.kr)
//	* Filename		: riscv_alu_tb.v
//	* Description	: 
// ==================================================

// --------------------------------------------------
//	Define Global Variables
// --------------------------------------------------
`define	CLKFREQ		100		// Clock Freq. (Unit: MHz)
`define	SIMCYCLE	16		// Sim. Cycles

// --------------------------------------------------
//	Includes
// --------------------------------------------------
`include	"riscv_alu.v"

module	riscv_alu_tb;
// --------------------------------------------------
//	DUT Signals & Instantiate
// --------------------------------------------------
	localparam	BW_DATA			= 32;
	localparam	BW_CTRL			= 4;

	wire	[BW_DATA-1:0]		o_alu_result;
	wire						o_alu_zero;
	reg		[BW_DATA-1:0]		i_alu_a;
	reg		[BW_DATA-1:0]		i_alu_b;
	reg		[BW_CTRL-1:0]		i_alu_ctrl;

	riscv_alu
	#(
		.BW_DATA			(BW_DATA			),
		.BW_CTRL			(BW_CTRL			)
	)
	u_riscv_alu(
		.o_alu_result		(o_alu_result		),
		.o_alu_zero			(o_alu_zero			),
		.i_alu_a			(i_alu_a			),
		.i_alu_b			(i_alu_b			),
		.i_alu_ctrl			(i_alu_ctrl			)
	);
// --------------------------------------------------
//	Tasks
// --------------------------------------------------
	reg		[4*32-1:0] taskState;	// Length is limitted to 32

	task init;
		begin
			i_alu_a			= 0;
			i_alu_b			= 0;
			i_alu_ctrl		= 0;
		end
	endtask

	task ADD;
		begin
			taskState	= "ADD";
			i_alu_ctrl	= `ALU_CTRL_ADD;
			i_alu_a		= $urandom;
			i_alu_b		= $urandom;
		end
	endtask

	task SUB;
		begin
			taskState	= "SUB";
			i_alu_ctrl	= `ALU_CTRL_SUB;
			i_alu_a		= $urandom;
			i_alu_b		= $urandom;
		end
	endtask

	task SLL;
		begin
			taskState	= "SLL";
			i_alu_ctrl	= `ALU_CTRL_SLL;
			i_alu_a		= $urandom;
			i_alu_b		= $urandom;
		end
	endtask

	task SLT;
		begin
			taskState	= "SLT";
			i_alu_ctrl	= `ALU_CTRL_SLT;
			i_alu_a		= $urandom;
			i_alu_b		= $urandom;
		end
	endtask

	task SLTU;
		begin
			taskState	= "SLTU";
			i_alu_ctrl	= `ALU_CTRL_SLTU;
			i_alu_a		= $urandom;
			i_alu_b		= $urandom;
		end
	endtask

	task XOR;
		begin
			taskState	= "XOR";
			i_alu_ctrl	= `ALU_CTRL_XOR;
			i_alu_a		= $urandom;
			i_alu_b		= $urandom;
		end
	endtask

	task SRL;
		begin
			taskState	= "SRL";
			i_alu_ctrl	= `ALU_CTRL_SRL;
			i_alu_a		= $urandom;
			i_alu_b		= $urandom;
		end
	endtask

	task SRA;
		begin
			taskState	= "SRA";
			i_alu_ctrl	= `ALU_CTRL_SRA;
			i_alu_a		= $urandom;
			i_alu_b		= $urandom;
		end
	endtask

	task OR;
		begin
			taskState	= "OR";
			i_alu_ctrl	= `ALU_CTRL_OR;
			i_alu_a		= $urandom;
			i_alu_b		= $urandom;
		end
	endtask

	task AND;
		begin
			taskState	= "AND";
			i_alu_ctrl	= `ALU_CTRL_AND;
			i_alu_a		= $urandom;
			i_alu_b		= $urandom;
		end
	endtask

// --------------------------------------------------
//	Test Stimulus
// --------------------------------------------------
	integer		i, j;
	initial begin
		init();
		#(4*1000/`CLKFREQ);

		for (i=0; i<`SIMCYCLE; i++) begin
//			#(1000/`CLKFREQ)	ADD;
//			#(1000/`CLKFREQ)	SUB;
//			#(1000/`CLKFREQ)	SLL;
//			#(1000/`CLKFREQ)	SLT;
			#(1000/`CLKFREQ)	SLTU;
//			#(1000/`CLKFREQ)	XOR;
//			#(1000/`CLKFREQ)	SRL;
//			#(1000/`CLKFREQ)	SRA;
//			#(1000/`CLKFREQ)	OR;
//			#(1000/`CLKFREQ)	AND;
		end
		$finish;
	end

// --------------------------------------------------
//	Dump VCD
// --------------------------------------------------
	reg	[8*32-1:0]	vcd_file;
	initial begin
		if ($value$plusargs("vcd_file=%s", vcd_file)) begin
			$dumpfile(vcd_file);
			$dumpvars;
		end else begin
			$dumpfile("alu_tb.vcd");
			$dumpvars;
		end
	end

endmodule

03_riscv/core/common/vcd/riscv_alu.vcd
$date
	Sun May 19 21:18:29 2024
$end
$version
	Icarus Verilog
$end
$timescale
	1ps
$end
$scope module riscv_alu_tb $end
$var wire 1 ! o_alu_zero $end
$var wire 32 " o_alu_result [31:0] $end
$var reg 32 # i_alu_a [31:0] $end
$var reg 32 $ i_alu_b [31:0] $end
$var reg 4 % i_alu_ctrl [3:0] $end
$var reg 128 & taskState [127:0] $end
$var reg 256 ' vcd_file [255:0] $end
$var integer 32 ( i [31:0] $end
$scope module u_riscv_alu $end
$var wire 32 ) i_alu_a [31:0] $end
$var wire 32 * i_alu_b [31:0] $end
$var wire 4 + i_alu_ctrl [3:0] $end
$var wire 1 ! o_alu_zero $end
$var reg 32 , o_alu_result [31:0] $end
$upscope $end
$scope task ADD $end
$upscope $end
$scope task AND $end
$upscope $end
$scope task OR $end
$upscope $end
$scope task SLL $end
$upscope $end
$scope task SLT $end
$upscope $end
$scope task SLTU $end
$upscope $end
$scope task SRA $end
$upscope $end
$scope task SRL $end
$upscope $end
$scope task SUB $end
$upscope $end
$scope task XOR $end
$upscope $end
$scope task init $end
$upscope $end
$upscope $end
$enddefinitions $end
#0
$dumpvars
b0 ,
b0 +
b0 *
b0 )
bx (
b101110001011110111011001100011011001000010111101110010011010010111001101100011011101100101111101100001011011000111010100101110011101100110001101100100 '
bx &
b0 %
b0 $
b0 #
b0 "
1!
$end
#40000
b0 (
#50000
b1 (
b1000000100010010101111010000001 $
b1000000100010010101111010000001 *
b10010010000101010011010100100100 #
b10010010000101010011010100100100 )
b11 %
b11 +
b1010011010011000101010001010101 &
#60000
0!
b1 "
b1 ,
b10 (
b110001111100000101011001100011 $
b110001111100000101011001100011 *
b100100001001101011000001001 #
b100100001001101011000001001 )
#70000
b11 (
b11000110110111111001100110001101 $
b11000110110111111001100110001101 *
b10000110101110010111101100001101 #
b10000110101110010111101100001101 )
#80000
1!
b0 "
b0 ,
b100 (
b1001001101110101001000010010 $
b1001001101110101001000010010 *
b110010110000101000010001100101 #
b110010110000101000010001100101 )
#90000
0!
b1 "
b1 ,
b101 (
b10000110110101111100110100001101 $
b10000110110101111100110100001101 *
b10000000111100111110001100000001 #
b10000000111100111110001100000001 )
#100000
1!
b0 "
b0 ,
b110 (
b10011110100011011100110100111101 $
b10011110100011011100110100111101 *
b10111011001000111111000101110110 #
b10111011001000111111000101110110 )
#110000
b111 (
b11000110001011011111011110001100 $
b11000110001011011111011110001100 *
b11110110110101000101011111101101 #
b11110110110101000101011111101101 )
#120000
b1000 (
b1100011001101110010010011000110 $
b1100011001101110010010011000110 *
b11111100111111011110100111111001 #
b11111100111111011110100111111001 )
#130000
b1001 (
b1010101000100111101001010101010 $
b1010101000100111101001010101010 *
b1100010111101111000010011000101 #
b1100010111101111000010011000101 )
#140000
b1010 (
b111011110100100111001001110111 $
b111011110100100111001001110111 *
b11110010101011111111011111100101 #
b11110010101011111111011111100101 )
#150000
0!
b1 "
b1 ,
b1011 (
b11000111111011001101101110001111 $
b11000111111011001101101110001111 *
b1001001100101101011000010010 #
b1001001100101101011000010010 )
#160000
1!
b0 "
b0 ,
b1100 (
b1100111011101101001011011001110 $
b1100111011101101001011011001110 *
b11111001001100000110100111110010 #
b11111001001100000110100111110010 )
#170000
b1101 (
b1100010110010100100111011000101 $
b1100010110010100100111011000101 *
b1110100000000000111101011101000 #
b1110100000000000111101011101000 )
#180000
b1110 (
b1011110100011100010100010111101 $
b1011110100011100010100010111101 *
b10101110010110000100100101011100 #
b10101110010110000100100101011100 )
#190000
0!
b1 "
b1 ,
b1111 (
b110010101001110010011001100101 $
b110010101001110010011001100101 *
b10110101010110101100000101101 #
b10110101010110101100000101101 )
#200000
b10000 (
b10000101011100111000011100001010 $
b10000101011100111000011100001010 *
b110001111011110110001001100011 #
b110001111011110110001001100011 )
