03_riscv/core/common/riscv_configs.v
// ==================================================
//	[ VLSISYS Lab. ]
//	* Author		: Woong Choi (woongchoi@sm.ac.kr)
//	* Filename		: riscv_configs.v
//	* Description	: 
// ==================================================

// --------------------------------------------------
// Instruction opcodes
// --------------------------------------------------
`define	OPCODE_LUI			7'b0110111	//	U-Type, x[rd] = sext(imm[31:12] << 12)
`define	OPCODE_AUIPC		7'b0010111	//	U-Type, x[rd] = pc + sext(imm[31:12] << 12)
`define	OPCODE_JAL			7'b1101111	//	J-Type, x[rd] = pc + 4; pc += sext(offset)
`define	OPCODE_JALR			7'b1100111	//	J-Type, x[rd] = pc + 4; pc = (x[rs1] + sext(offset)) & ~1
`define	OPCODE_BRANCH		7'b1100011	//	B-Type, if (rs1 'op' rs2) pc += sext(offset)
`define	OPCODE_LOAD			7'b0000011	//	I-Type, x[rd] = sext(M[x[rs1] + sext(offset)][31:0])
`define	OPCODE_STORE		7'b0100011	//	S-Type, M[x[rs1] + sext(offset)] = x[rs2][31:0]
`define	OPCODE_OP_IMM		7'b0010011	//	I-Type, x[rd] = x[rs1] 'op' sext(imm)
`define	OPCODE_OP			7'b0110011	//	R-Type, x[rd] = x[rd] = x[rs1] 'op' x[rs2]
`define	OPCODE_FENCE		7'b0001111	//	I-Type, 
`define	OPCODE_SYSTEM		7'b1110011	//	I-Type, 

// --------------------------------------------------
// Result Source (Register Write Data)
// --------------------------------------------------
`define	RES_SRC_ALU   		2'b00		//	From ALU
`define	RES_SRC_DME   		2'b01		//	From Data Memory
`define	RES_SRC_PC4			2'b10		//	From PC + 4
`define	RES_SRC_NOP			2'b11		//	Don't Care

// --------------------------------------------------
//	Immidiate Generate
// --------------------------------------------------
`define	INSTR_R_TYPE		3'b000
`define	INSTR_I_TYPE		3'b001
`define	INSTR_S_TYPE		3'b010
`define	INSTR_B_TYPE		3'b011
`define	INSTR_U_TYPE		3'b100
`define	INSTR_J_TYPE		3'b101

// --------------------------------------------------
//	ALU (Arithmetic & Logical Unit)
// --------------------------------------------------
//							{funct7[5], funct3}
`define	ALU_CTRL_ADD		4'b0000
`define	ALU_CTRL_SUB		4'b1000
`define	ALU_CTRL_SLL		4'b0001	// Shift Left Logical
`define	ALU_CTRL_SLT		4'b0010	// Set on Less Than
`define	ALU_CTRL_SLTU		4'b0011	// Set on Less Than Unsigned
`define	ALU_CTRL_XOR		4'b0100
`define	ALU_CTRL_SRL		4'b0101	// Shift Right Logical / Arithmetic
`define	ALU_CTRL_SRA		4'b1101	// Shift Right Logical / Arithmetic
`define	ALU_CTRL_OR			4'b0110
`define	ALU_CTRL_AND		4'b0111
`define	ALU_CTRL_NOP		4'b1111

// --------------------------------------------------
//	ALUOP
// --------------------------------------------------
`define	ALUOP_AUIPC_LOAD_STORE	2'b00
`define	ALUOP_BRANCH			2'b01
`define	ALUOP_RTYPE_ITYPE		2'b10
`define	ALUOP_NOP				2'b11

// --------------------------------------------------
//	Memory (Instruction / Data)
// --------------------------------------------------
`define	IME_ADDR_BIT		5
`define	DME_ADDR_BIT		32
`define	IME_ADDR_BUS		`IME_ADDR_BIT-1:0
`define	DME_ADDR_BUS		`DME_ADDR_BIT-1:0
`define	IME_INIT_FILE		""
`define	DME_INIT_FILE		""

03_riscv/core/common/riscv_mem.v
// ==================================================
//	[ VLSISYS Lab. ]
//	* Author		: Woong Choi (woongchoi@sm.ac.kr)
//	* Filename		: riscv_mem.v
//	* Description	: 
// ==================================================

`ifndef	DELINC
	`include	"riscv_configs.v"
`endif

module riscv_mem
#(	
	parameter	BW_DATA			= 32,
	parameter	BW_ADDR			= 4,
	parameter	INIT_FILE		= ""
)
(	
	output		[BW_DATA-1:0]	o_mem_data,
	input		[BW_DATA-1:0]	i_mem_data,
	input		[BW_ADDR-1:0]	i_mem_addr,
	input						i_mem_wr_en,
	input						i_clk
);

	reg			[BW_DATA-1:0]	mem_arr[0:2**BW_ADDR-1];
	initial		$readmemh(INIT_FILE, mem_arr);

	assign		o_mem_data = (i_mem_wr_en) ? o_mem_data : mem_arr[i_mem_addr];

	always @(posedge i_clk) begin
		if (i_mem_wr_en) begin
			mem_arr[i_mem_addr] <= i_mem_data;
		end else begin
			mem_arr[i_mem_addr] <= mem_arr[i_mem_addr];
		end
	end

endmodule

03_riscv/core/common/riscv_mem_tb.v
// ==================================================
//	[ VLSISYS Lab. ]
//	* Author		: Woong Choi (woongchoi@sm.ac.kr)
//	* Filename		: riscv_mem_tb.v
//	* Description	: 
// ==================================================

// --------------------------------------------------
//	Define Global Variables
// --------------------------------------------------
`define	CLKFREQ		100		// Clock Freq. (Unit: MHz)
`define	SIMCYCLE	2**BW_ADDR

`include	"riscv_mem.v"

module riscv_mem_tb;
// --------------------------------------------------
//	DUT Signals & Instantiate
// --------------------------------------------------
	localparam	BW_DATA			= 32;
	localparam	BW_ADDR			= 5;

	wire	[BW_DATA-1:0]	o_mem_data;
	reg		[BW_DATA-1:0]	i_mem_data;
	reg		[BW_ADDR-1:0]	i_mem_addr;
	reg						i_mem_wr_en;
	reg						i_clk;

	riscv_mem
	#(
		.BW_DATA			(BW_DATA			),
		.BW_ADDR			(BW_ADDR			),
		.INIT_FILE			("riscv_mem.init"	)
	)
	u_riscv_mem(
		.o_mem_data			(o_mem_data			),
		.i_mem_data			(i_mem_data			),
		.i_mem_addr			(i_mem_addr			),
		.i_mem_wr_en		(i_mem_wr_en		),
		.i_clk				(i_clk				)
	);
// --------------------------------------------------
//	Clock
// --------------------------------------------------
	always	#(500/`CLKFREQ)	i_clk = ~i_clk;

// --------------------------------------------------
//	Tasks
// --------------------------------------------------
	reg		[4*32-1:0] taskState;	// Length is limitted to 32

	task init;
		begin
			i_mem_data			= 0;
			i_mem_addr			= 0;
			i_mem_wr_en			= 0;
			i_clk				= 0;
		end
	endtask

	task memWR;
		input	[BW_ADDR-1:0]	ti_mem_addr;
		input	[BW_DATA-1:0]	ti_mem_data;
		begin
			taskState	= "WR";
			@(negedge i_clk) begin
			//	$display ("==================================================");
				$display ("%8g Write (%d) @ #(%d) of ResisterFile", $time, ti_mem_data, ti_mem_addr);
				i_mem_data	= ti_mem_data;
				i_mem_addr	= ti_mem_addr;
				i_mem_wr_en	= 1;
			end
		end
	endtask

	task memRD;
		input	[BW_ADDR-1:0]	ti_mem_addr;
		begin
			taskState	= "RD";
			@(negedge i_clk) begin
				i_mem_addr	= ti_mem_addr;
				i_mem_wr_en	= 0;
			end
			@(posedge i_clk) begin
//				$display ("==================================================");
				$display ("%8g  Read (%d) @ #(%d) of ResisterFile", $time, o_mem_data, i_mem_addr);
			end
		end
	endtask

	task singleCycle;
		begin
			#(1000/`CLKFREQ);
		end
	endtask

// --------------------------------------------------
//	Test Stimulus
// --------------------------------------------------
	integer		i, j;
	initial begin
		init();

		memRD(0);
		#(1000/`CLKFREQ);
		memRD(1);
		#(1000/`CLKFREQ);
		memRD(2);
		#(1000/`CLKFREQ);
		memRD(3);
		#(1000/`CLKFREQ);
		memRD(4);
		#(1000/`CLKFREQ);
		for (i=0; i<`SIMCYCLE; i++) begin
			memWR(i, i);
			#(1000/`CLKFREQ);
		end
		for (i=0; i<`SIMCYCLE; i++) begin
			memRD(i);
			#(1000/`CLKFREQ);
		end
		for (i=0; i<`SIMCYCLE; i++) begin
			memWR(i, $urandom);
			#(1000/`CLKFREQ);
			memRD(i);
			#(1000/`CLKFREQ);
		end
		$finish;
	end

// --------------------------------------------------
//	Dump VCD
// --------------------------------------------------
	reg	[8*32-1:0]	vcd_file;
	initial begin
		if ($value$plusargs("vcd_file=%s", vcd_file)) begin
			$dumpfile(vcd_file);
			for (i=0; i<2**BW_ADDR; i++) begin
				$dumpvars(0, u_riscv_mem.mem_arr[i]);
			end
			$dumpvars;
		end else begin
			$dumpfile("riscv_mem_tb.vcd");
			$dumpvars;
		end
	end

endmodule

03_riscv/core/common/vcd/riscv_mem.vcd
$date
	Tue May 28 09:14:05 2024
$end
$version
	Icarus Verilog
$end
$timescale
	1ps
$end
$scope module riscv_mem_tb $end
$scope module u_riscv_mem $end
$var reg 32 ! \mem_arr[0] [31:0] $end
$upscope $end
$upscope $end
$scope module riscv_mem_tb $end
$scope module u_riscv_mem $end
$var reg 32 " \mem_arr[1] [31:0] $end
$upscope $end
$upscope $end
$scope module riscv_mem_tb $end
$scope module u_riscv_mem $end
$var reg 32 # \mem_arr[2] [31:0] $end
$upscope $end
$upscope $end
$scope module riscv_mem_tb $end
$scope module u_riscv_mem $end
$var reg 32 $ \mem_arr[3] [31:0] $end
$upscope $end
$upscope $end
$scope module riscv_mem_tb $end
$scope module u_riscv_mem $end
$var reg 32 % \mem_arr[4] [31:0] $end
$upscope $end
$upscope $end
$scope module riscv_mem_tb $end
$scope module u_riscv_mem $end
$var reg 32 & \mem_arr[5] [31:0] $end
$upscope $end
$upscope $end
$scope module riscv_mem_tb $end
$scope module u_riscv_mem $end
$var reg 32 ' \mem_arr[6] [31:0] $end
$upscope $end
$upscope $end
$scope module riscv_mem_tb $end
$scope module u_riscv_mem $end
$var reg 32 ( \mem_arr[7] [31:0] $end
$upscope $end
$upscope $end
$scope module riscv_mem_tb $end
$scope module u_riscv_mem $end
$var reg 32 ) \mem_arr[8] [31:0] $end
$upscope $end
$upscope $end
$scope module riscv_mem_tb $end
$scope module u_riscv_mem $end
$var reg 32 * \mem_arr[9] [31:0] $end
$upscope $end
$upscope $end
$scope module riscv_mem_tb $end
$scope module u_riscv_mem $end
$var reg 32 + \mem_arr[10] [31:0] $end
$upscope $end
$upscope $end
$scope module riscv_mem_tb $end
$scope module u_riscv_mem $end
$var reg 32 , \mem_arr[11] [31:0] $end
$upscope $end
$upscope $end
$scope module riscv_mem_tb $end
$scope module u_riscv_mem $end
$var reg 32 - \mem_arr[12] [31:0] $end
$upscope $end
$upscope $end
$scope module riscv_mem_tb $end
$scope module u_riscv_mem $end
$var reg 32 . \mem_arr[13] [31:0] $end
$upscope $end
$upscope $end
$scope module riscv_mem_tb $end
$scope module u_riscv_mem $end
$var reg 32 / \mem_arr[14] [31:0] $end
$upscope $end
$upscope $end
$scope module riscv_mem_tb $end
$scope module u_riscv_mem $end
$var reg 32 0 \mem_arr[15] [31:0] $end
$upscope $end
$upscope $end
$scope module riscv_mem_tb $end
$scope module u_riscv_mem $end
$var reg 32 1 \mem_arr[16] [31:0] $end
$upscope $end
$upscope $end
$scope module riscv_mem_tb $end
$scope module u_riscv_mem $end
$var reg 32 2 \mem_arr[17] [31:0] $end
$upscope $end
$upscope $end
$scope module riscv_mem_tb $end
$scope module u_riscv_mem $end
$var reg 32 3 \mem_arr[18] [31:0] $end
$upscope $end
$upscope $end
$scope module riscv_mem_tb $end
$scope module u_riscv_mem $end
$var reg 32 4 \mem_arr[19] [31:0] $end
$upscope $end
$upscope $end
$scope module riscv_mem_tb $end
$scope module u_riscv_mem $end
$var reg 32 5 \mem_arr[20] [31:0] $end
$upscope $end
$upscope $end
$scope module riscv_mem_tb $end
$scope module u_riscv_mem $end
$var reg 32 6 \mem_arr[21] [31:0] $end
$upscope $end
$upscope $end
$scope module riscv_mem_tb $end
$scope module u_riscv_mem $end
$var reg 32 7 \mem_arr[22] [31:0] $end
$upscope $end
$upscope $end
$scope module riscv_mem_tb $end
$scope module u_riscv_mem $end
$var reg 32 8 \mem_arr[23] [31:0] $end
$upscope $end
$upscope $end
$scope module riscv_mem_tb $end
$scope module u_riscv_mem $end
$var reg 32 9 \mem_arr[24] [31:0] $end
$upscope $end
$upscope $end
$scope module riscv_mem_tb $end
$scope module u_riscv_mem $end
$var reg 32 : \mem_arr[25] [31:0] $end
$upscope $end
$upscope $end
$scope module riscv_mem_tb $end
$scope module u_riscv_mem $end
$var reg 32 ; \mem_arr[26] [31:0] $end
$upscope $end
$upscope $end
$scope module riscv_mem_tb $end
$scope module u_riscv_mem $end
$var reg 32 < \mem_arr[27] [31:0] $end
$upscope $end
$upscope $end
$scope module riscv_mem_tb $end
$scope module u_riscv_mem $end
$var reg 32 = \mem_arr[28] [31:0] $end
$upscope $end
$upscope $end
$scope module riscv_mem_tb $end
$scope module u_riscv_mem $end
$var reg 32 > \mem_arr[29] [31:0] $end
$upscope $end
$upscope $end
$scope module riscv_mem_tb $end
$scope module u_riscv_mem $end
$var reg 32 ? \mem_arr[30] [31:0] $end
$upscope $end
$upscope $end
$scope module riscv_mem_tb $end
$scope module u_riscv_mem $end
$var reg 32 @ \mem_arr[31] [31:0] $end
$upscope $end
$upscope $end
$scope module riscv_mem_tb $end
$var wire 32 A o_mem_data [31:0] $end
$var reg 1 B i_clk $end
$var reg 5 C i_mem_addr [4:0] $end
$var reg 32 D i_mem_data [31:0] $end
$var reg 1 E i_mem_wr_en $end
$var reg 128 F taskState [127:0] $end
$var reg 256 G vcd_file [255:0] $end
$var integer 32 H i [31:0] $end
$scope module u_riscv_mem $end
$var wire 1 B i_clk $end
$var wire 5 I i_mem_addr [4:0] $end
$var wire 32 J i_mem_data [31:0] $end
$var wire 1 E i_mem_wr_en $end
$var wire 32 K o_mem_data [31:0] $end
$upscope $end
$scope task init $end
$upscope $end
$scope task memRD $end
$var reg 5 L ti_mem_addr [4:0] $end
$upscope $end
$scope task memWR $end
$var reg 5 M ti_mem_addr [4:0] $end
$var reg 32 N ti_mem_data [31:0] $end
$upscope $end
$scope task singleCycle $end
$upscope $end
$upscope $end
$enddefinitions $end
#0
$dumpvars
bx N
bx M
b0 L
b11111111110001001010001100000011 K
b0 J
b0 I
b100000 H
b101110001011110111011001100011011001000010111101110010011010010111001101100011011101100101111101101101011001010110110100101110011101100110001101100100 G
b101001001000100 F
0E
b0 D
b0 C
0B
b11111111110001001010001100000011 A
bx @
bx ?
bx >
bx =
bx <
bx ;
bx :
bx 9
bx 8
bx 7
bx 6
bx 5
bx 4
bx 3
bx 2
bx 1
bx 0
bx /
bx .
bx -
bx ,
bx +
bx *
bx )
bx (
bx '
bx &
bx %
b11111110010000100000101011100011 $
b11000101110001000110011 #
b11001001010010000100011 "
b11111111110001001010001100000011 !
$end
#5000
b11111111110001001010001100000011 !
1B
#10000
0B
#15000
b11111111110001001010001100000011 !
1B
#20000
0B
#25000
b11111111110001001010001100000011 !
1B
b1 L
#30000
b11001001010010000100011 A
b11001001010010000100011 K
b1 C
b1 I
0B
#35000
b11001001010010000100011 "
1B
#40000
0B
#45000
b11001001010010000100011 "
1B
b10 L
#50000
b11000101110001000110011 A
b11000101110001000110011 K
b10 C
b10 I
0B
#55000
b11000101110001000110011 #
1B
#60000
0B
#65000
b11000101110001000110011 #
1B
b11 L
#70000
b11111110010000100000101011100011 A
b11111110010000100000101011100011 K
b11 C
b11 I
0B
#75000
b11111110010000100000101011100011 $
1B
#80000
0B
#85000
b11111110010000100000101011100011 $
1B
b100 L
#90000
bx A
bx K
b100 C
b100 I
0B
#95000
bx %
1B
#100000
0B
#105000
bx %
1B
b101011101010010 F
b0 N
b0 M
b0 H
#110000
1E
b0 C
b0 I
0B
#115000
b0 !
1B
#120000
b1 C
b1 I
b1 D
b1 J
0B
b1 N
b1 M
b1 H
#125000
b1 "
1B
#130000
b10 C
b10 I
b10 D
b10 J
0B
b10 N
b10 M
b10 H
#135000
b10 #
1B
#140000
b11 C
b11 I
b11 D
b11 J
0B
b11 N
b11 M
b11 H
#145000
b11 $
1B
#150000
b100 C
b100 I
b100 D
b100 J
0B
b100 N
b100 M
b100 H
#155000
b100 %
1B
#160000
b101 C
b101 I
b101 D
b101 J
0B
b101 N
b101 M
b101 H
#165000
b101 &
1B
#170000
b110 C
b110 I
b110 D
b110 J
0B
b110 N
b110 M
b110 H
#175000
b110 '
1B
#180000
b111 C
b111 I
b111 D
b111 J
0B
b111 N
b111 M
b111 H
#185000
b111 (
1B
#190000
b1000 C
b1000 I
b1000 D
b1000 J
0B
b1000 N
b1000 M
b1000 H
#195000
b1000 )
1B
#200000
b1001 C
b1001 I
b1001 D
b1001 J
0B
b1001 N
b1001 M
b1001 H
#205000
b1001 *
1B
#210000
b1010 C
b1010 I
b1010 D
b1010 J
0B
b1010 N
b1010 M
b1010 H
#215000
b1010 +
1B
#220000
b1011 C
b1011 I
b1011 D
b1011 J
0B
b1011 N
b1011 M
b1011 H
#225000
b1011 ,
1B
#230000
b1100 C
b1100 I
b1100 D
b1100 J
0B
b1100 N
b1100 M
b1100 H
#235000
b1100 -
1B
#240000
b1101 C
b1101 I
b1101 D
b1101 J
0B
b1101 N
b1101 M
b1101 H
#245000
b1101 .
1B
#250000
b1110 C
b1110 I
b1110 D
b1110 J
0B
b1110 N
b1110 M
b1110 H
#255000
b1110 /
1B
#260000
b1111 C
b1111 I
b1111 D
b1111 J
0B
b1111 N
b1111 M
b1111 H
#265000
b1111 0
1B
#270000
b10000 C
b10000 I
b10000 D
b10000 J
0B
b10000 N
b10000 M
b10000 H
#275000
b10000 1
1B
#280000
b10001 C
b10001 I
b10001 D
b10001 J
0B
b10001 N
b10001 M
b10001 H
#285000
b10001 2
1B
#290000
b10010 C
b10010 I
b10010 D
b10010 J
0B
b10010 N
b10010 M
b10010 H
#295000
b10010 3
1B
#300000
b10011 C
b10011 I
b10011 D
b10011 J
0B
b10011 N
b10011 M
b10011 H
#305000
b10011 4
1B
#310000
b10100 C
b10100 I
b10100 D
b10100 J
0B
b10100 N
b10100 M
b10100 H
#315000
b10100 5
1B
#320000
b10101 C
b10101 I
b10101 D
b10101 J
0B
b10101 N
b10101 M
b10101 H
#325000
b10101 6
1B
#330000
b10110 C
b10110 I
b10110 D
b10110 J
0B
b10110 N
b10110 M
b10110 H
#335000
b10110 7
1B
#340000
b10111 C
b10111 I
b10111 D
b10111 J
0B
b10111 N
b10111 M
b10111 H
#345000
b10111 8
1B
#350000
b11000 C
b11000 I
b11000 D
b11000 J
0B
b11000 N
b11000 M
b11000 H
#355000
b11000 9
1B
#360000
b11001 C
b11001 I
b11001 D
b11001 J
0B
b11001 N
b11001 M
b11001 H
#365000
b11001 :
1B
#370000
b11010 C
b11010 I
b11010 D
b11010 J
0B
b11010 N
b11010 M
b11010 H
#375000
b11010 ;
1B
#380000
b11011 C
b11011 I
b11011 D
b11011 J
0B
b11011 N
b11011 M
b11011 H
#385000
b11011 <
1B
#390000
b11100 C
b11100 I
b11100 D
b11100 J
0B
b11100 N
b11100 M
b11100 H
#395000
b11100 =
1B
#400000
b11101 C
b11101 I
b11101 D
b11101 J
0B
b11101 N
b11101 M
b11101 H
#405000
b11101 >
1B
#410000
b11110 C
b11110 I
b11110 D
b11110 J
0B
b11110 N
b11110 M
b11110 H
#415000
b11110 ?
1B
#420000
b11111 C
b11111 I
b11111 D
b11111 J
0B
b11111 N
b11111 M
b11111 H
#425000
b11111 @
1B
#430000
b0 A
b0 K
0E
b0 C
b0 I
0B
b101001001000100 F
b0 L
b0 H
#435000
b0 !
1B
#440000
0B
#445000
b0 !
1B
b1 L
b1 H
#450000
b1 A
b1 K
b1 C
b1 I
0B
#455000
b1 "
1B
#460000
0B
#465000
b1 "
1B
b10 L
b10 H
#470000
b10 A
b10 K
b10 C
b10 I
0B
#475000
b10 #
1B
#480000
0B
#485000
b10 #
1B
b11 L
b11 H
#490000
b11 A
b11 K
b11 C
b11 I
0B
#495000
b11 $
1B
#500000
0B
#505000
b11 $
1B
b100 L
b100 H
#510000
b100 A
b100 K
b100 C
b100 I
0B
#515000
b100 %
1B
#520000
0B
#525000
b100 %
1B
b101 L
b101 H
#530000
b101 A
b101 K
b101 C
b101 I
0B
#535000
b101 &
1B
#540000
0B
#545000
b101 &
1B
b110 L
b110 H
#550000
b110 A
b110 K
b110 C
b110 I
0B
#555000
b110 '
1B
#560000
0B
#565000
b110 '
1B
b111 L
b111 H
#570000
b111 A
b111 K
b111 C
b111 I
0B
#575000
b111 (
1B
#580000
0B
#585000
b111 (
1B
b1000 L
b1000 H
#590000
b1000 A
b1000 K
b1000 C
b1000 I
0B
#595000
b1000 )
1B
#600000
0B
#605000
b1000 )
1B
b1001 L
b1001 H
#610000
b1001 A
b1001 K
b1001 C
b1001 I
0B
#615000
b1001 *
1B
#620000
0B
#625000
b1001 *
1B
b1010 L
b1010 H
#630000
b1010 A
b1010 K
b1010 C
b1010 I
0B
#635000
b1010 +
1B
#640000
0B
#645000
b1010 +
1B
b1011 L
b1011 H
#650000
b1011 A
b1011 K
b1011 C
b1011 I
0B
#655000
b1011 ,
1B
#660000
0B
#665000
b1011 ,
1B
b1100 L
b1100 H
#670000
b1100 A
b1100 K
b1100 C
b1100 I
0B
#675000
b1100 -
1B
#680000
0B
#685000
b1100 -
1B
b1101 L
b1101 H
#690000
b1101 A
b1101 K
b1101 C
b1101 I
0B
#695000
b1101 .
1B
#700000
0B
#705000
b1101 .
1B
b1110 L
b1110 H
#710000
b1110 A
b1110 K
b1110 C
b1110 I
0B
#715000
b1110 /
1B
#720000
0B
#725000
b1110 /
1B
b1111 L
b1111 H
#730000
b1111 A
b1111 K
b1111 C
b1111 I
0B
#735000
b1111 0
1B
#740000
0B
#745000
b1111 0
1B
b10000 L
b10000 H
#750000
b10000 A
b10000 K
b10000 C
b10000 I
0B
#755000
b10000 1
1B
#760000
0B
#765000
b10000 1
1B
b10001 L
b10001 H
#770000
b10001 A
b10001 K
b10001 C
b10001 I
0B
#775000
b10001 2
1B
#780000
0B
#785000
b10001 2
1B
b10010 L
b10010 H
#790000
b10010 A
b10010 K
b10010 C
b10010 I
0B
#795000
b10010 3
1B
#800000
0B
#805000
b10010 3
1B
b10011 L
b10011 H
#810000
b10011 A
b10011 K
b10011 C
b10011 I
0B
#815000
b10011 4
1B
#820000
0B
#825000
b10011 4
1B
b10100 L
b10100 H
#830000
b10100 A
b10100 K
b10100 C
b10100 I
0B
#835000
b10100 5
1B
#840000
0B
#845000
b10100 5
1B
b10101 L
b10101 H
#850000
b10101 A
b10101 K
b10101 C
b10101 I
0B
#855000
b10101 6
1B
#860000
0B
#865000
b10101 6
1B
b10110 L
b10110 H
#870000
b10110 A
b10110 K
b10110 C
b10110 I
0B
#875000
b10110 7
1B
#880000
0B
#885000
b10110 7
1B
b10111 L
b10111 H
#890000
b10111 A
b10111 K
b10111 C
b10111 I
0B
#895000
b10111 8
1B
#900000
0B
#905000
b10111 8
1B
b11000 L
b11000 H
#910000
b11000 A
b11000 K
b11000 C
b11000 I
0B
#915000
b11000 9
1B
#920000
0B
#925000
b11000 9
1B
b11001 L
b11001 H
#930000
b11001 A
b11001 K
b11001 C
b11001 I
0B
#935000
b11001 :
1B
#940000
0B
#945000
b11001 :
1B
b11010 L
b11010 H
#950000
b11010 A
b11010 K
b11010 C
b11010 I
0B
#955000
b11010 ;
1B
#960000
0B
#965000
b11010 ;
1B
b11011 L
b11011 H
#970000
b11011 A
b11011 K
b11011 C
b11011 I
0B
#975000
b11011 <
1B
#980000
0B
#985000
b11011 <
1B
b11100 L
b11100 H
#990000
b11100 A
b11100 K
b11100 C
b11100 I
0B
#995000
b11100 =
1B
#1000000
0B
#1005000
b11100 =
1B
b11101 L
b11101 H
#1010000
b11101 A
b11101 K
b11101 C
b11101 I
0B
#1015000
b11101 >
1B
#1020000
0B
#1025000
b11101 >
1B
b11110 L
b11110 H
#1030000
b11110 A
b11110 K
b11110 C
b11110 I
0B
#1035000
b11110 ?
1B
#1040000
0B
#1045000
b11110 ?
1B
b11111 L
b11111 H
#1050000
b11111 A
b11111 K
b11111 C
b11111 I
0B
#1055000
b11111 @
1B
#1060000
0B
#1065000
b11111 @
1B
b101011101010010 F
b10010010000101010011010100100100 N
b0 M
b0 H
#1070000
1E
b0 C
b0 I
b10010010000101010011010100100100 D
b10010010000101010011010100100100 J
0B
#1075000
b10010010000101010011010100100100 !
1B
#1080000
b10010010000101010011010100100100 A
b10010010000101010011010100100100 K
0E
0B
b101001001000100 F
b0 L
#1085000
b10010010000101010011010100100100 !
1B
#1090000
0B
#1095000
b10010010000101010011010100100100 !
1B
b101011101010010 F
b1000000100010010101111010000001 N
b1 M
b1 H
#1100000
1E
b1 C
b1 I
b1000000100010010101111010000001 D
b1000000100010010101111010000001 J
0B
#1105000
b1000000100010010101111010000001 "
1B
#1110000
b1000000100010010101111010000001 A
b1000000100010010101111010000001 K
0E
0B
b101001001000100 F
b1 L
#1115000
b1000000100010010101111010000001 "
1B
#1120000
0B
#1125000
b1000000100010010101111010000001 "
1B
b101011101010010 F
b100100001001101011000001001 N
b10 M
b10 H
#1130000
1E
b10 C
b10 I
b100100001001101011000001001 D
b100100001001101011000001001 J
0B
#1135000
b100100001001101011000001001 #
1B
#1140000
b100100001001101011000001001 A
b100100001001101011000001001 K
0E
0B
b101001001000100 F
b10 L
#1145000
b100100001001101011000001001 #
1B
#1150000
0B
#1155000
b100100001001101011000001001 #
1B
b101011101010010 F
b110001111100000101011001100011 N
b11 M
b11 H
#1160000
1E
b11 C
b11 I
b110001111100000101011001100011 D
b110001111100000101011001100011 J
0B
#1165000
b110001111100000101011001100011 $
1B
#1170000
b110001111100000101011001100011 A
b110001111100000101011001100011 K
0E
0B
b101001001000100 F
b11 L
#1175000
b110001111100000101011001100011 $
1B
#1180000
0B
#1185000
b110001111100000101011001100011 $
1B
b101011101010010 F
b10000110101110010111101100001101 N
b100 M
b100 H
#1190000
1E
b100 C
b100 I
b10000110101110010111101100001101 D
b10000110101110010111101100001101 J
0B
#1195000
b10000110101110010111101100001101 %
1B
#1200000
b10000110101110010111101100001101 A
b10000110101110010111101100001101 K
0E
0B
b101001001000100 F
b100 L
#1205000
b10000110101110010111101100001101 %
1B
#1210000
0B
#1215000
b10000110101110010111101100001101 %
1B
b101011101010010 F
b11000110110111111001100110001101 N
b101 M
b101 H
#1220000
1E
b101 C
b101 I
b11000110110111111001100110001101 D
b11000110110111111001100110001101 J
0B
#1225000
b11000110110111111001100110001101 &
1B
#1230000
b11000110110111111001100110001101 A
b11000110110111111001100110001101 K
0E
0B
b101001001000100 F
b101 L
#1235000
b11000110110111111001100110001101 &
1B
#1240000
0B
#1245000
b11000110110111111001100110001101 &
1B
b101011101010010 F
b110010110000101000010001100101 N
b110 M
b110 H
#1250000
1E
b110 C
b110 I
b110010110000101000010001100101 D
b110010110000101000010001100101 J
0B
#1255000
b110010110000101000010001100101 '
1B
#1260000
b110010110000101000010001100101 A
b110010110000101000010001100101 K
0E
0B
b101001001000100 F
b110 L
#1265000
b110010110000101000010001100101 '
1B
#1270000
0B
#1275000
b110010110000101000010001100101 '
1B
b101011101010010 F
b1001001101110101001000010010 N
b111 M
b111 H
#1280000
1E
b111 C
b111 I
b1001001101110101001000010010 D
b1001001101110101001000010010 J
0B
#1285000
b1001001101110101001000010010 (
1B
#1290000
b1001001101110101001000010010 A
b1001001101110101001000010010 K
0E
0B
b101001001000100 F
b111 L
#1295000
b1001001101110101001000010010 (
1B
#1300000
0B
#1305000
b1001001101110101001000010010 (
1B
b101011101010010 F
b10000000111100111110001100000001 N
b1000 M
b1000 H
#1310000
1E
b1000 C
b1000 I
b10000000111100111110001100000001 D
b10000000111100111110001100000001 J
0B
#1315000
b10000000111100111110001100000001 )
1B
#1320000
b10000000111100111110001100000001 A
b10000000111100111110001100000001 K
0E
0B
b101001001000100 F
b1000 L
#1325000
b10000000111100111110001100000001 )
1B
#1330000
0B
#1335000
b10000000111100111110001100000001 )
1B
b101011101010010 F
b10000110110101111100110100001101 N
b1001 M
b1001 H
#1340000
1E
b1001 C
b1001 I
b10000110110101111100110100001101 D
b10000110110101111100110100001101 J
0B
#1345000
b10000110110101111100110100001101 *
1B
#1350000
b10000110110101111100110100001101 A
b10000110110101111100110100001101 K
0E
0B
b101001001000100 F
b1001 L
#1355000
b10000110110101111100110100001101 *
1B
#1360000
0B
#1365000
b10000110110101111100110100001101 *
1B
b101011101010010 F
b10111011001000111111000101110110 N
b1010 M
b1010 H
#1370000
1E
b1010 C
b1010 I
b10111011001000111111000101110110 D
b10111011001000111111000101110110 J
0B
#1375000
b10111011001000111111000101110110 +
1B
#1380000
b10111011001000111111000101110110 A
b10111011001000111111000101110110 K
0E
0B
b101001001000100 F
b1010 L
#1385000
b10111011001000111111000101110110 +
1B
#1390000
0B
#1395000
b10111011001000111111000101110110 +
1B
b101011101010010 F
b10011110100011011100110100111101 N
b1011 M
b1011 H
#1400000
1E
b1011 C
b1011 I
b10011110100011011100110100111101 D
b10011110100011011100110100111101 J
0B
#1405000
b10011110100011011100110100111101 ,
1B
#1410000
b10011110100011011100110100111101 A
b10011110100011011100110100111101 K
0E
0B
b101001001000100 F
b1011 L
#1415000
b10011110100011011100110100111101 ,
1B
#1420000
0B
#1425000
b10011110100011011100110100111101 ,
1B
b101011101010010 F
b11110110110101000101011111101101 N
b1100 M
b1100 H
#1430000
1E
b1100 C
b1100 I
b11110110110101000101011111101101 D
b11110110110101000101011111101101 J
0B
#1435000
b11110110110101000101011111101101 -
1B
#1440000
b11110110110101000101011111101101 A
b11110110110101000101011111101101 K
0E
0B
b101001001000100 F
b1100 L
#1445000
b11110110110101000101011111101101 -
1B
#1450000
0B
#1455000
b11110110110101000101011111101101 -
1B
b101011101010010 F
b11000110001011011111011110001100 N
b1101 M
b1101 H
#1460000
1E
b1101 C
b1101 I
b11000110001011011111011110001100 D
b11000110001011011111011110001100 J
0B
#1465000
b11000110001011011111011110001100 .
1B
#1470000
b11000110001011011111011110001100 A
b11000110001011011111011110001100 K
0E
0B
b101001001000100 F
b1101 L
#1475000
b11000110001011011111011110001100 .
1B
#1480000
0B
#1485000
b11000110001011011111011110001100 .
1B
b101011101010010 F
b11111100111111011110100111111001 N
b1110 M
b1110 H
#1490000
1E
b1110 C
b1110 I
b11111100111111011110100111111001 D
b11111100111111011110100111111001 J
0B
#1495000
b11111100111111011110100111111001 /
1B
