01_basics/02_hierarchical_adder/adder_4bit.v
// ==================================================
//	[ VLSISYS Lab. ]
//	* Filename		: adder_4bit.v
//	* Author		: Woong Choi (woongchoi@sm.ac.kr)
//	* Description	: 
// ==================================================

module fa
(
	output				o_s,
	output			  	o_c,
	input				i_a,
	input				i_b,
	input				i_c
);

	assign	{o_c, o_s}	= i_a + i_b + i_c;

endmodule

module adder_4bit(
	output		[3:0]	o_s,
	output				o_c,
	input		[3:0]	i_a,
	input		[3:0]	i_b,
	input				i_c
);

	wire		[2:0]	carry;

	fa
	u_fa0(
		.o_s	(o_s[0]		),
		.o_c	(carry[0]	),
		.i_a	(i_a[0]		),
		.i_b	(i_b[0]		),
		.i_c	(i_c		)
	);

	fa
	u_fa1(
		.o_s	(o_s[1]		),
		.o_c	(carry[1]	),
		.i_a	(i_a[1]		),
		.i_b	(i_b[1]		),
		.i_c	(carry[0]	)
	);

	fa
	u_fa2(
		.o_s	(o_s[2]		),
		.o_c	(carry[2]	),
		.i_a	(i_a[2]		),
		.i_b	(i_b[2]		),
		.i_c	(carry[1]	)
	);

	fa
	u_fa3(
		.o_s	(o_s[3]		),
		.o_c	(o_c		),
		.i_a	(i_a[3]		),
		.i_b	(i_b[3]		),
		.i_c	(carry[2]	)
	);

endmodule

01_basics/02_hierarchical_adder/adder_4bit_tb.v
// ==================================================
//	[ VLSISYS Lab. ]
//	* Filename		: adder_4bit_tb.v
//	* Author		: Woong Choi (woongchoi@sm.ac.kr)
//	* Description	: 
// ==================================================

// --------------------------------------------------
//	Define Global Variables
// --------------------------------------------------
`define	CLKFREQ		100		// Clock Freq. (Unit: MHz)
`define	SIMCYCLE	10		// Sim. Cycles

`include	"adder_4bit.v"

module	adder_4bit_tb;
// --------------------------------------------------
//	DUT Signals & Instantiate
// --------------------------------------------------

	wire	[3:0]	o_s;
	wire			o_c;
	reg		[3:0]	i_a;
	reg		[3:0]	i_b;
	reg				i_c;

	adder_4bit
	u_adder_4bit(
		.o_s		(o_s	),
		.o_c		(o_c	),
		.i_a		(i_a	),
		.i_b		(i_b	),
		.i_c		(i_c	)
	);

// --------------------------------------------------
//	Tasks
// --------------------------------------------------
	task init;
		begin
			i_a	= 0;
			i_b	= 0;
			i_c	= 0;
		end
	endtask

// --------------------------------------------------
//	Test Stimulus
// --------------------------------------------------
	integer		i, j, k, n;
	initial begin
		for (i=0; i<`SIMCYCLE; i++) begin
			{i_a, i_b, i_c} = $urandom_range(0, 2**9-1);
			#(1000/`CLKFREQ);
		end
		$finish;
	end

// --------------------------------------------------
//	Dump VCD
// --------------------------------------------------
	reg	[8*32-1:0]	vcd_file;
	initial begin
		if ($value$plusargs("vcd_file=%s", vcd_file)) begin
			$dumpfile(vcd_file);
			$dumpvars;
		end else begin
			$dumpfile("adder_4bit_tb.vcd");
			$dumpvars;
		end

	end

endmodule

01_basics/02_hierarchical_adder/vcd/adder_4bit.vcd
$date
	Fri Jun 21 16:09:03 2024
$end
$version
	Icarus Verilog
$end
$timescale
	1ps
$end
$scope module adder_4bit_tb $end
$var wire 4 ! o_s [3:0] $end
$var wire 1 " o_c $end
$var reg 4 # i_a [3:0] $end
$var reg 4 $ i_b [3:0] $end
$var reg 1 % i_c $end
$var reg 256 & vcd_file [255:0] $end
$var integer 32 ' i [31:0] $end
$scope module u_adder_4bit $end
$var wire 4 ( i_a [3:0] $end
$var wire 4 ) i_b [3:0] $end
$var wire 1 % i_c $end
$var wire 4 * o_s [3:0] $end
$var wire 1 " o_c $end
$var wire 3 + carry [2:0] $end
$scope module u_fa0 $end
$var wire 1 , i_a $end
$var wire 1 - i_b $end
$var wire 1 % i_c $end
$var wire 1 . o_s $end
$var wire 1 / o_c $end
$upscope $end
$scope module u_fa1 $end
$var wire 1 0 i_a $end
$var wire 1 1 i_b $end
$var wire 1 2 i_c $end
$var wire 1 3 o_s $end
$var wire 1 4 o_c $end
$upscope $end
$scope module u_fa2 $end
$var wire 1 5 i_a $end
$var wire 1 6 i_b $end
$var wire 1 7 i_c $end
$var wire 1 8 o_s $end
$var wire 1 9 o_c $end
$upscope $end
$scope module u_fa3 $end
$var wire 1 : i_a $end
$var wire 1 ; i_b $end
$var wire 1 < i_c $end
$var wire 1 = o_s $end
$var wire 1 " o_c $end
$upscope $end
$upscope $end
$scope task init $end
$upscope $end
$upscope $end
$enddefinitions $end
#0
$dumpvars
1=
0<
0;
1:
09
08
07
06
05
04
13
02
11
00
0/
1.
0-
1,
b0 +
b1011 *
b10 )
b1001 (
b0 '
b10111000101111011101100110001101100100001011110110000101100100011001000110010101110010010111110011010001100010011010010111010000101110011101100110001101100100 &
0%
b10 $
b1001 #
0"
b1011 !
$end
#10000
03
18
0=
02
0,
15
0:
01
b101 !
b101 *
1.
b0 +
0/
b100 #
b100 (
b0 $
b0 )
1%
b1 '
#20000
05
16
b0 #
b0 (
b100 $
b100 )
b10 '
#30000
17
14
12
03
b11 +
1/
b101 !
b101 *
18
1,
10
1-
06
b11 #
b11 (
b1 $
b1 )
b11 '
#40000
07
13
04
0"
02
0<
0/
1=
b1111 !
b1111 *
18
b0 +
09
0,
00
1:
0-
11
16
b1000 #
b1000 (
b110 $
b110 )
b100 '
#50000
0=
1"
1<
b11 !
b11 *
08
b100 +
19
15
b1100 #
b1100 (
b101 '
#60000
18
12
17
0<
0.
1/
13
14
b110 !
b110 *
0=
0"
b11 +
09
1,
10
05
0:
06
b11 #
b11 (
b10 $
b10 )
b110 '
#70000
08
07
04
03
1=
02
0,
00
1-
01
1;
b1001 !
b1001 *
1.
b0 +
0/
b0 #
b0 (
b1001 $
b1001 )
0%
b111 '
#80000
03
02
1:
0-
0;
b1001 !
b1001 *
1.
b0 +
0/
b1000 #
b1000 (
b0 $
b0 )
1%
b1000 '
#90000
13
b1111 !
b1111 *
18
11
16
b110 $
b110 )
b1001 '
#100000
b1010 '
