01_basics/09_regfile/regfile.v
// ==================================================
//	[ VLSISYS Lab. ]
//	* Author		: Woong Choi (woongchoi@sm.ac.kr)
//	* Filename		: regfile.v
//	* Description	: 
// ==================================================

module regfile
#(	
	parameter	BW_DATA	= 32,
	parameter	BW_ADDR	= 5
)
(
	output		[BW_DATA-1:0]	o_reg_rd_data0,
	output		[BW_DATA-1:0]	o_reg_rd_data1,
	input		[BW_ADDR-1:0]	i_reg_rd_addr0,
	input		[BW_ADDR-1:0]	i_reg_rd_addr1,
	input		[BW_DATA-1:0]	i_reg_wr_data,
	input		[BW_ADDR-1:0]	i_reg_wr_addr,
	input						i_reg_wr_en,
	input						i_clk,
	input						i_rstn
);

	reg			[BW_DATA-1:0]	reg_arr[0:2**BW_ADDR-1];

	// Async. Read 
	assign		o_reg_rd_data0	= reg_arr[i_reg_rd_addr0];
	assign		o_reg_rd_data1	= reg_arr[i_reg_rd_addr1];

	integer		i;
	always @(posedge i_clk or negedge i_rstn) begin
		if(!i_rstn) begin
			for (i=0; i<2**BW_ADDR-1; i++) begin
				reg_arr[i_reg_wr_addr] <= 0;
			end
		end else begin
			//	"Write" and  "Write Address != 0"
			if (i_reg_wr_en && (i_reg_wr_addr != 0)) begin
				reg_arr[i_reg_wr_addr] <= i_reg_wr_data;
			//	Hold Data
			end else begin
				reg_arr[i_reg_wr_addr] <= reg_arr[i_reg_wr_addr];
			end
		end
	end

endmodule

01_basics/09_regfile/regfile_tb.v
// ==================================================
//	[ VLSISYS Lab. ]
//	* Author		: Woong Choi (woongchoi@sm.ac.kr)
//	* Filename		: regfile_tb.v
//	* Description	: 
// ==================================================

// --------------------------------------------------
//	Define Global Variables
// --------------------------------------------------
`define	CLKFREQ		100				// Clock Freq. (Unit: MHz)
`define	SIMCYCLE	2**BW_ADDR		// Sim. Cycles

`include	"regfile.v"

module	regfile_tb;
// --------------------------------------------------
//	DUT Signals & Instantiate
// --------------------------------------------------

	localparam	BW_DATA			= 32;
	localparam	BW_ADDR			= 4;

	wire	[BW_DATA-1:0]	o_reg_rd_data0;
	wire	[BW_DATA-1:0]	o_reg_rd_data1;
	reg		[BW_ADDR-1:0]	i_reg_rd_addr0;
	reg		[BW_ADDR-1:0]	i_reg_rd_addr1;
	reg		[BW_DATA-1:0]	i_reg_wr_data;
	reg		[BW_ADDR-1:0]	i_reg_wr_addr;
	reg						i_reg_wr_en;
	reg						i_clk;
	reg						i_rstn;

	regfile
	#(
		.BW_DATA			(BW_DATA			),
		.BW_ADDR			(BW_ADDR			)
	)
	u_regfile(
		.o_reg_rd_data0		(o_reg_rd_data0		),
		.o_reg_rd_data1		(o_reg_rd_data1		),
		.i_reg_rd_addr0		(i_reg_rd_addr0		),
		.i_reg_rd_addr1		(i_reg_rd_addr1		),
		.i_reg_wr_data		(i_reg_wr_data		),
		.i_reg_wr_addr		(i_reg_wr_addr		),
		.i_reg_wr_en		(i_reg_wr_en		),
		.i_clk				(i_clk				),
		.i_rstn				(i_rstn				)
	);
// --------------------------------------------------
//	Clock
// --------------------------------------------------
	always	#(500/`CLKFREQ)	i_clk = ~i_clk;

// --------------------------------------------------
//	Tasks
// --------------------------------------------------
	reg		[4*32-1:0] taskState;	// Length is limitted to 32

	task init;
		begin
			i_reg_rd_addr0		= 0;
			i_reg_rd_addr1		= 0;
			i_reg_wr_data		= 0;
			i_reg_wr_addr		= 0;
			i_reg_wr_en			= 0;
			i_clk				= 0;
			i_rstn				= 0;
		end
	endtask

	task resetReleaseAfterNCycles;
		input	[  9:0]		n;
		begin
			taskState	= "Reset";
			i_rstn = 1'b0;
			#(n*1000/`CLKFREQ);
			i_rstn = 1'b1;
		end
	endtask

	task regWR;
		input	[BW_ADDR-1:0]	ti_reg_wr_addr;
		input	[BW_DATA-1:0]	ti_reg_wr_data;
		begin
			taskState	= "WR";
			@(negedge i_clk) begin
			//	$display ("==================================================");
				$display ("%8g Write (%d) @ #(%d) of ResisterFile", $time, ti_reg_wr_data, ti_reg_wr_addr);
				i_reg_wr_data	= ti_reg_wr_data;
				i_reg_wr_addr	= ti_reg_wr_addr;
				i_reg_wr_en		= 1;
			end
		end
	endtask

	task regRD;
		input	[BW_ADDR-1:0]	ti_reg_rd_addr0;
		input	[BW_ADDR-1:0]	ti_reg_rd_addr1;
		begin
			taskState	= "RD";
			@(negedge i_clk) begin
				i_reg_rd_addr0	= ti_reg_rd_addr0;
				i_reg_rd_addr1	= ti_reg_rd_addr1;
				i_reg_wr_en		= 0;
			end
			@(posedge i_clk) begin
//				$display ("==================================================");
				$display ("%8g  Read (%d) @ #(%d) of ResisterFile", $time, o_reg_rd_data0, i_reg_rd_addr0);
				$display ("%8g  Read (%d) @ #(%d) of ResisterFile", $time, o_reg_rd_data1, i_reg_rd_addr1);
			end
		end
	endtask

	task singleCycle;
		begin
			#(1000/`CLKFREQ);
		end
	endtask

// --------------------------------------------------
//	Test Stimulus
// --------------------------------------------------
	integer		i, j;
	initial begin
		init();
		resetReleaseAfterNCycles(4);
		for (i=0; i<`SIMCYCLE; i++) begin
			regWR(i, i);
			singleCycle;
		end
		for (i=0; i<`SIMCYCLE; i++) begin
			regRD($urandom_range(0, 31), $urandom_range(0, 31));
			#(1000/`CLKFREQ);
		end
		resetReleaseAfterNCycles(4);
		for (i=0; i<`SIMCYCLE; i++) begin
			regWR(i, $urandom_range(0, 2**31-1));	// 2**32 is not supported
			#(1000/`CLKFREQ);
			regRD(i, i);
			#(1000/`CLKFREQ);
		end
		$finish;
	end

// --------------------------------------------------
//	Dump VCD
// --------------------------------------------------
	reg	[8*32-1:0]	vcd_file;
	initial begin
		if ($value$plusargs("vcd_file=%s", vcd_file)) begin
			$dumpfile(vcd_file);
			$dumpvars;
			for (i=0; i<2**BW_ADDR; i++) begin
				$dumpvars(0, u_regfile.reg_arr[i]);
			end
			$dumpvars;
		end else begin
			$dumpfile("regfile_tb.vcd");
			$dumpvars;
		end
	end

endmodule

01_basics/09_regfile/vcd/regfile.vcd
$date
	Wed May 22 14:58:43 2024
$end
$version
	Icarus Verilog
$end
$timescale
	1ps
$end
$scope module regfile_tb $end
$var wire 32 ! o_reg_rd_data1 [31:0] $end
$var wire 32 " o_reg_rd_data0 [31:0] $end
$var reg 1 # i_clk $end
$var reg 4 $ i_reg_rd_addr0 [3:0] $end
$var reg 4 % i_reg_rd_addr1 [3:0] $end
$var reg 4 & i_reg_wr_addr [3:0] $end
$var reg 32 ' i_reg_wr_data [31:0] $end
$var reg 1 ( i_reg_wr_en $end
$var reg 1 ) i_rstn $end
$var reg 128 * taskState [127:0] $end
$var reg 256 + vcd_file [255:0] $end
$var integer 32 , i [31:0] $end
$scope module u_regfile $end
$var wire 1 # i_clk $end
$var wire 4 - i_reg_rd_addr0 [3:0] $end
$var wire 4 . i_reg_rd_addr1 [3:0] $end
$var wire 4 / i_reg_wr_addr [3:0] $end
$var wire 32 0 i_reg_wr_data [31:0] $end
$var wire 1 ( i_reg_wr_en $end
$var wire 1 ) i_rstn $end
$var wire 32 1 o_reg_rd_data0 [31:0] $end
$var wire 32 2 o_reg_rd_data1 [31:0] $end
$var integer 32 3 i [31:0] $end
$upscope $end
$scope task init $end
$upscope $end
$scope task regRD $end
$var reg 4 4 ti_reg_rd_addr0 [3:0] $end
$var reg 4 5 ti_reg_rd_addr1 [3:0] $end
$upscope $end
$scope task regWR $end
$var reg 4 6 ti_reg_wr_addr [3:0] $end
$var reg 32 7 ti_reg_wr_data [31:0] $end
$upscope $end
$scope task resetReleaseAfterNCycles $end
$var reg 10 8 n [9:0] $end
$upscope $end
$scope task singleCycle $end
$upscope $end
$upscope $end
$scope module regfile_tb $end
$scope module u_regfile $end
$var reg 32 9 \reg_arr[0] [31:0] $end
$upscope $end
$upscope $end
$scope module regfile_tb $end
$scope module u_regfile $end
$var reg 32 : \reg_arr[1] [31:0] $end
$upscope $end
$upscope $end
$scope module regfile_tb $end
$scope module u_regfile $end
$var reg 32 ; \reg_arr[2] [31:0] $end
$upscope $end
$upscope $end
$scope module regfile_tb $end
$scope module u_regfile $end
$var reg 32 < \reg_arr[3] [31:0] $end
$upscope $end
$upscope $end
$scope module regfile_tb $end
$scope module u_regfile $end
$var reg 32 = \reg_arr[4] [31:0] $end
$upscope $end
$upscope $end
$scope module regfile_tb $end
$scope module u_regfile $end
$var reg 32 > \reg_arr[5] [31:0] $end
$upscope $end
$upscope $end
$scope module regfile_tb $end
$scope module u_regfile $end
$var reg 32 ? \reg_arr[6] [31:0] $end
$upscope $end
$upscope $end
$scope module regfile_tb $end
$scope module u_regfile $end
$var reg 32 @ \reg_arr[7] [31:0] $end
$upscope $end
$upscope $end
$scope module regfile_tb $end
$scope module u_regfile $end
$var reg 32 A \reg_arr[8] [31:0] $end
$upscope $end
$upscope $end
$scope module regfile_tb $end
$scope module u_regfile $end
$var reg 32 B \reg_arr[9] [31:0] $end
$upscope $end
$upscope $end
$scope module regfile_tb $end
$scope module u_regfile $end
$var reg 32 C \reg_arr[10] [31:0] $end
$upscope $end
$upscope $end
$scope module regfile_tb $end
$scope module u_regfile $end
$var reg 32 D \reg_arr[11] [31:0] $end
$upscope $end
$upscope $end
$scope module regfile_tb $end
$scope module u_regfile $end
$var reg 32 E \reg_arr[12] [31:0] $end
$upscope $end
$upscope $end
$scope module regfile_tb $end
$scope module u_regfile $end
$var reg 32 F \reg_arr[13] [31:0] $end
$upscope $end
$upscope $end
$scope module regfile_tb $end
$scope module u_regfile $end
$var reg 32 G \reg_arr[14] [31:0] $end
$upscope $end
$upscope $end
$scope module regfile_tb $end
$scope module u_regfile $end
$var reg 32 H \reg_arr[15] [31:0] $end
$upscope $end
$upscope $end
$scope module regfile_tb $end
$scope module u_regfile $end
$upscope $end
$scope task init $end
$upscope $end
$scope task regRD $end
$upscope $end
$scope task regWR $end
$upscope $end
$scope task resetReleaseAfterNCycles $end
$upscope $end
$scope task singleCycle $end
$upscope $end
$upscope $end
$enddefinitions $end
#0
$dumpvars
bx H
bx G
bx F
bx E
bx D
bx C
bx B
bx A
bx @
bx ?
bx >
bx =
bx <
bx ;
bx :
b0 9
b100 8
bx 7
bx 6
bx 5
bx 4
b1111 3
b0 2
b0 1
b0 0
b0 /
b0 .
b0 -
b10000 ,
b10111000101111011101100110001101100100001011110111001001100101011001110110011001101001011011000110010100101110011101100110001101100100 +
b101001001100101011100110110010101110100 *
0)
0(
b0 '
b0 &
b0 %
b0 $
0#
b0 "
b0 !
$end
#5000
b0 9
b1111 3
1#
#10000
0#
#15000
b0 9
b1111 3
1#
#20000
0#
#25000
b0 9
b1111 3
1#
#30000
0#
#35000
b0 9
b1111 3
1#
#40000
1(
0#
b101011101010010 *
b0 7
b0 6
b0 ,
1)
#45000
b0 9
1#
#50000
b1 &
b1 /
b1 '
b1 0
0#
b1 7
b1 6
b1 ,
#55000
b1 :
1#
#60000
b10 &
b10 /
b10 '
b10 0
0#
b10 7
b10 6
b10 ,
#65000
b10 ;
1#
#70000
b11 &
b11 /
b11 '
b11 0
0#
b11 7
b11 6
b11 ,
#75000
b11 <
1#
#80000
b100 &
b100 /
b100 '
b100 0
0#
b100 7
b100 6
b100 ,
#85000
b100 =
1#
#90000
b101 &
b101 /
b101 '
b101 0
0#
b101 7
b101 6
b101 ,
#95000
b101 >
1#
#100000
b110 &
b110 /
b110 '
b110 0
0#
b110 7
b110 6
b110 ,
#105000
b110 ?
1#
#110000
b111 &
b111 /
b111 '
b111 0
0#
b111 7
b111 6
b111 ,
#115000
b111 @
1#
#120000
b1000 &
b1000 /
b1000 '
b1000 0
0#
b1000 7
b1000 6
b1000 ,
#125000
b1000 A
1#
#130000
b1001 &
b1001 /
b1001 '
b1001 0
0#
b1001 7
b1001 6
b1001 ,
#135000
b1001 B
1#
#140000
b1010 &
b1010 /
b1010 '
b1010 0
0#
b1010 7
b1010 6
b1010 ,
#145000
b1010 C
1#
#150000
b1011 &
b1011 /
b1011 '
b1011 0
0#
b1011 7
b1011 6
b1011 ,
#155000
b1011 D
1#
#160000
b1100 &
b1100 /
b1100 '
b1100 0
0#
b1100 7
b1100 6
b1100 ,
#165000
b1100 E
1#
#170000
b1101 &
b1101 /
b1101 '
b1101 0
0#
b1101 7
b1101 6
b1101 ,
#175000
b1101 F
1#
#180000
b1110 &
b1110 /
b1110 '
b1110 0
0#
b1110 7
b1110 6
b1110 ,
#185000
b1110 G
1#
#190000
b1111 &
b1111 /
b1111 '
b1111 0
0#
b1111 7
b1111 6
b1111 ,
#195000
b1111 H
1#
#200000
0(
b1000 !
b1000 2
b1000 %
b1000 .
b10 "
b10 1
b10 $
b10 -
0#
b101001001000100 *
b1000 5
b10 4
b0 ,
#205000
b1111 H
1#
#210000
0#
#215000
b1111 H
1#
b110 5
b0 4
b1 ,
#220000
b110 !
b110 2
b110 %
b110 .
b0 "
b0 1
b0 $
b0 -
0#
#225000
b1111 H
1#
#230000
0#
#235000
b1111 H
1#
b1000 5
b10 ,
#240000
b1000 !
b1000 2
b1000 %
b1000 .
0#
#245000
b1111 H
1#
#250000
0#
#255000
b1111 H
1#
b1 5
b110 4
b11 ,
#260000
b1 !
b1 2
b1 %
b1 .
b110 "
b110 1
b110 $
b110 -
0#
#265000
b1111 H
1#
#270000
0#
#275000
b1111 H
1#
b0 5
b0 4
b100 ,
#280000
b0 !
b0 2
b0 %
b0 .
b0 "
b0 1
b0 $
b0 -
0#
#285000
b1111 H
1#
#290000
0#
#295000
b1111 H
1#
b11 5
b111 4
b101 ,
#300000
b11 !
b11 2
b11 %
b11 .
b111 "
b111 1
b111 $
b111 -
0#
#305000
b1111 H
1#
#310000
0#
#315000
b1111 H
1#
b1000 5
b1110 4
b110 ,
#320000
b1000 !
b1000 2
b1000 %
b1000 .
b1110 "
b1110 1
b1110 $
b1110 -
0#
#325000
b1111 H
1#
#330000
0#
#335000
b1111 H
1#
b1100 5
b1111 4
b111 ,
#340000
b1100 !
b1100 2
b1100 %
b1100 .
b1111 "
b1111 1
b1111 $
b1111 -
0#
#345000
b1111 H
1#
#350000
0#
#355000
b1111 H
1#
b1010 5
b1100 4
b1000 ,
#360000
b1010 !
b1010 2
b1010 %
b1010 .
b1100 "
b1100 1
b1100 $
b1100 -
0#
#365000
b1111 H
1#
#370000
0#
#375000
b1111 H
1#
b111 5
b1110 4
b1001 ,
#380000
b111 !
b111 2
b111 %
b111 .
b1110 "
b1110 1
b1110 $
b1110 -
0#
#385000
b1111 H
1#
#390000
0#
#395000
b1111 H
1#
b1000 5
b1 4
b1010 ,
#400000
b1000 !
b1000 2
b1000 %
b1000 .
b1 "
b1 1
b1 $
b1 -
0#
#405000
b1111 H
1#
#410000
0#
#415000
b1111 H
1#
b1100 5
b1111 4
b1011 ,
#420000
b1100 !
b1100 2
b1100 %
b1100 .
b1111 "
b1111 1
b1111 $
b1111 -
0#
#425000
b1111 H
1#
#430000
0#
#435000
b1111 H
1#
b1110 4
b1100 ,
#440000
b1110 "
b1110 1
b1110 $
b1110 -
0#
#445000
b1111 H
1#
#450000
0#
#455000
b1111 H
1#
b1011 5
b101 4
b1101 ,
#460000
b1011 !
b1011 2
b1011 %
b1011 .
b101 "
b101 1
b101 $
b101 -
0#
#465000
b1111 H
1#
#470000
0#
#475000
b1111 H
1#
b110 5
b10 4
b1110 ,
#480000
b110 !
b110 2
b110 %
b110 .
b10 "
b10 1
b10 $
b10 -
0#
#485000
b1111 H
1#
#490000
0#
#495000
b1111 H
1#
b0 5
b110 4
b1111 ,
#500000
b0 !
b0 2
b0 %
b0 .
b110 "
b110 1
b110 $
b110 -
0#
#505000
b1111 H
1#
#510000
0#
#515000
b0 H
b1111 3
1#
0)
b101001001100101011100110110010101110100 *
b10000 ,
#520000
0#
#525000
b0 H
b1111 3
1#
#530000
0#
#535000
b0 H
b1111 3
1#
#540000
0#
#545000
b0 H
b1111 3
1#
#550000
0#
#555000
b0 H
1#
b101011101010010 *
b100000000111011001000101000000 7
b0 6
b0 ,
1)
#560000
1(
b0 &
b0 /
b100000000111011001000101000000 '
b100000000111011001000101000000 0
0#
#565000
b0 9
1#
#570000
0(
b0 "
b0 1
b0 $
b0 -
0#
b101001001000100 *
b0 4
#575000
b0 9
1#
#580000
0#
#585000
b0 9
1#
b101011101010010 *
b1001000001100100001000010010000 7
b1 6
b1 ,
#590000
1(
b1 &
b1 /
b1001000001100100001000010010000 '
b1001000001100100001000010010000 0
0#
#595000
b1001000001100100001000010010000 :
1#
#600000
0(
b1001000001100100001000010010000 !
b1001000001100100001000010010000 2
b1 %
b1 .
b1001000001100100001000010010000 "
b1001000001100100001000010010000 1
b1 $
b1 -
0#
b101001001000100 *
b1 5
b1 4
#605000
b1001000001100100001000010010000 :
1#
#610000
0#
#615000
b1001000001100100001000010010000 :
1#
b101011101010010 *
b1101010101111000010001011010101 7
b10 6
b10 ,
#620000
1(
b10 &
b10 /
b1101010101111000010001011010101 '
b1101010101111000010001011010101 0
0#
#625000
b1101010101111000010001011010101 ;
1#
#630000
0(
b1101010101111000010001011010101 !
b1101010101111000010001011010101 2
b10 %
b10 .
b1101010101111000010001011010101 "
b1101010101111000010001011010101 1
b10 $
b10 -
0#
b101001001000100 *
b10 5
b10 4
#635000
b1101010101111000010001011010101 ;
1#
#640000
0#
#645000
b1101010101111000010001011010101 ;
1#
b101011101010010 *
b100111011001100110011001001110 7
b11 6
b11 ,
#650000
1(
b11 &
b11 /
b100111011001100110011001001110 '
b100111011001100110011001001110 0
0#
#655000
b100111011001100110011001001110 <
1#
#660000
0(
b100111011001100110011001001110 !
b100111011001100110011001001110 2
b11 %
b11 .
b100111011001100110011001001110 "
b100111011001100110011001001110 1
b11 $
b11 -
0#
b101001001000100 *
b11 5
b11 4
#665000
b100111011001100110011001001110 <
1#
#670000
0#
#675000
b100111011001100110011001001110 <
1#
b101011101010010 *
b100101100100000001111101001011 7
b100 6
b100 ,
#680000
1(
b100 &
b100 /
b100101100100000001111101001011 '
b100101100100000001111101001011 0
0#
#685000
b100101100100000001111101001011 =
1#
#690000
0(
b100101100100000001111101001011 !
b100101100100000001111101001011 2
b100 %
b100 .
b100101100100000001111101001011 "
b100101100100000001111101001011 1
b100 $
b100 -
0#
b101001001000100 *
b100 5
b100 4
#695000
b100101100100000001111101001011 =
1#
#700000
0#
#705000
b100101100100000001111101001011 =
1#
b101011101010010 *
b100110000011101110000001001 7
b101 6
b101 ,
#710000
1(
b101 &
b101 /
b100110000011101110000001001 '
b100110000011101110000001001 0
0#
#715000
b100110000011101110000001001 >
1#
#720000
0(
b100110000011101110000001001 !
b100110000011101110000001001 2
b101 %
b101 .
b100110000011101110000001001 "
b100110000011101110000001001 1
b101 $
b101 -
0#
b101001001000100 *
b101 5
b101 4
#725000
b100110000011101110000001001 >
1#
#730000
0#
#735000
b100110000011101110000001001 >
1#
b101011101010010 *
b11010111100001110000000110 7
b110 6
b110 ,
#740000
1(
b110 &
b110 /
b11010111100001110000000110 '
b11010111100001110000000110 0
0#
#745000
b11010111100001110000000110 ?
1#
#750000
0(
b11010111100001110000000110 !
b11010111100001110000000110 2
b110 %
b110 .
b11010111100001110000000110 "
b11010111100001110000000110 1
b110 $
b110 -
0#
b101001001000100 *
b110 5
b110 4
#755000
b11010111100001110000000110 ?
1#
#760000
0#
#765000
b11010111100001110000000110 ?
1#
b101011101010010 *
b10100110100111110101100101001 7
b111 6
b111 ,
#770000
1(
b111 &
b111 /
b10100110100111110101100101001 '
b10100110100111110101100101001 0
0#
#775000
b10100110100111110101100101001 @
1#
#780000
0(
b10100110100111110101100101001 !
b10100110100111110101100101001 2
b111 %
b111 .
b10100110100111110101100101001 "
b10100110100111110101100101001 1
b111 $
b111 -
0#
b101001001000100 *
b111 5
b111 4
#785000
b10100110100111110101100101001 @
1#
#790000
0#
#795000
b10100110100111110101100101001 @
1#
b101011101010010 *
b1011010110011111110111010110101 7
b1000 6
b1000 ,
#800000
1(
b1000 &
b1000 /
b1011010110011111110111010110101 '
b1011010110011111110111010110101 0
0#
#805000
b1011010110011111110111010110101 A
1#
#810000
0(
b1011010110011111110111010110101 !
b1011010110011111110111010110101 2
b1000 %
b1000 .
b1011010110011111110111010110101 "
b1011010110011111110111010110101 1
b1000 $
b1000 -
0#
b101001001000100 *
b1000 5
b1000 4
#815000
b1011010110011111110111010110101 A
1#
#820000
0#
#825000
b1011010110011111110111010110101 A
1#
b101011101010010 *
b110101010100110001010101101010 7
b1001 6
b1001 ,
#830000
1(
b1001 &
b1001 /
b110101010100110001010101101010 '
b110101010100110001010101101010 0
0#
#835000
b110101010100110001010101101010 B
1#
#840000
0(
b110101010100110001010101101010 !
b110101010100110001010101101010 2
b1001 %
b1001 .
b110101010100110001010101101010 "
b110101010100110001010101101010 1
b1001 $
b1001 -
0#
b101001001000100 *
b1001 5
b1001 4
#845000
b110101010100110001010101101010 B
1#
#850000
0#
#855000
b110101010100110001010101101010 B
1#
b101011101010010 *
b100010111010010100000001 7
b1010 6
b1010 ,
#860000
1(
b1010 &
b1010 /
b100010111010010100000001 '
b100010111010010100000001 0
0#
#865000
b100010111010010100000001 C
1#
#870000
0(
b100010111010010100000001 !
b100010111010010100000001 2
b1010 %
b1010 .
b100010111010010100000001 "
b100010111010010100000001 1
b1010 $
b1010 -
0#
b101001001000100 *
b1010 5
b1010 4
#875000
b100010111010010100000001 C
1#
#880000
0#
#885000
b100010111010010100000001 C
1#
b101011101010010 *
b101011101010110001111101010111 7
b1011 6
b1011 ,
#890000
1(
b1011 &
b1011 /
b101011101010110001111101010111 '
b101011101010110001111101010111 0
0#
#895000
b101011101010110001111101010111 D
1#
#900000
0(
b101011101010110001111101010111 !
b101011101010110001111101010111 2
b1011 %
b1011 .
b101011101010110001111101010111 "
b101011101010110001111101010111 1
b1011 $
b1011 -
0#
b101001001000100 *
b1011 5
b1011 4
#905000
b101011101010110001111101010111 D
1#
#910000
0#
#915000
b101011101010110001111101010111 D
1#
b101011101010010 *
b1000111011111111111010010001110 7
b1100 6
b1100 ,
#920000
1(
b1100 &
b1100 /
b1000111011111111111010010001110 '
b1000111011111111111010010001110 0
0#
#925000
b1000111011111111111010010001110 E
1#
#930000
0(
b1000111011111111111010010001110 !
b1000111011111111111010010001110 2
b1100 %
b1100 .
b1000111011111111111010010001110 "
b1000111011111111111010010001110 1
b1100 $
b1100 -
0#
b101001001000100 *
b1100 5
b1100 4
#935000
b1000111011111111111010010001110 E
1#
#940000
0#
#945000
b1000111011111111111010010001110 E
1#
b101011101010010 *
b110011111000101011100101100111 7
b1101 6
b1101 ,
#950000
1(
b1101 &
b1101 /
b110011111000101011100101100111 '
b110011111000101011100101100111 0
0#
#955000
b110011111000101011100101100111 F
1#
#960000
0(
b110011111000101011100101100111 !
b110011111000101011100101100111 2
b1101 %
b1101 .
b110011111000101011100101100111 "
b110011111000101011100101100111 1
b1101 $
b1101 -
0#
b101001001000100 *
b1101 5
b1101 4
#965000
b110011111000101011100101100111 F
1#
#970000
0#
#975000
b110011111000101011100101100111 F
1#
b101011101010010 *
b1001000110000100010010010010001 7
b1110 6
b1110 ,
#980000
1(
b1110 &
b1110 /
b1001000110000100010010010010001 '
b1001000110000100010010010010001 0
0#
#985000
b1001000110000100010010010010001 G
1#
#990000
0(
b1001000110000100010010010010001 !
b1001000110000100010010010010001 2
b1110 %
b1110 .
b1001000110000100010010010010001 "
b1001000110000100010010010010001 1
b1110 $
b1110 -
0#
b101001001000100 *
b1110 5
b1110 4
#995000
b1001000110000100010010010010001 G
1#
#1000000
0#
#1005000
b1001000110000100010010010010001 G
1#
b101011101010010 *
b1000010100001001011001010000101 7
b1111 6
b1111 ,
#1010000
1(
b1111 &
b1111 /
b1000010100001001011001010000101 '
b1000010100001001011001010000101 0
0#
#1015000
b1000010100001001011001010000101 H
1#
#1020000
0(
b1000010100001001011001010000101 !
b1000010100001001011001010000101 2
b1111 %
b1111 .
b1000010100001001011001010000101 "
b1000010100001001011001010000101 1
b1111 $
b1111 -
0#
b101001001000100 *
b1111 5
b1111 4
#1025000
b1000010100001001011001010000101 H
1#
#1030000
0#
#1035000
b1000010100001001011001010000101 H
1#
b10000 ,
