zaram_training_course/03_sequential/fsm_seq_detector/fsm_moore.v
// ==================================================
//	[ VLSISYS Lab. ]
//	* Author		: Woong Choi (woongchoi@sm.ac.kr)
//	* Filename		: fsm_moore.v
//	* Date			: 2024-06-24 16:18:38
//	* Description	: '1011' sequence detector
// ==================================================

module fsm_moore
(	
	output reg	o_out,
	input		i_seq,
	input		i_clk,
	input		i_rstn
);

	localparam	S_IDLE = 3'b000;
	localparam	S_H    = 3'b001;
	localparam	S_HL   = 3'b010;
	localparam	S_HLH  = 3'b011;
	localparam	S_HLHH = 3'b100;

	reg	[2:0]	cState;
	reg	[2:0]	nState;

	reg			seq;

	//	State Register
	always @(posedge i_clk or negedge i_rstn) begin
		if(!i_rstn) begin
			cState	<= 0;
			seq		<= 0;
		end else begin
			cState	<= nState;
			seq		<= i_seq;
		end
	end

	//	Next State Logic
	always @(*) begin
		if(seq==1'b0) begin
			case(cState)
				S_IDLE	:	nState	= S_IDLE;
				S_H		:	nState	= S_HL;
				S_HL	:	nState	= S_IDLE;
				S_HLH	:	nState	= S_HL;
				S_HLHH	:	nState	= S_IDLE;
			endcase
		end else begin
			case(cState)
				S_IDLE	:	nState	= S_H;
				S_H		:	nState	= S_H;
				S_HL	:	nState	= S_HLH;
				S_HLH	:	nState	= S_HLHH;
				S_HLHH	:	nState	= S_H;
			endcase
		end
	end

	//	Output Logic
	always @(*) begin
		case(cState)
			S_HLHH	:	o_out	= 1'b1;
			default	:	o_out	= 1'b0;
		endcase
	end

	`ifdef	DEBUG
		reg	[32*8-1:0]	stateMonitor;
		always @(*) begin
			case(cState)
				S_IDLE	:	stateMonitor	= "S_IDLE";
				S_H		:	stateMonitor	= "S_H";
				S_HL	:	stateMonitor	= "S_HL";
				S_HLH	:	stateMonitor	= "S_HLH";
				S_HLHH	:	stateMonitor	= "S_HLHH";
			endcase
		end
	`endif

endmodule

zaram_training_course/03_sequential/fsm_seq_detector/fsm_moore_tb.v
// ==================================================
//	[ VLSISYS Lab. ]
//	* Author		: Woong Choi (woongchoi@sm.ac.kr)
//	* Filename		: fsm_moore_tb.v
//	* Date			: 2024-06-24 16:26:19
//	* Description	: 
// ==================================================

// --------------------------------------------------
//	Define Global Variables
// --------------------------------------------------
`define	CLKFREQ		100		// Clock Freq. (Unit: MHz)
`define	SIMCYCLE	`NVEC	// Sim. Cycles
`define BW_DATA		32		// Bitwidth of ~~
`define BW_ADDR		5		// Bitwidth of ~~
`define BW_CTRL		4		// Bitwidth of ~~
`define NVEC		100		// # of Test Vector
`define DEBUG

// --------------------------------------------------
//	Includes
// --------------------------------------------------
`include	"fsm_moore.v"

module fsm_moore_tb;
// --------------------------------------------------
//	DUT Signals & Instantiate
// --------------------------------------------------
	wire	o_out;
	reg		i_seq;
	reg		i_clk;
	reg		i_rstn;

	fsm_moore
	u_fsm_moore(
		.o_out				(o_out				),
		.i_seq				(i_seq				),
		.i_clk				(i_clk				),
		.i_rstn				(i_rstn				)
	);

// --------------------------------------------------
//	Clock
// --------------------------------------------------
	always	#(500/`CLKFREQ)	i_clk	= ~i_clk;

// --------------------------------------------------
//	Tasks
// --------------------------------------------------
	reg		[8*16-1:0]	taskState;

	task	init;
		begin
			taskState	= "Init";
			i_seq		= 0;
			i_clk		= 0;
			i_rstn		= 0;
		end
	endtask

	task	resetNCycle;
		input	[31:0]	i;
		begin
			taskState	= "Reset_On";
			#(i*1000/`CLKFREQ);
			taskState	= "Reset_Off";
			i_rstn		= 1;
		end
	endtask

// --------------------------------------------------
//	Test Stimulus
// --------------------------------------------------
	integer		i, j;
	initial begin
		init();
		resetNCycle(4);

		for (i=0; i<`SIMCYCLE; i++) begin
			i_seq	= $urandom;
			#(1000/`CLKFREQ);
		end
		#(1000/`CLKFREQ);
		$finish;
	end

// --------------------------------------------------
//	Dump VCD
// --------------------------------------------------
	reg	[8*32-1:0]	vcd_file;
	initial begin
		if ($value$plusargs("vcd_file=%s", vcd_file)) begin
			$dumpfile(vcd_file);
			$dumpvars;
		end else begin
			$dumpfile("fsm_moore_tb.vcd");
			$dumpvars;
		end
	end

endmodule

zaram_training_course/03_sequential/fsm_seq_detector/vcd/fsm_moore.vcd
$date
	Mon Jun 24 16:32:39 2024
$end
$version
	Icarus Verilog
$end
$timescale
	1ps
$end
$scope module fsm_moore_tb $end
$var wire 1 ! o_out $end
$var reg 1 " i_clk $end
$var reg 1 # i_rstn $end
$var reg 1 $ i_seq $end
$var reg 128 % taskState [127:0] $end
$var reg 256 & vcd_file [255:0] $end
$var integer 32 ' i [31:0] $end
$scope module u_fsm_moore $end
$var wire 1 " i_clk $end
$var wire 1 # i_rstn $end
$var wire 1 $ i_seq $end
$var reg 3 ( cState [2:0] $end
$var reg 3 ) nState [2:0] $end
$var reg 1 ! o_out $end
$var reg 1 * seq $end
$var reg 32 + stateMonitor [31:0] $end
$upscope $end
$scope task init $end
$upscope $end
$scope task resetNCycle $end
$var reg 32 , i [31:0] $end
$upscope $end
$upscope $end
$enddefinitions $end
#0
$dumpvars
b100 ,
b1001001010001000100110001000101 +
0*
b0 )
b0 (
bx '
b101110001011110111011001100011011001000010111101100110011100110110110101011111011011010110111101101111011100100110010100101110011101100110001101100100 &
b101001001100101011100110110010101110100010111110100111101101110 %
0$
0#
0"
0!
$end
#5000
1"
#10000
0"
#15000
1"
#20000
0"
#25000
1"
#30000
0"
#35000
1"
#40000
0"
b0 '
1#
b10100100110010101110011011001010111010001011111010011110110011001100110 %
#45000
1"
#50000
0"
1$
b1 '
#55000
b1 )
1*
1"
#60000
0"
b10 '
#65000
b10100110101111101001000 +
b1 (
1"
#70000
0"
b11 '
#75000
1"
#80000
0"
b100 '
#85000
1"
#90000
0"
b101 '
#95000
1"
#100000
0"
b110 '
#105000
1"
#110000
0"
0$
b111 '
#115000
b10 )
0*
1"
#120000
0"
1$
b1000 '
#125000
b1010011010111110100100001001100 +
b11 )
1*
b10 (
1"
#130000
0"
b1001 '
#135000
b1011111010010000100110001001000 +
b100 )
b11 (
1"
#140000
0"
0$
b1010 '
#145000
b1001000010011000100100001001000 +
1!
b0 )
0*
b100 (
1"
#150000
0"
1$
b1011 '
#155000
0!
b1001001010001000100110001000101 +
b1 )
1*
b0 (
1"
#160000
0"
b1100 '
#165000
b10100110101111101001000 +
b1 (
1"
#170000
0"
0$
b1101 '
#175000
b10 )
0*
1"
#180000
0"
1$
b1110 '
#185000
b1010011010111110100100001001100 +
b11 )
1*
b10 (
1"
#190000
0"
0$
b1111 '
#195000
b1011111010010000100110001001000 +
b10 )
0*
b11 (
1"
#200000
0"
1$
b10000 '
#205000
b1010011010111110100100001001100 +
b11 )
1*
b10 (
1"
#210000
0"
0$
b10001 '
#215000
b1011111010010000100110001001000 +
b10 )
0*
b11 (
1"
#220000
0"
1$
b10010 '
#225000
b1010011010111110100100001001100 +
b11 )
1*
b10 (
1"
#230000
0"
b10011 '
#235000
b1011111010010000100110001001000 +
b100 )
b11 (
1"
#240000
0"
0$
b10100 '
#245000
1!
b1001000010011000100100001001000 +
b0 )
0*
b100 (
1"
#250000
0"
1$
b10101 '
#255000
b1001001010001000100110001000101 +
0!
b1 )
1*
b0 (
1"
#260000
0"
0$
b10110 '
#265000
b10100110101111101001000 +
b10 )
0*
b1 (
1"
#270000
0"
b10111 '
#275000
b1010011010111110100100001001100 +
b0 )
b10 (
1"
#280000
0"
b11000 '
#285000
b1001001010001000100110001000101 +
b0 (
1"
#290000
0"
1$
b11001 '
#295000
b1 )
1*
1"
#300000
0"
0$
b11010 '
#305000
b10100110101111101001000 +
b10 )
0*
b1 (
1"
#310000
0"
1$
b11011 '
#315000
b1010011010111110100100001001100 +
b11 )
1*
b10 (
1"
#320000
0"
b11100 '
#325000
b1011111010010000100110001001000 +
b100 )
b11 (
1"
#330000
0"
b11101 '
#335000
1!
b1001000010011000100100001001000 +
b1 )
b100 (
1"
#340000
0"
b11110 '
#345000
b10100110101111101001000 +
0!
b1 (
1"
#350000
0"
0$
b11111 '
#355000
b10 )
0*
1"
#360000
0"
b100000 '
#365000
b1010011010111110100100001001100 +
b0 )
b10 (
1"
#370000
0"
b100001 '
#375000
b1001001010001000100110001000101 +
b0 (
1"
#380000
0"
b100010 '
#385000
1"
#390000
0"
1$
b100011 '
#395000
b1 )
1*
1"
#400000
0"
0$
b100100 '
#405000
b10100110101111101001000 +
b10 )
0*
b1 (
1"
#410000
0"
1$
b100101 '
#415000
b1010011010111110100100001001100 +
b11 )
1*
b10 (
1"
#420000
0"
b100110 '
#425000
b1011111010010000100110001001000 +
b100 )
b11 (
1"
#430000
0"
b100111 '
#435000
b1001000010011000100100001001000 +
1!
b1 )
b100 (
1"
#440000
0"
b101000 '
#445000
0!
b10100110101111101001000 +
b1 (
1"
#450000
0"
b101001 '
#455000
1"
#460000
0"
0$
b101010 '
#465000
b10 )
0*
1"
#470000
0"
b101011 '
#475000
b1010011010111110100100001001100 +
b0 )
b10 (
1"
#480000
0"
1$
b101100 '
#485000
b1001001010001000100110001000101 +
b1 )
1*
b0 (
1"
#490000
0"
b101101 '
#495000
b10100110101111101001000 +
b1 (
1"
#500000
0"
b101110 '
#505000
1"
#510000
0"
0$
b101111 '
#515000
b10 )
0*
1"
#520000
0"
b110000 '
#525000
b1010011010111110100100001001100 +
b0 )
b10 (
1"
#530000
0"
b110001 '
#535000
b1001001010001000100110001000101 +
b0 (
1"
#540000
0"
b110010 '
#545000
1"
#550000
0"
b110011 '
#555000
1"
#560000
0"
1$
b110100 '
#565000
b1 )
1*
1"
#570000
0"
0$
b110101 '
#575000
b10100110101111101001000 +
b10 )
0*
b1 (
1"
#580000
0"
b110110 '
#585000
b1010011010111110100100001001100 +
b0 )
b10 (
1"
#590000
0"
1$
b110111 '
#595000
b1001001010001000100110001000101 +
b1 )
1*
b0 (
1"
#600000
0"
b111000 '
#605000
b10100110101111101001000 +
b1 (
1"
#610000
0"
0$
b111001 '
#615000
b10 )
0*
1"
#620000
0"
b111010 '
#625000
b1010011010111110100100001001100 +
b0 )
b10 (
1"
#630000
0"
b111011 '
#635000
b1001001010001000100110001000101 +
b0 (
1"
#640000
0"
b111100 '
#645000
1"
#650000
0"
b111101 '
#655000
1"
#660000
0"
1$
b111110 '
#665000
b1 )
1*
1"
#670000
0"
b111111 '
#675000
b10100110101111101001000 +
b1 (
1"
#680000
0"
b1000000 '
#685000
1"
#690000
0"
b1000001 '
#695000
1"
#700000
0"
b1000010 '
#705000
1"
#710000
0"
0$
b1000011 '
#715000
b10 )
0*
1"
#720000
0"
b1000100 '
#725000
b1010011010111110100100001001100 +
b0 )
b10 (
1"
#730000
0"
1$
b1000101 '
#735000
b1001001010001000100110001000101 +
b1 )
1*
b0 (
1"
#740000
0"
b1000110 '
#745000
b10100110101111101001000 +
b1 (
1"
#750000
0"
b1000111 '
#755000
1"
#760000
0"
0$
b1001000 '
#765000
b10 )
0*
1"
#770000
0"
b1001001 '
#775000
b1010011010111110100100001001100 +
b0 )
b10 (
1"
#780000
0"
1$
b1001010 '
#785000
b1001001010001000100110001000101 +
b1 )
1*
b0 (
1"
#790000
0"
b1001011 '
#795000
b10100110101111101001000 +
b1 (
1"
#800000
0"
0$
b1001100 '
#805000
b10 )
0*
1"
#810000
0"
1$
b1001101 '
#815000
b1010011010111110100100001001100 +
b11 )
1*
b10 (
1"
#820000
0"
b1001110 '
#825000
b1011111010010000100110001001000 +
b100 )
b11 (
1"
#830000
0"
0$
b1001111 '
#835000
b1001000010011000100100001001000 +
1!
b0 )
0*
b100 (
1"
#840000
0"
1$
b1010000 '
#845000
0!
b1001001010001000100110001000101 +
b1 )
1*
b0 (
1"
#850000
0"
b1010001 '
#855000
b10100110101111101001000 +
b1 (
1"
#860000
0"
b1010010 '
#865000
1"
#870000
0"
0$
b1010011 '
#875000
b10 )
0*
1"
#880000
0"
1$
b1010100 '
#885000
b1010011010111110100100001001100 +
b11 )
1*
b10 (
1"
#890000
0"
b1010101 '
#895000
b1011111010010000100110001001000 +
b100 )
b11 (
1"
#900000
0"
0$
b1010110 '
#905000
1!
b1001000010011000100100001001000 +
b0 )
0*
b100 (
1"
#910000
0"
b1010111 '
#915000
b1001001010001000100110001000101 +
0!
b0 (
1"
#920000
0"
b1011000 '
#925000
1"
#930000
0"
b1011001 '
#935000
1"
#940000
0"
1$
b1011010 '
#945000
b1 )
1*
1"
#950000
0"
b1011011 '
#955000
b10100110101111101001000 +
b1 (
1"
#960000
0"
0$
b1011100 '
#965000
b10 )
0*
1"
#970000
0"
b1011101 '
#975000
b1010011010111110100100001001100 +
b0 )
b10 (
1"
#980000
0"
1$
b1011110 '
#985000
b1001001010001000100110001000101 +
b1 )
1*
b0 (
1"
#990000
0"
b1011111 '
#995000
b10100110101111101001000 +
b1 (
1"
#1000000
0"
b1100000 '
#1005000
1"
#1010000
0"
b1100001 '
#1015000
1"
#1020000
0"
b1100010 '
#1025000
1"
#1030000
0"
0$
b1100011 '
#1035000
b10 )
0*
1"
#1040000
0"
b1100100 '
#1045000
b1010011010111110100100001001100 +
b0 )
b10 (
1"
