01_basics/08_sram/spsram.v
// ==================================================
//	[ VLSISYS Lab. ]
//	* Author		: Woong Choi (woongchoi@sm.ac.kr)
//	* Filename		: spsram.v
//	* Date			: 2024-05-15 22:06:21
//	* Description	: 
// ==================================================


module spsram
#(	
	parameter	BW_DATA	= 32,
	parameter	BW_ADDR	= 5
)
(	
	output		[BW_DATA-1:0]	o_data,
	input		[BW_DATA-1:0]	i_data,
	input		[BW_ADDR-1:0]	i_addr,
	input						i_wen,
	input						i_cen,
	input						i_oen,
	input						i_clk
);
	
	//	Memory Write
	reg		[BW_DATA-1:0]	mem[0:2**BW_ADDR-1];
	always @(posedge i_clk) begin
		if(i_cen && i_wen) begin
			mem[i_addr]	<= i_data;
		end else begin
			mem[i_addr]	<= mem[i_addr];
		end
	end

	`ifdef	SPSRAM_ASYNC
		assign	o_data	= (!i_cen && i_wen && !i_oen) ? mem[i_addr] : 'bz;

	`else
		reg		[BW_DATA-1:0]	o_data;
		always @(posedge i_clk) begin
			if(i_cen && !i_wen && i_oen) begin
				o_data	<= mem[i_addr];
			end else begin
				o_data	<= mem[i_addr];
			end
		end
	`endif

endmodule

01_basics/08_sram/spsram_tb.v
// ==================================================
//	[ VLSISYS Lab. ]
//	* Author		: Woong Choi (woongchoi@sm.ac.kr)
//	* Filename		: spsram_tb.v
//	* Date			: 2024-05-16 00:08:06
//	* Description	: 
// ==================================================

// --------------------------------------------------
//	Define Global Variables
// --------------------------------------------------
`define	CLKFREQ		100		// Clock Freq. (Unit: MHz)
`define	SIMCYCLE	32		// Sim. Cycles
`define BW_DATA		32
`define BW_ADDR		5
`define BW_CTRL		4

//`define	SPSRAM_ASYNC

// --------------------------------------------------
//	Includes
// --------------------------------------------------
`include	"spsram.v"

module	spsram_tb;
// --------------------------------------------------
//	DUT Signals & Instantiate
// --------------------------------------------------
	wire	[`BW_DATA-1:0]	o_data;
	reg		[`BW_DATA-1:0]	i_data;
	reg		[`BW_ADDR-1:0]	i_addr;
	reg						i_wen;
	reg						i_cen;
	reg						i_oen;
	reg						i_clk;

	spsram
	#(
		.BW_DATA		(`BW_DATA		),
		.BW_ADDR		(`BW_ADDR		)
	)
	u_spsram(
		.o_data			(o_data			),
		.i_data			(i_data			),
		.i_addr			(i_addr			),
		.i_wen			(i_wen			),
		.i_cen			(i_cen			),
		.i_oen			(i_oen			),
		.i_clk			(i_clk			)
	);

// --------------------------------------------------
//	Clock
// --------------------------------------------------
//	reg							i_clk = 0;
	always	#(500/`CLKFREQ)		i_clk = ~i_clk;

// --------------------------------------------------
//	Tasks
// --------------------------------------------------
	reg		[4*32-1:0] taskState;	// Length of Text is limitted to 32

	task init;
		begin
			i_data	= 0;
			i_addr	= 0;
			i_wen	= 0;
			i_cen	= 0;
			i_oen	= 0;
			i_clk	= 0;
		end
	endtask

	task memWR;
		input	[`BW_ADDR-1:0]	ti_addr;
		input	[`BW_DATA-1:0]	ti_data;
		begin
			taskState	= "WR";
			@(negedge i_clk) begin
				$display ("%8g Write (%d) @ #(%d) of ResisterFile", $time, ti_data, ti_addr);
				i_data	= ti_data;
				i_addr	= ti_addr;
				i_wen	= 1;
				i_cen	= 1;
				i_oen	= 0;
			end
		end
	endtask

	task memRD;
		input	[`BW_ADDR-1:0]	ti_addr;
		begin
			taskState	= "RD";
			@(negedge i_clk) begin
				i_addr	= ti_addr;
				i_wen	= 0;
				i_cen	= 1;
				i_oen	= 1;
			end
			@(posedge i_clk) begin
				$display ("%8g  Read (%d) @ #(%d) of ResisterFile", $time, o_data, i_addr);
			end
		end
	endtask

// --------------------------------------------------
//	Test Stimulus
// --------------------------------------------------
	integer		i, j;
	initial begin
		init();
		#(4*1000/`CLKFREQ);

		for (i=0; i<`SIMCYCLE; i++) begin
			#(1000/`CLKFREQ)	memWR(i, i);
		end
		for (i=0; i<`SIMCYCLE; i++) begin
			#(1000/`CLKFREQ)	memRD(i);
		end
		$finish;
	end

// --------------------------------------------------
//	Dump VCD
// --------------------------------------------------
	reg	[8*32-1:0]	vcd_file;
	initial begin
		if ($value$plusargs("vcd_file=%s", vcd_file)) begin
			$dumpfile(vcd_file);
			$dumpvars;
		end else begin
			$dumpfile("spsram_tb.vcd");
			$dumpvars;
		end
	end

endmodule

01_basics/08_sram/vcd/spsram.vcd
$date
	Thu May 16 00:23:00 2024
$end
$version
	Icarus Verilog
$end
$timescale
	1ps
$end
$scope module spsram_tb $end
$var wire 32 ! o_data [31:0] $end
$var reg 5 " i_addr [4:0] $end
$var reg 1 # i_cen $end
$var reg 1 $ i_clk $end
$var reg 32 % i_data [31:0] $end
$var reg 1 & i_oen $end
$var reg 1 ' i_wen $end
$var reg 128 ( taskState [127:0] $end
$var reg 256 ) vcd_file [255:0] $end
$var integer 32 * i [31:0] $end
$scope module u_spsram $end
$var wire 5 + i_addr [4:0] $end
$var wire 1 # i_cen $end
$var wire 1 $ i_clk $end
$var wire 32 , i_data [31:0] $end
$var wire 1 & i_oen $end
$var wire 1 ' i_wen $end
$var reg 32 - o_data [31:0] $end
$upscope $end
$scope task init $end
$upscope $end
$scope task memRD $end
$var reg 5 . ti_addr [4:0] $end
$upscope $end
$scope task memWR $end
$var reg 5 / ti_addr [4:0] $end
$var reg 32 0 ti_data [31:0] $end
$upscope $end
$upscope $end
$enddefinitions $end
#0
$dumpvars
bx 0
bx /
bx .
bx -
b0 ,
b0 +
bx *
b101110001011110111011001100011011001000010111101110011011100000111001101110010011000010110110100101110011101100110001101100100 )
bx (
0'
0&
b0 %
0$
0#
b0 "
bx !
$end
#5000
1$
#10000
0$
#15000
1$
#20000
0$
#25000
1$
#30000
0$
#35000
1$
#40000
0$
b0 *
#45000
1$
#50000
b1 *
1#
1'
0$
b101011101010010 (
b0 0
b0 /
#55000
1$
#60000
b10 *
b1 "
b1 +
b1 %
b1 ,
0$
b1 0
b1 /
#65000
1$
#70000
b11 *
b10 "
b10 +
b10 %
b10 ,
0$
b10 0
b10 /
#75000
1$
#80000
b100 *
b11 "
b11 +
b11 %
b11 ,
0$
b11 0
b11 /
#85000
1$
#90000
b101 *
b100 "
b100 +
b100 %
b100 ,
0$
b100 0
b100 /
#95000
1$
#100000
b110 *
b101 "
b101 +
b101 %
b101 ,
0$
b101 0
b101 /
#105000
1$
#110000
b111 *
b110 "
b110 +
b110 %
b110 ,
0$
b110 0
b110 /
#115000
1$
#120000
b1000 *
b111 "
b111 +
b111 %
b111 ,
0$
b111 0
b111 /
#125000
1$
#130000
b1001 *
b1000 "
b1000 +
b1000 %
b1000 ,
0$
b1000 0
b1000 /
#135000
1$
#140000
b1010 *
b1001 "
b1001 +
b1001 %
b1001 ,
0$
b1001 0
b1001 /
#145000
1$
#150000
b1011 *
b1010 "
b1010 +
b1010 %
b1010 ,
0$
b1010 0
b1010 /
#155000
1$
#160000
b1100 *
b1011 "
b1011 +
b1011 %
b1011 ,
0$
b1011 0
b1011 /
#165000
1$
#170000
b1101 *
b1100 "
b1100 +
b1100 %
b1100 ,
0$
b1100 0
b1100 /
#175000
1$
#180000
b1110 *
b1101 "
b1101 +
b1101 %
b1101 ,
0$
b1101 0
b1101 /
#185000
1$
#190000
b1111 *
b1110 "
b1110 +
b1110 %
b1110 ,
0$
b1110 0
b1110 /
#195000
1$
#200000
b10000 *
b1111 "
b1111 +
b1111 %
b1111 ,
0$
b1111 0
b1111 /
#205000
1$
#210000
b10001 *
b10000 "
b10000 +
b10000 %
b10000 ,
0$
b10000 0
b10000 /
#215000
1$
#220000
b10010 *
b10001 "
b10001 +
b10001 %
b10001 ,
0$
b10001 0
b10001 /
#225000
1$
#230000
b10011 *
b10010 "
b10010 +
b10010 %
b10010 ,
0$
b10010 0
b10010 /
#235000
1$
#240000
b10100 *
b10011 "
b10011 +
b10011 %
b10011 ,
0$
b10011 0
b10011 /
#245000
1$
#250000
b10101 *
b10100 "
b10100 +
b10100 %
b10100 ,
0$
b10100 0
b10100 /
#255000
1$
#260000
b10110 *
b10101 "
b10101 +
b10101 %
b10101 ,
0$
b10101 0
b10101 /
#265000
1$
#270000
b10111 *
b10110 "
b10110 +
b10110 %
b10110 ,
0$
b10110 0
b10110 /
#275000
1$
#280000
b11000 *
b10111 "
b10111 +
b10111 %
b10111 ,
0$
b10111 0
b10111 /
#285000
1$
#290000
b11001 *
b11000 "
b11000 +
b11000 %
b11000 ,
0$
b11000 0
b11000 /
#295000
1$
#300000
b11010 *
b11001 "
b11001 +
b11001 %
b11001 ,
0$
b11001 0
b11001 /
#305000
1$
#310000
b11011 *
b11010 "
b11010 +
b11010 %
b11010 ,
0$
b11010 0
b11010 /
#315000
1$
#320000
b11100 *
b11011 "
b11011 +
b11011 %
b11011 ,
0$
b11011 0
b11011 /
#325000
1$
#330000
b11101 *
b11100 "
b11100 +
b11100 %
b11100 ,
0$
b11100 0
b11100 /
#335000
1$
#340000
b11110 *
b11101 "
b11101 +
b11101 %
b11101 ,
0$
b11101 0
b11101 /
#345000
1$
#350000
b11111 *
b11110 "
b11110 +
b11110 %
b11110 ,
0$
b11110 0
b11110 /
#355000
1$
#360000
b0 *
b11111 "
b11111 +
b11111 %
b11111 ,
0$
b11111 0
b11111 /
#365000
1$
#370000
1&
0'
b0 "
b0 +
0$
b101001001000100 (
b0 .
#375000
b0 !
b0 -
b1 *
1$
#380000
0$
#385000
1$
b1 .
#390000
b1 "
b1 +
0$
#395000
b1 !
b1 -
b10 *
1$
#400000
0$
#405000
1$
b10 .
#410000
b10 "
b10 +
0$
#415000
b10 !
b10 -
b11 *
1$
#420000
0$
#425000
1$
b11 .
#430000
b11 "
b11 +
0$
#435000
b11 !
b11 -
b100 *
1$
#440000
0$
#445000
1$
b100 .
#450000
b100 "
b100 +
0$
#455000
b100 !
b100 -
b101 *
1$
#460000
0$
#465000
1$
b101 .
#470000
b101 "
b101 +
0$
#475000
b101 !
b101 -
b110 *
1$
#480000
0$
#485000
1$
b110 .
#490000
b110 "
b110 +
0$
#495000
b110 !
b110 -
b111 *
1$
#500000
0$
#505000
1$
b111 .
#510000
b111 "
b111 +
0$
#515000
b111 !
b111 -
b1000 *
1$
#520000
0$
#525000
1$
b1000 .
#530000
b1000 "
b1000 +
0$
#535000
b1000 !
b1000 -
b1001 *
1$
#540000
0$
#545000
1$
b1001 .
#550000
b1001 "
b1001 +
0$
#555000
b1001 !
b1001 -
b1010 *
1$
#560000
0$
#565000
1$
b1010 .
#570000
b1010 "
b1010 +
0$
#575000
b1010 !
b1010 -
b1011 *
1$
#580000
0$
#585000
1$
b1011 .
#590000
b1011 "
b1011 +
0$
#595000
b1011 !
b1011 -
b1100 *
1$
#600000
0$
#605000
1$
b1100 .
#610000
b1100 "
b1100 +
0$
#615000
b1100 !
b1100 -
b1101 *
1$
#620000
0$
#625000
1$
b1101 .
#630000
b1101 "
b1101 +
0$
#635000
b1101 !
b1101 -
b1110 *
1$
#640000
0$
#645000
1$
b1110 .
#650000
b1110 "
b1110 +
0$
#655000
b1110 !
b1110 -
b1111 *
1$
#660000
0$
#665000
1$
b1111 .
#670000
b1111 "
b1111 +
0$
#675000
b1111 !
b1111 -
b10000 *
1$
#680000
0$
#685000
1$
b10000 .
#690000
b10000 "
b10000 +
0$
#695000
b10000 !
b10000 -
b10001 *
1$
#700000
0$
#705000
1$
b10001 .
#710000
b10001 "
b10001 +
0$
#715000
b10001 !
b10001 -
b10010 *
1$
#720000
0$
#725000
1$
b10010 .
#730000
b10010 "
b10010 +
0$
#735000
b10010 !
b10010 -
b10011 *
1$
#740000
0$
#745000
1$
b10011 .
#750000
b10011 "
b10011 +
0$
#755000
b10011 !
b10011 -
b10100 *
1$
#760000
0$
#765000
1$
b10100 .
#770000
b10100 "
b10100 +
0$
#775000
b10100 !
b10100 -
b10101 *
1$
#780000
0$
#785000
1$
b10101 .
#790000
b10101 "
b10101 +
0$
#795000
b10101 !
b10101 -
b10110 *
1$
#800000
0$
#805000
1$
b10110 .
#810000
b10110 "
b10110 +
0$
#815000
b10110 !
b10110 -
b10111 *
1$
#820000
0$
#825000
1$
b10111 .
#830000
b10111 "
b10111 +
0$
#835000
b10111 !
b10111 -
b11000 *
1$
#840000
0$
#845000
1$
b11000 .
#850000
b11000 "
b11000 +
0$
#855000
b11000 !
b11000 -
b11001 *
1$
#860000
0$
#865000
1$
b11001 .
#870000
b11001 "
b11001 +
0$
#875000
b11001 !
b11001 -
b11010 *
1$
#880000
0$
#885000
1$
b11010 .
#890000
b11010 "
b11010 +
0$
#895000
b11010 !
b11010 -
b11011 *
1$
#900000
0$
#905000
1$
b11011 .
#910000
b11011 "
b11011 +
0$
#915000
b11011 !
b11011 -
b11100 *
1$
#920000
0$
#925000
1$
b11100 .
#930000
b11100 "
b11100 +
0$
#935000
b11100 !
b11100 -
b11101 *
1$
#940000
0$
#945000
1$
b11101 .
#950000
b11101 "
b11101 +
0$
#955000
b11101 !
b11101 -
b11110 *
1$
#960000
0$
#965000
1$
b11110 .
#970000
b11110 "
b11110 +
0$
#975000
b11110 !
b11110 -
b11111 *
1$
#980000
0$
#985000
1$
b11111 .
#990000
b11111 "
b11111 +
0$
#995000
b11111 !
b11111 -
b100000 *
1$
