01_descriptions/01_mux/mux2.v
module	mux2_primitive
(
	output		o_out,
	input		i_sel,
	input		i_in0,
	input		i_in1
);
	wire		sel_n;
	wire		out_0;
	wire		out_1;

	not	u_not0	(sel_n , i_sel         ) ;
	and	u_and0	(out_0 , i_in0 , sel_n ) ;
	and	u_and1	(out_1 , i_in1 , i_sel ) ;
	or	u_or0	(o_out , out_0 , out_1 ) ;

endmodule

module	mux2_assign
(
	output		o_out,
	input		i_sel,
	input		i_in0,
	input		i_in1
);

	assign	o_out	= i_sel ? i_in1 : i_in0;

endmodule

module	mux2_if
(
	output reg	o_out,
	input		i_sel,
	input		i_in0,
	input		i_in1
);

	always @(*) begin
		if (i_sel == 0) begin
			o_out	= i_in0;
		end else begin
			o_out	= i_in1;
		end
	end

endmodule

module	mux2_case
(
	output reg	o_out,
	input		i_sel,
	input		i_in0,
	input		i_in1
);

	always @(*) begin
		case(i_sel)
			0:			o_out = i_in0;
			1:			o_out = i_in1;
			//default:	o_out = i_in1;
		endcase
	end

endmodule

01_descriptions/01_mux/mux2_tb.v
// --------------------------------------------------
//	Define Global Variables
// --------------------------------------------------
//	Clock
`define	CLKFREQ		100		// Unit: MHz
`define	SIMCYCLE	100

`include	"mux2.v"

module	mux2_tb;
// --------------------------------------------------
//	DUT Signals & Instantiate
// --------------------------------------------------
	wire		o_out_primitive;
	wire		o_out_assign;
	wire		o_out_if;
	wire		o_out_case;
	reg			i_sel;
	reg			i_in0;
	reg			i_in1;

	mux2_primitive
	u_mux2_primitive
	(	
		.o_out		(o_out_primitive	),
		.i_sel		(i_sel				),
		.i_in0		(i_in0				),
		.i_in1		(i_in1				)
	);
	
	mux2_assign
	u_mux2_assign
	(	
		.o_out		(o_out_assign		),
		.i_sel		(i_sel				),
		.i_in0		(i_in0				),
		.i_in1		(i_in1				)
	);

	mux2_if
	u_mux2_if
	(	
		.o_out		(o_out_if			),
		.i_sel		(i_sel				),
		.i_in0		(i_in0				),
		.i_in1		(i_in1				)
	);

	mux2_case
	u_mux2_case
	(	
		.o_out		(o_out_case			),
		.i_sel		(i_sel				),
		.i_in0		(i_in0				),
		.i_in1		(i_in1				)
	);

// --------------------------------------------------
//	Test Stimulus
// --------------------------------------------------
	integer		i, j, k, n;
	initial begin
		for (i=0; i<`SIMCYCLE; i++) begin
			{i_sel, i_in0, i_in1} = $urandom_range(0,7);
			//i_sel = 1;
			#(1000/`CLKFREQ);
		end
	end

	reg	[8*32-1:0]	vcd_file;
	initial begin
		if ($value$plusargs("vcd_file=%s", vcd_file)) begin
			$dumpfile(vcd_file);
			$dumpvars;
		end
	end

endmodule

01_descriptions/01_mux/vcd/mux2.vcd
$date
	Wed May  1 09:58:04 2024
$end
$version
	Icarus Verilog
$end
$timescale
	1ps
$end
$scope module mux2_tb $end
$var wire 1 ! o_out_primitive $end
$var wire 1 " o_out_if $end
$var wire 1 # o_out_case $end
$var wire 1 $ o_out_assign $end
$var reg 1 % i_in0 $end
$var reg 1 & i_in1 $end
$var reg 1 ' i_sel $end
$var reg 256 ( vcd_file [255:0] $end
$var integer 32 ) i [31:0] $end
$scope module u_mux2_assign $end
$var wire 1 % i_in0 $end
$var wire 1 & i_in1 $end
$var wire 1 ' i_sel $end
$var wire 1 $ o_out $end
$upscope $end
$scope module u_mux2_case $end
$var wire 1 % i_in0 $end
$var wire 1 & i_in1 $end
$var wire 1 ' i_sel $end
$var reg 1 # o_out $end
$upscope $end
$scope module u_mux2_if $end
$var wire 1 % i_in0 $end
$var wire 1 & i_in1 $end
$var wire 1 ' i_sel $end
$var reg 1 " o_out $end
$upscope $end
$scope module u_mux2_primitive $end
$var wire 1 % i_in0 $end
$var wire 1 & i_in1 $end
$var wire 1 ' i_sel $end
$var wire 1 ! o_out $end
$var wire 1 * out_0 $end
$var wire 1 + out_1 $end
$var wire 1 , sel_n $end
$upscope $end
$upscope $end
$enddefinitions $end
#0
$dumpvars
0,
0+
0*
b0 )
b10111000101111011101100110001101100100001011110110110101110101011110000011001000101110011101100110001101100100 (
1'
0&
0%
0$
0#
0"
0!
$end
#10000
1'
1%
b1 )
#20000
1'
0%
b10 )
#30000
1!
1$
1"
1#
1+
1'
1&
b11 )
#40000
0!
0$
0#
0"
0+
0&
b100 )
#50000
1%
b101 )
#60000
1!
1$
1#
1"
1+
1'
0%
1&
b110 )
#70000
0!
0$
0"
0#
0+
1'
0&
b111 )
#80000
b1000 )
#90000
b1001 )
#100000
1!
1$
1#
1"
1+
1&
b1010 )
#110000
0!
0$
0"
0#
0+
0&
b1011 )
#120000
1!
1$
1#
1"
1+
1%
1&
b1100 )
#130000
0!
0$
0"
0#
0+
0&
b1101 )
#140000
1!
1$
1#
1"
1+
1&
b1110 )
#150000
1'
b1111 )
#160000
1'
b10000 )
#170000
0!
0$
0"
0#
0+
1'
0&
b10001 )
#180000
1!
1$
1#
1"
1+
1&
b10010 )
#190000
1'
0%
b10011 )
#200000
0!
0$
0#
0"
0+
1'
0&
b10100 )
#210000
1%
b10101 )
#220000
1!
1$
1#
1"
1+
1&
b10110 )
#230000
1'
b10111 )
#240000
1'
b11000 )
#250000
1'
b11001 )
#260000
0%
b11010 )
#270000
0!
0$
0"
0#
0+
1'
1%
0&
b11011 )
#280000
1'
0%
b11100 )
#290000
1!
1$
1"
1#
1+
1'
1&
b11101 )
#300000
1'
b11110 )
#310000
0!
0$
0"
0#
0+
0&
b11111 )
#320000
1'
1%
b100000 )
#330000
0%
b100001 )
#340000
1%
b100010 )
#350000
1'
b100011 )
#360000
1'
b100100 )
#370000
1'
0%
b100101 )
#380000
1'
b100110 )
#390000
1!
1$
1"
1#
1+
1'
1&
b100111 )
#400000
b101000 )
#410000
1'
1%
b101001 )
#420000
0!
0$
0"
0#
0+
1'
0%
0&
b101010 )
#430000
1'
1%
b101011 )
#440000
0%
b101100 )
#450000
1!
1$
1#
1"
1+
1'
1%
1&
b101101 )
#460000
0!
0$
0"
0#
0+
0%
0&
b101110 )
#470000
b101111 )
#480000
1!
1$
1#
1"
1+
1'
1%
1&
b110000 )
#490000
0!
0$
0"
0#
0+
1'
0%
0&
b110001 )
#500000
1!
1$
1#
1"
1+
1%
1&
b110010 )
#510000
0!
0$
0"
0#
0+
0&
b110011 )
#520000
1!
1$
1#
1"
1+
0%
1&
b110100 )
#530000
1'
1%
b110101 )
#540000
0%
b110110 )
#550000
0!
0$
0"
0#
0+
1'
1%
0&
b110111 )
#560000
1!
1$
1#
1"
1+
1&
b111000 )
#570000
0!
0$
0"
0#
0+
0&
b111001 )
#580000
1!
1$
1#
1"
1+
1&
b111010 )
#590000
0!
0$
0"
0#
0+
0&
b111011 )
#600000
1'
b111100 )
#610000
0%
b111101 )
#620000
1'
b111110 )
#630000
1!
1$
1"
1#
1+
1'
1&
b111111 )
#640000
0!
0$
0#
0"
0+
1%
0&
b1000000 )
#650000
1!
1$
1"
1#
1+
0%
1&
b1000001 )
#660000
0!
0$
0#
0"
0+
1'
0&
b1000010 )
#670000
b1000011 )
#680000
1!
1$
1"
1#
1+
1'
1&
b1000100 )
#690000
0!
0$
0#
0"
0+
0&
b1000101 )
#700000
1!
1$
1"
1#
1+
1%
1&
b1000110 )
#710000
b1000111 )
#720000
0%
b1001000 )
#730000
b1001001 )
#740000
0!
0$
0"
0#
0+
1%
0&
b1001010 )
#750000
b1001011 )
#760000
1!
1$
1#
1"
1+
1&
b1001100 )
#770000
0!
0$
0"
0#
0+
1'
0&
b1001101 )
#780000
1'
b1001110 )
#790000
1!
1$
1"
1#
1+
1'
0%
1&
b1001111 )
#800000
1'
b1010000 )
#810000
0!
0$
0"
0#
0+
1%
0&
b1010001 )
#820000
1!
1$
1#
1"
1+
1'
0%
1&
b1010010 )
#830000
1'
1%
b1010011 )
#840000
1'
b1010100 )
#850000
1'
0%
b1010101 )
#860000
0!
0$
0#
0"
0+
1%
0&
b1010110 )
#870000
0%
b1010111 )
#880000
1!
1$
1#
1"
1+
1'
1%
1&
b1011000 )
#890000
b1011001 )
#900000
1'
0%
b1011010 )
#910000
0!
0$
0#
0"
0+
0&
b1011011 )
#920000
b1011100 )
#930000
1!
1$
1"
1#
1+
1'
1&
b1011101 )
#940000
b1011110 )
#950000
0!
0$
0#
0"
0+
0&
b1011111 )
#960000
b1100000 )
#970000
1!
1$
1"
1#
1+
1'
1%
1&
b1100001 )
#980000
0!
0$
0#
0"
0+
0&
b1100010 )
#990000
1!
1$
1"
1#
1+
1'
0%
1&
b1100011 )
#1000000
b1100100 )
