zaram_training_course/03_sequential/latch_vs_dff/latch_vs_dff.v
// ==================================================
//	[ VLSISYS Lab. ]
//	* Author		: Woong Choi (woongchoi@sm.ac.kr)
//	* Filename		: latch_vs_dff.v
//	* Date			: 2024-06-24 14:43:33
//	* Description	: 
// ==================================================

module	latch 
(	
	output reg	o_q,
	input		i_d,
	input		i_clk
);

	always @(*) begin
		if(i_clk) begin
			o_q	= i_d;
		end
	end
	
endmodule

module	dff
(	
	output reg	o_q,
	input		i_d,
	input		i_clk
);

	always @(posedge i_clk) begin
		o_q	<= i_d;
	end
	
endmodule

zaram_training_course/03_sequential/latch_vs_dff/latch_vs_dff_tb.v
// ==================================================
//	[ VLSISYS Lab. ]
//	* Author		: Woong Choi (woongchoi@sm.ac.kr)
//	* Filename		: latch_vs_dff_tb.v
//	* Date			: 2024-06-24 14:44:58
//	* Description	: 
// ==================================================

// --------------------------------------------------
//	Define Global Variables
// --------------------------------------------------
`define	CLKFREQ		100		// Clock Freq. (Unit: MHz)
`define	SIMCYCLE	`NVEC	// Sim. Cycles
`define BW_DATA		32		// Bitwidth of ~~
`define BW_ADDR		5		// Bitwidth of ~~
`define BW_CTRL		4		// Bitwidth of ~~
`define NVEC		100		// # of Test Vector

// --------------------------------------------------
//	Includes
// --------------------------------------------------
`include	"latch_vs_dff.v"

module latch_vs_dff_tb;
// --------------------------------------------------
//	DUT Signals & Instantiate
// --------------------------------------------------
	wire	o_q_latch;
	wire	o_q_dff;
	reg		i_d;
	reg		i_clk;

	latch
	u_latch(
		.o_q				(o_q_latch			),
		.i_d				(i_d				),
		.i_clk				(i_clk				)
	);

	dff
	u_dff(
		.o_q				(o_q_dff			),
		.i_d				(i_d				),
		.i_clk				(i_clk				)
	);


// --------------------------------------------------
//	Clock
// --------------------------------------------------
	always #(500/`CLKFREQ)	i_clk = ~i_clk;

// --------------------------------------------------
//	Test Stimulus
// --------------------------------------------------
	integer		i, j;
	initial begin
		i_d		= 0;
		i_clk	= 0;
		for (i=0; i<`SIMCYCLE; i++) begin
			j = $urandom_range(0, 10);
			#((0+(j*0.1))*1000/`CLKFREQ);
			i_d = $urandom;
			#((1-(j*0.1))*1000/`CLKFREQ);
		end
		#(1000/`CLKFREQ);
		$finish;
	end

// --------------------------------------------------
//	Dump VCD
// --------------------------------------------------
	reg	[8*32-1:0]	vcd_file;
	initial begin
		if ($value$plusargs("vcd_file=%s", vcd_file)) begin
			$dumpfile(vcd_file);
			$dumpvars;
		end else begin
			$dumpfile("latch_vs_dff_tb.vcd");
			$dumpvars;
		end
	end

endmodule

zaram_training_course/03_sequential/latch_vs_dff/vcd/latch_vs_dff.vcd
$date
	Mon Jun 24 14:47:13 2024
$end
$version
	Icarus Verilog
$end
$timescale
	1ps
$end
$scope module latch_vs_dff_tb $end
$var wire 1 ! o_q_latch $end
$var wire 1 " o_q_dff $end
$var reg 1 # i_clk $end
$var reg 1 $ i_d $end
$var reg 256 % vcd_file [255:0] $end
$var integer 32 & i [31:0] $end
$var integer 32 ' j [31:0] $end
$scope module u_dff $end
$var wire 1 # i_clk $end
$var wire 1 $ i_d $end
$var reg 1 " o_q $end
$upscope $end
$scope module u_latch $end
$var wire 1 # i_clk $end
$var wire 1 $ i_d $end
$var reg 1 ! o_q $end
$upscope $end
$upscope $end
$enddefinitions $end
#0
$dumpvars
b110 '
b0 &
b101110001011110111011001100011011001000010111101101100011000010111010001100011011010000101111101110110011100110101111101100100011001100110011000101110011101100110001101100100 %
0$
0#
x"
x!
$end
#5000
0"
0!
1#
#6000
1!
1$
#10000
b0 '
b1 &
0#
#15000
1"
1#
#20000
0#
b101 '
b10 &
#25000
1#
#30000
0#
b10 '
b11 &
#32000
0$
#35000
0"
0!
1#
#40000
0#
b101 '
b100 &
#45000
1"
1!
1#
1$
#50000
0#
b1000 '
b101 &
#55000
1#
#60000
b1010 '
b110 &
0#
#65000
1#
#70000
b111 &
0#
0$
#75000
0"
0!
1#
#80000
b100 '
b1000 &
0#
#85000
1#
#90000
0#
b1010 '
b1001 &
#95000
1#
#100000
b0 '
b1010 &
0#
1$
#105000
1"
1!
1#
#110000
0#
b1010 '
b1011 &
#115000
1#
#120000
b100 '
b1100 &
0#
0$
#124000
1$
#125000
1#
#130000
0#
b111 '
b1101 &
#135000
1#
#140000
b0 '
b1110 &
0#
#145000
1#
#150000
0#
b10 '
b1111 &
#152000
0$
#155000
0"
0!
1#
#160000
0#
b10000 &
#165000
1#
#170000
0#
b1001 '
b10001 &
#175000
1#
#179000
1!
1$
#180000
b11 '
b10010 &
0#
#185000
1"
1#
#190000
0#
b0 '
b10011 &
#195000
1#
#200000
0#
b111 '
b10100 &
#205000
1#
#210000
0$
b0 '
b10101 &
0#
#215000
0"
0!
1#
#220000
0#
b110 '
b10110 &
#225000
1#
#226000
1!
1$
#230000
b10111 &
0#
#235000
1"
1#
#236000
0!
0$
#240000
b100 '
b11000 &
0#
#245000
0"
1#
#250000
0#
b1010 '
b11001 &
#255000
1#
#260000
b110 '
b11010 &
0#
#265000
1#
#270000
b1000 '
b11011 &
0#
#275000
1#
#278000
1!
1$
#280000
b1010 '
b11100 &
0#
#285000
1"
1#
#290000
b1001 '
b11101 &
0#
0$
#295000
0"
0!
1#
#300000
b100 '
b11110 &
0#
#305000
1#
#310000
1$
0#
b0 '
b11111 &
#315000
1"
1!
1#
#320000
0#
b1000 '
b100000 &
#325000
1#
#330000
b1 '
b100001 &
0#
#331000
0$
#335000
0"
0!
1#
#340000
0#
b10 '
b100010 &
#342000
1$
#345000
1"
1!
1#
#350000
0#
b1010 '
b100011 &
#355000
1#
#360000
b111 '
b100100 &
0#
#365000
1#
#367000
0!
0$
#370000
b1000 '
b100101 &
0#
#375000
0"
1#
#378000
1!
1$
#380000
b1010 '
b100110 &
0#
#385000
1"
1#
#390000
b11 '
b100111 &
0#
#393000
0$
#395000
0"
0!
1#
#400000
0#
b1 '
b101000 &
#401000
1$
#405000
1"
1!
1#
#410000
0#
b101001 &
#411000
0$
#415000
0"
0!
1#
#420000
0#
b100 '
b101010 &
#424000
1$
#425000
1"
1!
1#
#430000
0#
b1000 '
b101011 &
#435000
1#
#438000
0!
0$
#440000
b100 '
b101100 &
0#
#445000
0"
1#
#450000
0#
b10 '
b101101 &
#452000
1$
#455000
1"
1!
1#
#460000
0#
b101 '
b101110 &
#465000
0"
0!
1#
0$
#470000
0#
b111 '
b101111 &
#475000
1#
#477000
1!
1$
#480000
b110 '
b110000 &
0#
#485000
1"
1#
#490000
b1000 '
b110001 &
0#
#495000
1#
#498000
0!
0$
#500000
b111 '
b110010 &
0#
#505000
0"
1#
#507000
1!
1$
#510000
b1 '
b110011 &
0#
#511000
0$
#515000
0!
1#
#520000
0#
b111 '
b110100 &
#525000
1#
#530000
b11 '
b110101 &
0#
#535000
1#
#540000
0#
b1010 '
b110110 &
#545000
1#
#550000
b111 '
b110111 &
0#
#555000
1#
#557000
1!
1$
#560000
b1 '
b111000 &
0#
#565000
1"
1#
#570000
0#
b10 '
b111001 &
#572000
0$
#575000
0"
0!
1#
#580000
0#
b1010 '
b111010 &
#585000
1#
#590000
b100 '
b111011 &
0#
1$
#594000
0$
#595000
1#
#600000
0#
b110 '
b111100 &
#605000
1#
#606000
1!
1$
#610000
b100 '
b111101 &
0#
#615000
1"
1#
#620000
0#
b11 '
b111110 &
#625000
1#
#630000
0#
b1000 '
b111111 &
#635000
1#
#638000
0!
0$
#640000
b100 '
b1000000 &
0#
#645000
0"
1#
#650000
0#
b1001 '
b1000001 &
#655000
1#
#660000
b1010 '
b1000010 &
0#
#665000
1#
#670000
b101 '
b1000011 &
0#
#675000
1"
1!
1$
1#
#680000
b111 '
b1000100 &
0#
#685000
1#
#687000
0!
0$
#690000
b10 '
b1000101 &
0#
#695000
0"
1#
#700000
0#
b1001 '
b1000110 &
#705000
1#
#710000
b1000 '
b1000111 &
0#
#715000
1#
#720000
b1001000 &
0#
#725000
1#
#728000
1!
1$
#730000
b0 '
b1001001 &
0#
#735000
1"
1#
#740000
0#
b1010 '
b1001010 &
#745000
1#
#750000
b1001011 &
0#
#755000
1#
#760000
b10 '
b1001100 &
0#
#762000
0$
#765000
0"
0!
1#
#770000
0#
b1001 '
b1001101 &
#775000
1#
#779000
1!
1$
#780000
b1 '
b1001110 &
0#
#781000
0$
#785000
0!
1#
#790000
0#
b1010 '
b1001111 &
#795000
1#
#800000
b11 '
b1010000 &
0#
1$
#803000
0$
#805000
1#
#810000
0#
b110 '
b1010001 &
#815000
1#
#816000
1!
1$
#820000
b100 '
b1010010 &
0#
#824000
0$
#825000
0!
1#
#830000
0#
b0 '
b1010011 &
#835000
1#
#840000
0#
b101 '
b1010100 &
#845000
1"
1!
1#
1$
#850000
0$
0#
b0 '
b1010101 &
#855000
0"
0!
1#
#860000
0#
b100 '
b1010110 &
#864000
1$
#865000
1"
1!
1#
#870000
0#
b111 '
b1010111 &
#875000
1#
#877000
0!
0$
#880000
b10 '
b1011000 &
0#
#885000
0"
1#
#890000
0#
b111 '
b1011001 &
#895000
1#
#900000
b1010 '
b1011010 &
0#
#905000
1#
#910000
b11 '
b1011011 &
0#
#913000
1$
#915000
1"
1!
1#
#920000
0#
b1000 '
b1011100 &
#925000
1#
#928000
0!
0$
#930000
b110 '
b1011101 &
0#
#935000
0"
1#
#940000
b1000 '
b1011110 &
0#
#945000
1#
#950000
b1011111 &
0#
#955000
1#
#960000
b1100000 &
0#
#965000
1#
#968000
1!
1$
#970000
b100 '
b1100001 &
0#
#975000
1"
1#
#980000
0#
b101 '
b1100010 &
#985000
1#
#990000
0#
b1100011 &
#995000
1#
#1000000
0#
b1100100 &
