01_basics/10_test_vector/adder.v
// ==================================================
//	[ VLSISYS Lab. ]
//	* Author		: Woong Choi (woongchoi@sm.ac.kr)
//	* Filename		: adder.v
//	* Description	: 
// ==================================================

module adder
#(	
	parameter	BW_DATA	= 32
)
(	
	output		[BW_DATA-1:0]	o_s,
	output						o_c,
	input		[BW_DATA-1:0]	i_a,
	input		[BW_DATA-1:0]	i_b,
	input						i_c
);

	assign	{o_c, o_s} = i_a + i_b + i_c;

endmodule

01_basics/10_test_vector/adder_tb.v
// ==================================================
//	[ VLSISYS Lab. ]
//	* Author		: Woong Choi (woongchoi@sm.ac.kr)
//	* Filename		: adder_tb.v
//	* Date			: 2024-05-17 13:24:24
//	* Description	: 
// ==================================================
// --------------------------------------------------
//	Define Global Variables
// --------------------------------------------------
`define	CLKFREQ		100		// Clock Freq. (Unit: MHz)
`define	SIMCYCLE	`NVEC	// Sim. Cycles
`define BW_DATA		32		// Bitwidth of ~~
`define NVEC		100		// # of Test Vector

// --------------------------------------------------
//	Includes
// --------------------------------------------------
`include	"adder.v"

module	adder_tb;
// --------------------------------------------------
//	DUT Signals & Instantiate
// --------------------------------------------------

	localparam	BW_DATA		= 32;

	wire	[`BW_DATA-1:0]	o_s;
	wire					o_c;
	reg		[`BW_DATA-1:0]	i_a;
	reg		[`BW_DATA-1:0]	i_b;
	reg						i_c;

	adder
	#(
		.BW_DATA		(`BW_DATA		)
	)
	u_adder(
		.o_s			(o_s			),
		.o_c			(o_c			),
		.i_a			(i_a			),
		.i_b			(i_b			),
		.i_c			(i_c			)
	);

// --------------------------------------------------
//	Test Vector Configuration
// --------------------------------------------------
	reg		[`BW_DATA-1:0]	vo_s[0:`NVEC-1];
	reg						vo_c[0:`NVEC-1];
	reg		[`BW_DATA-1:0]	vi_a[0:`NVEC-1];
	reg		[`BW_DATA-1:0]	vi_b[0:`NVEC-1];
	reg						vi_c[0:`NVEC-1];

	initial begin
		$readmemb("./vec/o_s.vec",		vo_s);
		$readmemb("./vec/o_c.vec",		vo_c);
		$readmemb("./vec/i_a.vec",		vi_a);
		$readmemb("./vec/i_b.vec",		vi_b);
		$readmemb("./vec/i_c.vec",		vi_c);
	end

// --------------------------------------------------
//	Tasks
// --------------------------------------------------
	reg		[4*32-1:0]	taskState;
	integer				err	= 0;

	task init;
		begin
			taskState		= "Init";
			i_a				= 0;
			i_b				= 0;
			i_c				= 0;
		end
	endtask

	task vecInsert;
		input	[$clog2(`NVEC)-1:0]	i;
		begin
			$sformat(taskState,	"VEC[%3d]", i);
			i_a				= vi_a[i];
			i_b				= vi_b[i];
			i_c				= vi_c[i];
		end
	endtask

	task vecVerify;
		input	[$clog2(`NVEC)-1:0]	i;
		begin
			#(0.1*1000/`CLKFREQ);
			if (o_s	 != vo_s[i]) begin $display("[Idx: %3d] Mismatched o_s", i); end
			if (o_c	 != vo_c[i]) begin $display("[Idx: %3d] Mismatched o_c", i); end
			if ((o_s != vo_s[i]) || (o_c != vo_c[i])) begin err++; end
			#(0.9*1000/`CLKFREQ);
		end
	endtask

// --------------------------------------------------
//	Test Stimulus
// --------------------------------------------------
	integer		i, j;
	initial begin
		init();

		for (i=0; i<`SIMCYCLE; i++) begin
			vecInsert(i);
			vecVerify(i);
		end
		#(1000/`CLKFREQ);
		$finish;
	end

// --------------------------------------------------
//	Dump VCD
// --------------------------------------------------
	reg	[8*32-1:0]	vcd_file;
	initial begin
		if ($value$plusargs("vcd_file=%s", vcd_file)) begin
			$dumpfile(vcd_file);
			$dumpvars;
		end else begin
			$dumpfile("adder_tb.vcd");
			$dumpvars;
		end
	end

endmodule

01_basics/10_test_vector/vcd/adder.vcd
$date
	Fri May 17 13:26:59 2024
$end
$version
	Icarus Verilog
$end
$timescale
	1ps
$end
$scope module adder_tb $end
$var wire 32 ! o_s [31:0] $end
$var wire 1 " o_c $end
$var reg 32 # i_a [31:0] $end
$var reg 32 $ i_b [31:0] $end
$var reg 1 % i_c $end
$var reg 128 & taskState [127:0] $end
$var reg 256 ' vcd_file [255:0] $end
$var integer 32 ( err [31:0] $end
$var integer 32 ) i [31:0] $end
$scope module u_adder $end
$var wire 32 * i_a [31:0] $end
$var wire 32 + i_b [31:0] $end
$var wire 1 % i_c $end
$var wire 32 , o_s [31:0] $end
$var wire 1 " o_c $end
$upscope $end
$scope task init $end
$upscope $end
$scope task vecInsert $end
$var reg 7 - i [6:0] $end
$upscope $end
$scope task vecVerify $end
$var reg 7 . i [6:0] $end
$upscope $end
$upscope $end
$enddefinitions $end
#0
$dumpvars
b0 .
b0 -
b1110101011010011010101001111101 ,
b11111100000101100000000010101100 +
b1111001010100111010100111010000 *
b0 )
b0 (
b1011100010111101110110011000110110010000101111011000010110010001100100011001010111001000101110011101100110001101100100 '
b101011001000101010000110101101100100000001000000011000001011101 &
1%
b11111100000101100000000010101100 $
b1111001010100111010100111010000 #
1"
b1110101011010011010101001111101 !
$end
#1000
b1 (
#10000
b10001100110110010111101101011101 !
b10001100110110010111101101011101 ,
b1 .
0%
b10010000001010111001011011111001 $
b10010000001010111001011011111001 +
b11111100101011011110010001100100 #
b11111100101011011110010001100100 *
b101011001000101010000110101101100100000001000000011000101011101 &
b1 -
b1 )
#11000
b10 (
#20000
b11010010101000011101000010111100 !
b11010010101000011101000010111100 ,
0"
b10 .
1%
b10111101110101010011101111011101 $
b10111101110101010011101111011101 +
b10100110011001001010011011110 #
b10100110011001001010011011110 *
b101011001000101010000110101101100100000001000000011001001011101 &
b10 -
b10 )
#21000
b11 (
#30000
b10011011011010100010000000100001 !
b10011011011010100010000000100001 ,
b11 .
0%
b10010010111101100000001101010100 $
b10010010111101100000001101010100 +
b1000011101000001110011001101 #
b1000011101000001110011001101 *
b101011001000101010000110101101100100000001000000011001101011101 &
b11 -
b11 )
#40000
1"
b101010011111011110010110100100 !
b101010011111011110010110100100 ,
b100 .
b11001000111100111001010001111110 $
b11001000111100111001010001111110 +
b1100001100010100101000100100110 #
b1100001100010100101000100100110 *
b101011001000101010000110101101100100000001000000011010001011101 &
b100 -
b100 )
#41000
b100 (
#50000
b111001001100001110100011000111 !
b111001001100001110100011000111 ,
b101 .
b1010110110001011100100101001100 $
b1010110110001011100100101001100 +
b11100010011010110001111101111011 #
b11100010011010110001111101111011 *
b101011001000101010000110101101100100000001000000011010101011101 &
b101 -
b101 )
#60000
b10011111011010001001111011010101 !
b10011111011010001001111011010101 ,
0"
b110 .
1%
b1100000101000110000010010111110 $
b1100000101000110000010010111110 +
b111110110001011001101000010110 #
b111110110001011001101000010110 *
b101011001000101010000110101101100100000001000000011011001011101 &
b110 -
b110 )
#70000
1"
b1001011110010110010010000010010 !
b1001011110010110010010000010010 ,
b111 .
0%
b10111101101110101100001100110111 $
b10111101101110101100001100110111 +
b10001110000100000110000011011011 #
b10001110000100000110000011011011 *
b101011001000101010000110101101100100000001000000011011101011101 &
b111 -
b111 )
#71000
b101 (
#80000
b110001110000111011011001101100 !
b110001110000111011011001101100 ,
0"
b1000 .
1%
b10100101011101011001000101000 $
b10100101011101011001000101000 +
b11101000101010000010001000011 #
b11101000101010000010001000011 *
b101011001000101010000110101101100100000001000000011100001011101 &
b1000 -
b1000 )
#81000
b110 (
#90000
1"
b1000110000111010101111000001001 !
b1000110000111010101111000001001 ,
b1001 .
b10101111101110110101010101111110 $
b10101111101110110101010101111110 +
b10010110011000100000100010001010 #
b10010110011000100000100010001010 *
b101011001000101010000110101101100100000001000000011100101011101 &
b1001 -
b1001 )
#91000
b111 (
#100000
b10101000001000111111000011 !
b10101000001000111111000011 ,
b1010 .
0%
b110111111010010010011111111011 $
b110111111010010010011111111011 +
b11001010101101110110011111001000 #
b11001010101101110110011111001000 *
b101011001000101010000110101101100100000001100010011000001011101 &
b1010 -
b1010 )
#110000
b1110101001011001111100100001101 !
b1110101001011001111100100001101 ,
0"
b1011 .
b1001101110111011100100011001101 $
b1001101110111011100100011001101 +
b100111010011110011000001000000 #
b100111010011110011000001000000 *
b101011001000101010000110101101100100000001100010011000101011101 &
b1011 -
b1011 )
#120000
1"
b111001101111001110110001001010 !
b111001101111001110110001001010 ,
b1100 .
1%
b11010001100011110000011110000100 $
b11010001100011110000011110000100 +
b1101000001011011110010011000101 #
b1101000001011011110010011000101 *
b101011001000101010000110101101100100000001100010011001001011101 &
b1100 -
b1100 )
#130000
b111101111010100110011010001110 !
b111101111010100110011010001110 ,
b1101 .
0%
b1101110100101101001100111110101 $
b1101110100101101001100111110101 +
b11001111010100111100110010011001 #
b11001111010100111100110010011001 *
b101011001000101010000110101101100100000001100010011001101011101 &
b1101 -
b1101 )
#140000
b1011001010101110000000010110010 !
b1011001010101110000000010110010 ,
b1110 .
b10011100010111001101001111101001 $
b10011100010111001101001111101001 +
b10111100111110100010110011001001 #
b10111100111110100010110011001001 *
b101011001000101010000110101101100100000001100010011010001011101 &
b1110 -
b1110 )
#141000
b1000 (
#150000
b10100010100010111100100001010100 !
b10100010100010111100100001010100 ,
b1111 .
1%
b11000001011010010100011110101101 $
b11000001011010010100011110101101 +
b11100001001000101000000010100110 #
b11100001001000101000000010100110 *
b101011001000101010000110101101100100000001100010011010101011101 &
b1111 -
b1111 )
#151000
b1001 (
#160000
b10111100111010011000010000100010 !
b10111100111010011000010000100010 ,
0"
b10000 .
b10001101000110011000110101011101 $
b10001101000110011000110101011101 +
b101111110011111111011011000100 #
b101111110011111111011011000100 *
b101011001000101010000110101101100100000001100010011011001011101 &
b10000 -
b10000 )
#161000
b1010 (
#170000
b10111111011011111101011001101001 !
b10111111011011111101011001101001 ,
b10001 .
b1000101011001001110000010101010 $
b1000101011001001110000010101010 +
b1111010000010101111010110111110 #
b1111010000010101111010110111110 *
b101011001000101010000110101101100100000001100010011011101011101 &
b10001 -
b10001 )
#171000
b1011 (
#180000
b11001100001110000010100111100110 !
b11001100001110000010100111100110 ,
1"
b10010 .
0%
b11011000111110111010001001000001 $
b11011000111110111010001001000001 +
b11110011001111001000011110100101 #
b11110011001111001000011110100101 *
b101011001000101010000110101101100100000001100010011100001011101 &
b10010 -
b10010 )
#190000
0"
b11011001001000001000110101001010 !
b11011001001000001000110101001010 ,
b10011 .
b100001110111000000010110111011 $
b100001110111000000010110111011 +
b10110111010001001000011110001111 #
b10110111010001001000011110001111 *
b101011001000101010000110101101100100000001100010011100101011101 &
b10011 -
b10011 )
#200000
b10010011110110011110011011010010 !
b10010011110110011110011011010010 ,
1"
b10100 .
1%
b10100011000001011111000111010101 $
b10100011000001011111000111010101 +
b11110000110100111111010011111100 #
b11110000110100111111010011111100 *
b101011001000101010000110101101100100000001100100011000001011101 &
b10100 -
b10100 )
#201000
b1100 (
#210000
0"
b11100111001100101000110010100110 !
b11100111001100101000110010100110 ,
b10101 .
b100101111010001010100010001100 $
b100101111010001010100010001100 +
b11000001010010011110010000011001 #
b11000001010010011110010000011001 *
b101011001000101010000110101101100100000001100100011000101011101 &
b10101 -
b10101 )
#220000
1"
b1101000101010110000001001100110 !
b1101000101010110000001001100110 ,
b10110 .
0%
b10111010101100011110001110100000 $
b10111010101100011110001110100000 +
b10101101111110010001111011000110 #
b10101101111110010001111011000110 *
b101011001000101010000110101101100100000001100100011001001011101 &
b10110 -
b10110 )
#221000
b1101 (
#230000
b100110101100001000011000011101 !
b100110101100001000011000011101 ,
0"
b10111 .
b100000101001000100001110110000 $
b100000101001000100001110110000 +
b110000011000100001001101101 #
b110000011000100001001101101 *
b101011001000101010000110101101100100000001100100011001101011101 &
b10111 -
b10111 )
#240000
b10110101110001111000110100001010 !
b10110101110001111000110100001010 ,
b11000 .
b10110101101111010010101111010101 $
b10110101101111010010101111010101 +
b10100110000100110101 #
b10100110000100110101 *
b101011001000101010000110101101100100000001100100011010001011101 &
b11000 -
b11000 )
#241000
b1110 (
#250000
b10001010110110011010110100001001 !
b10001010110110011010110100001001 ,
1"
b11001 .
1%
b10001111101111000011010011111111 $
b10001111101111000011010011111111 +
b11111011000111010111100000001001 #
b11111011000111010111100000001001 *
b101011001000101010000110101101100100000001100100011010101011101 &
b11001 -
b11001 )
#251000
b1111 (
#260000
b1100000101011000010001110 !
b1100000101011000010001110 ,
b11010 .
0%
b1011111100010011000100000110111 $
b1011111100010011000100000110111 +
b10100001111110010010100001010111 #
b10100001111110010010100001010111 *
b101011001000101010000110101101100100000001100100011011001011101 &
b11010 -
b11010 )
#270000
b11001101010000010000000111100 !
b11001101010000010000000111100 ,
b11011 .
1%
b11010010110111010011101110000110 $
b11010010110111010011101110000110 +
b1000110110010101110010010110101 #
b1000110110010101110010010110101 *
b101011001000101010000110101101100100000001100100011011101011101 &
b11011 -
b11011 )
#280000
b1100010110101101100001001101011 !
b1100010110101101100001001101011 ,
0"
b11100 .
b1100001111001111100001101100010 $
b1100001111001111100001101100010 +
b111011101111111100001000 #
b111011101111111100001000 *
b101011001000101010000110101101100100000001100100011100001011101 &
b11100 -
b11100 )
#290000
b10000110001100101101000110101000 !
b10000110001100101101000110101000 ,
1"
b11101 .
b11100111101101001001111000100100 $
b11100111101101001001111000100100 +
b10011110011111100011001110000011 #
b10011110011111100011001110000011 *
b101011001000101010000110101101100100000001100100011100101011101 &
b11101 -
b11101 )
#300000
0"
b1000101010100001011110100111010 !
b1000101010100001011110100111010 ,
b11110 .
0%
b100000000000001111001111101100 $
b100000000000001111001111101100 +
b100101010011111100100101001110 #
b100101010011111100100101001110 *
b101011001000101010000110101101100100000001100110011000001011101 &
b11110 -
b11110 )
#310000
b100000100110100110000011101001 !
b100000100110100110000011101001 ,
1"
b11111 .
1%
b110111011110111011000101101100 $
b110111011110111011000101101100 +
b11101001000111101010111101111100 #
b11101001000111101010111101111100 *
b101011001000101010000110101101100100000001100110011000101011101 &
b11111 -
b11111 )
#320000
b1011100101010101010011000110111 !
b1011100101010101010011000110111 ,
b100000 .
0%
b10111110000011010000110010110101 $
b10111110000011010000110010110101 +
b10011110100111011001100110000010 #
b10011110100111011001100110000010 *
b101011001000101010000110101101100100000001100110011001001011101 &
b100000 -
b100000 )
#330000
b100101000010001001001001011010 !
b100101000010001001001001011010 ,
b100001 .
1%
b10000010000010001111110100100110 $
b10000010000010001111110100100110 +
b10100010111111111001010100110011 #
b10100010111111111001010100110011 *
b101011001000101010000110101101100100000001100110011001101011101 &
b100001 -
b100001 )
#340000
b1111010100100010111110111101101 !
b1111010100100010111110111101101 ,
0"
b100010 .
b11010000100011000101000101101 $
b11010000100011000101000101101 +
b1100000011111111111001110111111 #
b1100000011111111111001110111111 *
b101011001000101010000110101101100100000001100110011010001011101 &
b100010 -
b100010 )
#341000
b10000 (
#350000
b10100000011111010001000101111111 !
b10100000011111010001000101111111 ,
b100011 .
0%
b111010100001110001100010111011 $
b111010100001110001100010111011 +
b1100101111101011111100011000100 #
b1100101111101011111100011000100 *
b101011001000101010000110101101100100000001100110011010101011101 &
b100011 -
b100011 )
#351000
b10001 (
#360000
1"
b11011001010110010010001011000 !
b11011001010110010010001011000 ,
b100100 .
1%
b11110011001111101111101000001011 $
b11110011001111101111101000001011 +
b100111111011000010101001001100 #
b100111111011000010101001001100 *
b101011001000101010000110101101100100000001100110011011001011101 &
b100100 -
b100100 )
#361000
b10010 (
#370000
b1110010100011000101001101110001 !
b1110010100011000101001101110001 ,
b100101 .
b10010111100001100010001111101110 $
b10010111100001100010001111101110 +
b11011011000001100010111110000010 #
b11011011000001100010111110000010 *
b101011001000101010000110101101100100000001100110011011101011101 &
b100101 -
b100101 )
#380000
b10010101101100001101100111110101 !
b10010101101100001101100111110101 ,
0"
b100110 .
0%
b1000110001100010101100101100010 $
b1000110001100010101100101100010 +
b1001111011111111000000010010011 #
b1001111011111111000000010010011 *
b101011001000101010000110101101100100000001100110011100001011101 &
b100110 -
b100110 )
#390000
b1011001011010011111110001001110 !
b1011001011010011111110001001110 ,
b100111 .
1%
b110011110110001100011010110110 $
b110011110110001100011010110110 +
b100101100100010011010110010111 #
b100101100100010011010110010111 *
b101011001000101010000110101101100100000001100110011100101011101 &
b100111 -
b100111 )
#391000
b10011 (
#400000
1"
b1000011111111110010001110100011 !
b1000011111111110010001110100011 ,
b101000 .
b11011101110010011010100011100101 $
b11011101110010011010100011100101 +
b1100110001101010111101010111101 #
b1100110001101010111101010111101 *
b101011001000101010000110101101100100000001101000011000001011101 &
b101000 -
b101000 )
#401000
b10100 (
#410000
0"
b1000111001010010001111011000110 !
b1000111001010010001111011000110 ,
b101001 .
b11110000011000111111010000011 $
b11110000011000111111010000011 +
b101001000111001010000001000010 #
b101001000111001010000001000010 *
b101011001000101010000110101101100100000001101000011000101011101 &
b101001 -
b101001 )
#411000
b10101 (
#420000
b111011101111111100011110011001 !
b111011101111111100011110011001 ,
1"
b101010 .
0%
b1000011110010101110010010111011 $
b1000011110010101110010010111011 +
b11110111111101001110001011011110 #
b11110111111101001110001011011110 *
b101011001000101010000110101101100100000001101000011001001011101 &
b101010 -
b101010 )
#421000
b10110 (
#430000
b10111001101000101101011101111010 !
b10111001101000101101011101111010 ,
0"
b101011 .
1%
b1010010011000010001101011011000 $
b1010010011000010001101011011000 +
b1100111010000011011110010100001 #
b1100111010000011011110010100001 *
b101011001000101010000110101101100100000001101000011001101011101 &
b101011 -
b101011 )
#440000
b1011111101100110001111110001001 !
b1011111101100110001111110001001 ,
1"
b101100 .
b1100010000101111110000101001000 $
b1100010000101111110000101001000 +
b11111101100110110011111001000000 #
b11111101100110110011111001000000 *
b101011001000101010000110101101100100000001101000011010001011101 &
b101100 -
b101100 )
#441000
b10111 (
#450000
b100100010011011011110011000110 !
b100100010011011011110011000110 ,
b101101 .
0%
b10010110000010100110001110111001 $
b10010110000010100110001110111001 +
b10001110010000110101100100001101 #
b10001110010000110101100100001101 *
b101011001000101010000110101101100100000001101000011010101011101 &
b101101 -
b101101 )
#451000
b11000 (
#460000
b11000011110101101010110001110011 !
b11000011110101101010110001110011 ,
b101110 .
1%
b11000111100111000100100011111011 $
b11000111100111000100100011111011 +
b11111100001110100110001101110111 #
b11111100001110100110001101110111 *
b101011001000101010000110101101100100000001101000011011001011101 &
b101110 -
b101110 )
#470000
b10100111101010011011011010000010 !
b10100111101010011011011010000010 ,
b101111 .
b11010111101011100111111000000010 $
b11010111101011100111111000000010 +
b11001111111110110011100001111111 #
b11001111111110110011100001111111 *
b101011001000101010000110101101100100000001101000011011101011101 &
b101111 -
b101111 )
#471000
b11001 (
#480000
0"
b11000110101110111011010001101001 !
b11000110101110111011010001101001 ,
b110000 .
0%
b111001111001100011011010011101 $
b111001111001100011011010011101 +
b10001100110101010111110111001100 #
b10001100110101010111110111001100 *
b101011001000101010000110101101100100000001101000011100001011101 &
b110000 -
b110000 )
#481000
b11010 (
#490000
1"
b111010010110100000101010011101 !
b111010010110100000101010011101 ,
b110001 .
1%
b10100111101011010111010000011001 $
b10100111101011010111010000011001 +
b10010010101011001001011010000011 #
b10010010101011001001011010000011 *
b101011001000101010000110101101100100000001101000011100101011101 &
b110001 -
b110001 )
#500000
b1110011110010010110101110101000 !
b1110011110010010110101110101000 ,
0"
b110010 .
b1010011010001011000110010010001 $
b1010011010001011000110010010001 +
b100000100000111101111100010110 #
b100000100000111101111100010110 *
b101011001000101010000110101101100100000001101010011000001011101 &
b110010 -
b110010 )
#501000
b11011 (
#510000
1"
b110101100111111001111011101 !
b110101100111111001111011101 ,
b110011 .
b11001010111000010000010100011011 $
b11001010111000010000010100011011 +
b111011110100101110111011000001 #
b111011110100101110111011000001 *
b101011001000101010000110101101100100000001101010011000101011101 &
b110011 -
b110011 )
#511000
b11100 (
#520000
b1000000101100111011100100101 !
b1000000101100111011100100101 ,
b110100 .
0%
b101111111100101000010001011111 $
b101111111100101000010001011111 +
b11011000001000111111001011000110 #
b11011000001000111111001011000110 *
b101011001000101010000110101101100100000001101010011001001011101 &
b110100 -
b110100 )
#530000
b11000010110010001100100111011 !
b11000010110010001100100111011 ,
b110101 .
b101001010011001101100001000001 $
b101001010011001101100001000001 +
b11101111000011000100000011111010 #
b11101111000011000100000011111010 *
b101011001000101010000110101101100100000001101010011001101011101 &
b110101 -
b110101 )
#531000
b11101 (
#540000
b10110101100010101100010101001001 !
b10110101100010101100010101001001 ,
0"
b110110 .
b10101011101110010011001111110011 $
b10101011101110010011001111110011 +
b1001110100011001000101010110 #
b1001110100011001000101010110 *
b101011001000101010000110101101100100000001101010011010001011101 &
b110110 -
b110110 )
#550000
b11011001011010001100010011010101 !
b11011001011010001100010011010101 ,
b110111 .
b1111010111101101111000011001000 $
b1111010111101101111000011001000 +
b1011110011100011101010000001101 #
b1011110011100011101010000001101 *
b101011001000101010000110101101100100000001101010011010101011101 &
b110111 -
b110111 )
#560000
b101011010100001110110101110000 !
b101011010100001110110101110000 ,
b111000 .
b101001010001111111101001100101 $
b101001010001111111101001100101 +
b10000010001111001100001011 #
b10000010001111001100001011 *
b101011001000101010000110101101100100000001101010011011001011101 &
b111000 -
b111000 )
#570000
b11110001001100110001010110110101 !
b11110001001100110001010110110101 ,
b111001 .
b111001010001001100001100001000 $
b111001010001001100001100001000 +
b10110111111011100101001010101101 #
b10110111111011100101001010101101 *
b101011001000101010000110101101100100000001101010011011101011101 &
b111001 -
b111001 )
#571000
b11110 (
#580000
1"
b1101000000011011110101110100 !
b1101000000011011110101110100 ,
b111010 .
1%
b11000110001010110001111110010110 $
b11000110001010110001111110010110 +
b1000110110101101001110111011101 #
b1000110110101101001110111011101 *
b101011001000101010000110101101100100000001101010011100001011101 &
b111010 -
b111010 )
#581000
b11111 (
#590000
0"
b10000101001001100011110100010011 !
b10000101001001100011110100010011 ,
b111011 .
0%
b111101000000110100010001010010 $
b111101000000110100010001010010 +
b1001000001000101111100011000001 #
b1001000001000101111100011000001 *
b101011001000101010000110101101100100000001101010011100101011101 &
b111011 -
b111011 )
#600000
b10000111110110110010001111001001 !
b10000111110110110010001111001001 ,
1"
b111100 .
b10110110010110000011100011011010 $
b10110110010110000011100011011010 +
b11010001100000101110101011101111 #
b11010001100000101110101011101111 *
b101011001000101010000110101101100100000001101100011000001011101 &
b111100 -
b111100 )
#601000
b100000 (
#610000
0"
b11110100101001101001011111000010 !
b11110100101001101001011111000010 ,
b111101 .
b10001110011011100100111101010000 $
b10001110011011100100111101010000 +
b1100110001110000100100001110010 #
b1100110001110000100100001110010 *
b101011001000101010000110101101100100000001101100011000101011101 &
b111101 -
b111101 )
#620000
b1100101000011001110100110111110 !
b1100101000011001110100110111110 ,
b111110 .
1%
b10010110000100010010101001111 $
b10010110000100010010101001111 +
b1010010010010101100010001101110 #
b1010010010010101100010001101110 *
b101011001000101010000110101101100100000001101100011001001011101 &
b111110 -
b111110 )
#630000
1"
b1101110010001010111100010110111 !
b1101110010001010111100010110111 ,
b111111 .
0%
b11100001001001011110000000101110 $
b11100001001001011110000000101110 +
b10001101000111111001100010001001 #
b10001101000111111001100010001001 *
b101011001000101010000110101101100100000001101100011001101011101 &
b111111 -
b111111 )
#631000
b100001 (
#640000
b10001001100111101111101111011 !
b10001001100111101111101111011 ,
b1000000 .
b11110111001111111010011011101011 $
b11110111001111111010011011101011 +
b11001111101000011100010010000 #
b11001111101000011100010010000 *
b101011001000101010000110101101100100000001101100011010001011101 &
b1000000 -
b1000000 )
#641000
b100010 (
#650000
b1001110100101000101111010001 !
b1001110100101000101111010001 ,
b1000001 .
1%
b1100010100101010001011011001 $
b1100010100101010001011011001 +
b11111101011111111110100011110111 #
b11111101011111111110100011110111 *
b101011001000101010000110101101100100000001101100011010101011101 &
b1000001 -
b1000001 )
#660000
b100110010011001010011110110110 !
b100110010011001010011110110110 ,
b1000010 .
0%
b110011101000011110110110100110 $
b110011101000011110110110100110 +
b11110010101010101011101000010000 #
b11110010101010101011101000010000 *
b101011001000101010000110101101100100000001101100011011001011101 &
b1000010 -
b1000010 )
#670000
b111000101111010000010101100101 !
b111000101111010000010101100101 ,
b1000011 .
1%
b1110011000111110001000101011011 $
b1110011000111110001000101011011 +
b11000101100111011111010000001001 #
b11000101100111011111010000001001 *
b101011001000101010000110101101100100000001101100011011101011101 &
b1000011 -
b1000011 )
#671000
b100011 (
#680000
b1001011010010011011001010101100 !
b1001011010010011011001010101100 ,
0"
b1000100 .
0%
b10100011000100111001011111111 $
b10100011000100111001011111111 +
b110110111001110011111110101101 #
b110110111001110011111110101101 *
b101011001000101010000110101101100100000001101100011100001011101 &
b1000100 -
b1000100 )
#681000
b100100 (
#690000
1"
b101100111000010011100100001111 !
b101100111000010011100100001111 ,
b1000101 .
1%
b10011000011001010010110101101110 $
b10011000011001010010110101101110 +
b10010100011111000000101110100000 #
b10010100011111000000101110100000 *
b101011001000101010000110101101100100000001101100011100101011101 &
b1000101 -
b1000101 )
#691000
b100101 (
#700000
0"
b10101111001111010010100010111001 !
b10101111001111010010100010111001 ,
b1000110 .
b1001011010101100101111011111 $
b1001011010101100101111011111 +
b10100101110100100101110011011001 #
b10100101110100100101110011011001 *
b101011001000101010000110101101100100000001101110011000001011101 &
b1000110 -
b1000110 )
#701000
b100110 (
#710000
1"
b11010100100001111011011010110100 !
b11010100100001111011011010110100 ,
b1000111 .
b11111100011011100001010111001011 $
b11111100011011100001010111001011 +
b11011000000110011010000011101000 #
b11011000000110011010000011101000 *
b101011001000101010000110101101100100000001101110011000101011101 &
b1000111 -
b1000111 )
#711000
b100111 (
#720000
0"
b10110110000010110111011001100000 !
b10110110000010110111011001100000 ,
b1001000 .
b10011110010001110011100100100 $
b10011110010001110011100100100 +
b10100010010000101000111100111011 #
b10100010010000101000111100111011 *
b101011001000101010000110101101100100000001101110011001001011101 &
b1001000 -
b1001000 )
#721000
b101000 (
#730000
b11010110000010011011100100101111 !
b11010110000010011011100100101111 ,
b1001001 .
b1001001000000010110111100101111 $
b1001001000000010110111100101111 +
b10001101000010000100100111111111 #
b10001101000010000100100111111111 *
b101011001000101010000110101101100100000001101110011001101011101 &
b1001001 -
b1001001 )
#731000
b101001 (
#740000
b11100100000000101110110110111010 !
b11100100000000101110110110111010 ,
b1001010 .
0%
b1110011001011000011000011011010 $
b1110011001011000011000011011010 +
b1110000110101101011110011100000 #
b1110000110101101011110011100000 *
b101011001000101010000110101101100100000001101110011010001011101 &
b1001010 -
b1001010 )
#750000
b11000111110011000111010000001010 !
b11000111110011000111010000001010 ,
b1001011 .
b1111110001111100101111100111100 $
b1111110001111100101111100111100 +
b1001001100011100001010011001110 #
b1001001100011100001010011001110 *
b101011001000101010000110101101100100000001101110011010101011101 &
b1001011 -
b1001011 )
#760000
b10001110101000011010101000001111 !
b10001110101000011010101000001111 ,
1"
b1001100 .
1%
b11111010011001010000001111110111 $
b11111010011001010000001111110111 +
b10010100001111001010011000010111 #
b10010100001111001010011000010111 *
b101011001000101010000110101101100100000001101110011011001011101 &
b1001100 -
b1001100 )
#761000
b101010 (
#770000
b1011011101101100001101001010111 !
b1011011101101100001101001010111 ,
b1001101 .
0%
b11011010111101110000101010011011 $
b11011010111101110000101010011011 +
b10000000101111110000111110111100 #
b10000000101111110000111110111100 *
b101011001000101010000110101101100100000001101110011011101011101 &
b1001101 -
b1001101 )
#780000
b1101100001100010011100010111010 !
b1101100001100010011100010111010 ,
b1001110 .
1%
b10111001101100100000101111010011 $
b10111001101100100000101111010011 +
b10110010011111110010110011100110 #
b10110010011111110010110011100110 *
b101011001000101010000110101101100100000001101110011100001011101 &
b1001110 -
b1001110 )
#781000
b101011 (
#790000
b1101001100011011111000010010010 !
b1101001100011011111000010010010 ,
b1001111 .
0%
b11100011010010100110001011111101 $
b11100011010010100110001011111101 +
b10000110010000111000110110010101 #
b10000110010000111000110110010101 *
b101011001000101010000110101101100100000001101110011100101011101 &
b1001111 -
b1001111 )
#791000
b101100 (
#800000
0"
b11101010110000011101101000110011 !
b11101010110000011101101000110011 ,
b1010000 .
1%
b1110101100111110011100000110011 $
b1110101100111110011100000110011 +
b1110101001000101010000111111111 #
b1110101001000101010000111111111 *
b101011001000101010000110101101100100000001110000011000001011101 &
b1010000 -
b1010000 )
#801000
b101101 (
#810000
b10101100100011001011001000010100 !
b10101100100011001011001000010100 ,
b1010001 .
b10000100000110110011010101111100 $
b10000100000110110011010101111100 +
b101000011100010111110010010111 #
b101000011100010111110010010111 *
b101011001000101010000110101101100100000001110000011000101011101 &
b1010001 -
b1010001 )
#820000
b10100100111000011101110001000000 !
b10100100111000011101110001000000 ,
b1010010 .
0%
b101000101010111110100101110001 $
b101000101010111110100101110001 +
b1111100001101011111001011001111 #
b1111100001101011111001011001111 *
b101011001000101010000110101101100100000001110000011001001011101 &
b1010010 -
b1010010 )
#821000
b101110 (
#830000
1"
b1000110101001111010111100011001 !
b1000110101001111010111100011001 ,
b1010011 .
1%
b10100110011111101101111110100101 $
b10100110011111101101111110100101 +
b10100000001010001100111101110011 #
b10100000001010001100111101110011 *
b101011001000101010000110101101100100000001110000011001101011101 &
b1010011 -
b1010011 )
#831000
b101111 (
#840000
b101011110011010000001110101111 !
b101011110011010000001110101111 ,
b1010100 .
0%
b110010100101011011010101100011 $
b110010100101011011010101100011 +
b11111001001101110100111001001100 #
b11111001001101110100111001001100 *
b101011001000101010000110101101100100000001110000011010001011101 &
b1010100 -
b1010100 )
#841000
b110000 (
#850000
b1011101110101111101000110101 !
b1011101110101111101000110101 ,
b1010101 .
1%
b11110001110001000100100100000011 $
b11110001110001000100100100000011 +
b11001111101101011000100110001 #
b11001111101101011000100110001 *
b101011001000101010000110101101100100000001110000011010101011101 &
b1010101 -
b1010101 )
#860000
0"
b11110110001110011001010110100001 !
b11110110001110011001010110100001 ,
b1010110 .
b10001101011001100100110001101111 $
b10001101011001100100110001101111 +
b1101000110100110100100100110001 #
b1101000110100110100100100110001 *
b101011001000101010000110101101100100000001110000011011001011101 &
b1010110 -
b1010110 )
