01_basics/03_parameterized_adder/adder.v
// ==================================================
//	[ VLSISYS Lab. ]
//	* Filename		: adder.v
//	* Author		: Woong Choi (woongchoi@sm.ac.kr)
//	* Description	: 
//		- Key Points
//			1. Parameterized Module
//			2. Multibit Expression
//			3. 'assign'-based Description
//			4. Concatenation & Operand
// ==================================================

module	adder
#(	
	parameter	NBIT		= 8
)
(	
	output 		[NBIT-1:0]	o_s,
	output 			 	  	o_c,
	input		[NBIT-1:0]	i_a,
	input		[NBIT-1:0]	i_b,
	input					i_c
);

	assign		{o_c, o_s} = i_a + i_b + i_c;

endmodule

01_basics/03_parameterized_adder/adder_tb.v
// ==================================================
//	[ VLSISYS Lab. ]
//	* Filename		: adder_tb.v
//	* Author		: Woong Choi (woongchoi@sm.ac.kr)
//	* Description	: 
//		- Key Points
//			1. 
//			2. 
// ==================================================

// --------------------------------------------------
//	Define Global Variables
// --------------------------------------------------
`define	CLKFREQ		100		// Unit: MHz
`define	SIMCYCLE	10
`define NBIT		8

`include	"adder.v"

module	adder_tb;
// --------------------------------------------------
//	DUT Signals & Instantiate
// --------------------------------------------------
	wire 	[`NBIT-1:0]		o_s;
	wire 	 				o_c;
	reg		[`NBIT-1:0]		i_a;
	reg		[`NBIT-1:0]		i_b;
	reg						i_c;

	adder
	#(
		.NBIT		(`NBIT		)
	)
	u_adder
	(
		.o_s		(o_s		),
		.o_c		(o_c		),
		.i_a		(i_a		),
		.i_b		(i_b		),
		.i_c		(i_c		)
	);

// --------------------------------------------------
//	Test Stimulus
// --------------------------------------------------
	integer		i, j, k, n;
	initial begin
		for (i=0; i<`SIMCYCLE; i++) begin
			i_a = $urandom_range(0, 2**`NBIT-1);
			i_b = $urandom_range(0, 2**`NBIT-1);
			i_c = $urandom_range(0, 1);
			#(1000/`CLKFREQ);
		end
		$finish;
	end

	reg	[8*32-1:0]	vcd_file;
	initial begin
		if ($value$plusargs("vcd_file=%s", vcd_file)) begin
			$dumpfile(vcd_file);
			$dumpvars;
		end else begin
			$dumpfile("adder_tb.vcd");
			$dumpvars;
		end
	end

endmodule

01_basics/03_parameterized_adder/vcd/adder.vcd
$date
	Fri May  3 10:33:07 2024
$end
$version
	Icarus Verilog
$end
$timescale
	1ps
$end
$scope module adder_tb $end
$var wire 8 ! o_s [7:0] $end
$var wire 1 " o_c $end
$var reg 8 # i_a [7:0] $end
$var reg 8 $ i_b [7:0] $end
$var reg 1 % i_c $end
$var reg 256 & vcd_file [255:0] $end
$var integer 32 ' i [31:0] $end
$scope module u_adder $end
$var wire 8 ( i_a [7:0] $end
$var wire 8 ) i_b [7:0] $end
$var wire 1 % i_c $end
$var wire 8 * o_s [7:0] $end
$var wire 1 " o_c $end
$upscope $end
$upscope $end
$enddefinitions $end
#0
$dumpvars
b11010010 *
b1000000 )
b10010010 (
b0 '
b1011100010111101110110011000110110010000101111011000010110010001100100011001010111001000101110011101100110001101100100 &
0%
b1000000 $
b10010010 #
0"
b11010010 !
$end
#10000
b10111000 !
b10111000 *
1%
b10000110 $
b10000110 )
b110001 #
b110001 (
b1 '
#20000
b111100 !
b111100 *
b1001 $
b1001 )
b110010 #
b110010 (
b10 '
#30000
1"
b1000010 !
b1000010 *
b10111011 $
b10111011 )
b10000110 #
b10000110 (
b11 '
#40000
b10111101 !
b10111101 *
b11000110 $
b11000110 )
b11110110 #
b11110110 (
b100 '
#50000
0"
b11000101 !
b11000101 *
0%
b1100010 $
b1100010 )
b1100011 #
b1100011 (
b101 '
#60000
b101101 !
b101101 *
1"
b111011 $
b111011 )
b11110010 #
b11110010 (
b110 '
#70000
b11000000 !
b11000000 *
b11111001 $
b11111001 )
b11000111 #
b11000111 (
b111 '
#80000
0"
b11010111 !
b11010111 *
1%
b1100010 $
b1100010 )
b1110100 #
b1110100 (
b1000 '
#90000
b1110100 !
b1110100 *
0%
b10110 $
b10110 )
b1011110 #
b1011110 (
b1001 '
#100000
b1010 '
