random_clock/lfsr.v
// ==================================================
//	[ VLSISYS Lab. ]
//	* Author		: Woong Choi (woongchoi@sm.ac.kr)
//	* Filename		: lfsr.v
//	* Date			: 2024-07-07 18:52:17
//	* Description	: 
// ==================================================

module lfsr8
#(	
	parameter	SEED		= 8'd1
)
(	
	output reg	[7:0]		o_lfsr,
	input					i_clk,
	input					i_rstn
);

	always @(posedge i_clk or negedge i_rstn) begin
		if(!i_rstn) begin
			o_lfsr	<= SEED;
		end else begin
			o_lfsr	<= {o_lfsr[6:0], o_lfsr[1] ^ o_lfsr[2] ^ o_lfsr[3] ^ o_lfsr[7]};
		end
	end

endmodule

module lfsr3
#(	
	parameter	SEED		= 3'd1
)
(	
	output reg	[2:0]		o_lfsr,
	input					i_clk,
	input					i_rstn
);

	always @(posedge i_clk or negedge i_rstn) begin
		if(!i_rstn) begin
			o_lfsr	<= SEED;
		end else begin
			o_lfsr	<= {o_lfsr[1:0], o_lfsr[0] ^ o_lfsr[2]};
		end
	end

endmodule

random_clock/rnd_clk_gen.v
// ==================================================
//	[ VLSISYS Lab. ]
//	* Author		: Woong Choi (woongchoi@sm.ac.kr)
//	* Filename		: rand_clk_gen.v
//	* Date			: 2024-07-07 19:09:48
//	* Description	: 
// ==================================================

`include	"lfsr.v"

module rand_clk_gen
#(	
	parameter	SEED		= 8'd1
)
(	
	output reg				o_rnd_clk,
	input					i_clk,
	input					i_rstn
);

	wire	[2:0]			lfsr3;
	wire	[7:0]			lfsr8;
	wire					mux_o;

	lfsr3
	#(
		.SEED				(SEED				)
	)
	u_lfsr3(
		.o_lfsr				(lfsr3				),
		.i_clk				(i_clk				),
		.i_rstn				(i_rstn				)
	);

	lfsr8
	#(
		.SEED				(SEED				)
	)
	u_lfsr8(
		.o_lfsr				(lfsr8				),
		.i_clk				(i_clk				),
		.i_rstn				(i_rstn				)
	);

	assign	mux_o = lfsr8[lfsr3] ? ~o_rnd_clk : o_rnd_clk;

	always @(posedge i_clk or negedge i_rstn) begin
		if(!i_rstn) begin
			o_rnd_clk	<= 1'b0;
		end else begin
			o_rnd_clk	<= mux_o;
		end
	end

endmodule

random_clock/rnd_clk_gen_tb.v
// ==================================================
//	[ VLSISYS Lab. ]
//	* Author		: Woong Choi (woongchoi@sm.ac.kr)
//	* Filename		: rnd_clk_gen_tb.v
//	* Date			: 2024-07-07 19:15:04
//	* Description	: 
// ==================================================

// --------------------------------------------------
//	Define Global Variables
// --------------------------------------------------
`define	CLKFREQ		100		// Clock Freq. (Unit: MHz)
`define	SIMCYCLE	`NVEC	// Sim. Cycles
`define NVEC		1500		// # of Test Vector

// --------------------------------------------------
//	Includes
// --------------------------------------------------
`include	"rnd_clk_gen.v"

module rnd_clk_gen_tb;
// --------------------------------------------------
//	DUT Signals & Instantiate
// --------------------------------------------------
	wire				o_rnd_clk;
	reg					i_clk;
	reg					i_rstn;

	rand_clk_gen
	#(
		.SEED				(1					)
	)
	u_rand_clk_gen(
		.o_rnd_clk			(o_rnd_clk			),
		.i_clk				(i_clk				),
		.i_rstn				(i_rstn				)
	);

// --------------------------------------------------
//	Clock
// --------------------------------------------------
	always #(500/`CLKFREQ) i_clk = ~i_clk;

// --------------------------------------------------
//	Tasks
// --------------------------------------------------
	task	init;
		begin
			i_clk	= 0;
			i_rstn	= 0;
			#(4*1000/`CLKFREQ);
			i_rstn	= 1;
		end
	endtask

// --------------------------------------------------
//	Test Stimulus
// --------------------------------------------------
	integer		i, j;
	initial begin
		init();

		for (i=0; i<`SIMCYCLE; i++) begin
			$display("IDX[%3d] - LFSR3: %b(%d), LFSR8: %b(%d)", i,
														u_rand_clk_gen.lfsr3, u_rand_clk_gen.lfsr3, 
														u_rand_clk_gen.lfsr8, u_rand_clk_gen.lfsr8
													);
			#(1000/`CLKFREQ);
		end
		#(1000/`CLKFREQ);
		$finish;
	end

// --------------------------------------------------
//	Dump VCD
// --------------------------------------------------
	reg	[8*32-1:0]	vcd_file;
	initial begin
		if ($value$plusargs("vcd_file=%s", vcd_file)) begin
			$dumpfile(vcd_file);
			$dumpvars;
		end else begin
			$dumpfile("rnd_clk_gen_tb.vcd");
			$dumpvars;
		end
	end

endmodule

random_clock/vcd/rnd_clk_gen.vcd
$date
	Mon Jul  8 21:23:34 2024
$end
$version
	Icarus Verilog
$end
$timescale
	1ps
$end
$scope module rnd_clk_gen_tb $end
$var wire 1 ! o_rnd_clk $end
$var reg 1 " i_clk $end
$var reg 1 # i_rstn $end
$var reg 256 $ vcd_file [255:0] $end
$var integer 32 % i [31:0] $end
$scope module u_rand_clk_gen $end
$var wire 1 " i_clk $end
$var wire 1 # i_rstn $end
$var wire 1 & mux_o $end
$var wire 8 ' lfsr8 [7:0] $end
$var wire 3 ( lfsr3 [2:0] $end
$var reg 1 ! o_rnd_clk $end
$scope module u_lfsr3 $end
$var wire 1 " i_clk $end
$var wire 1 # i_rstn $end
$var reg 3 ) o_lfsr [2:0] $end
$upscope $end
$scope module u_lfsr8 $end
$var wire 1 " i_clk $end
$var wire 1 # i_rstn $end
$var reg 8 * o_lfsr [7:0] $end
$upscope $end
$upscope $end
$scope task init $end
$upscope $end
$upscope $end
$enddefinitions $end
#0
$dumpvars
b1 *
b1 )
b1 (
b1 '
0&
bx %
b1011100010111101110110011000110110010000101111011100100110111001100100010111110110001101101100011010110101111101100111011001010110111000101110011101100110001101100100 $
0#
0"
0!
$end
#5000
1"
#10000
0"
#15000
1"
#20000
0"
#25000
1"
#30000
0"
#35000
1"
#40000
0"
b0 %
1#
#45000
b10 '
b10 *
b11 (
b11 )
1"
#50000
0"
b1 %
#55000
b111 (
b111 )
b101 '
b101 *
1"
#60000
0"
b10 %
#65000
b1011 '
b1011 *
b110 (
b110 )
1"
#70000
0"
b11 %
#75000
b101 (
b101 )
b10110 '
b10110 *
1"
#80000
0"
b100 %
#85000
1&
b101100 '
b101100 *
b10 (
b10 )
1"
#90000
0"
b101 %
#95000
0&
b100 (
b100 )
b1011000 '
b1011000 *
1!
1"
#100000
0"
b110 %
#105000
0!
b10110001 '
b10110001 *
b1 (
b1 )
1"
#110000
0"
b111 %
#115000
b11 (
b11 )
b1100011 '
b1100011 *
1"
#120000
0"
b1000 %
#125000
1&
b11000111 '
b11000111 *
b111 (
b111 )
1"
#130000
0"
b1001 %
#135000
b110 (
b110 )
b10001111 '
b10001111 *
1!
1"
#140000
0"
b1010 %
#145000
b11110 '
b11110 *
b101 (
b101 )
1"
#150000
0"
b1011 %
#155000
0&
b10 (
b10 )
b111101 '
b111101 *
1"
#160000
0"
b1100 %
#165000
1&
0!
b1111010 '
b1111010 *
b100 (
b100 )
1"
#170000
0"
b1101 %
#175000
b1 (
b1 )
b11110100 '
b11110100 *
1!
1"
#180000
0"
b1110 %
#185000
0&
b11101000 '
b11101000 *
b11 (
b11 )
1"
#190000
0"
b1111 %
#195000
1&
b111 (
b111 )
b11010000 '
b11010000 *
0!
1"
#200000
0"
b10000 %
#205000
1!
b10100001 '
b10100001 *
b110 (
b110 )
1"
#210000
0"
b10001 %
#215000
b101 (
b101 )
b1000011 '
b1000011 *
1"
#220000
0"
b10010 %
#225000
0&
b10000111 '
b10000111 *
b10 (
b10 )
1"
#230000
0"
b10011 %
#235000
b100 (
b100 )
b1111 '
b1111 *
0!
1"
#240000
0"
b10100 %
#245000
1&
b11111 '
b11111 *
b1 (
b1 )
1"
#250000
0"
b10101 %
#255000
0&
b11 (
b11 )
b111111 '
b111111 *
1!
1"
#260000
0"
b10110 %
#265000
0!
b1111111 '
b1111111 *
b111 (
b111 )
1"
#270000
0"
b10111 %
#275000
1&
b110 (
b110 )
b11111111 '
b11111111 *
1"
#280000
0"
b11000 %
#285000
0&
1!
b11111110 '
b11111110 *
b101 (
b101 )
1"
#290000
0"
b11001 %
#295000
1&
b10 (
b10 )
b11111100 '
b11111100 *
0!
1"
#300000
0"
b11010 %
#305000
0&
1!
b11111001 '
b11111001 *
b100 (
b100 )
1"
#310000
0"
b11011 %
#315000
1&
b1 (
b1 )
b11110010 '
b11110010 *
0!
1"
#320000
0"
b11100 %
#325000
1!
b11100100 '
b11100100 *
b11 (
b11 )
1"
#330000
0"
b11101 %
#335000
0&
b111 (
b111 )
b11001000 '
b11001000 *
1"
#340000
0"
b11110 %
#345000
0!
b10010000 '
b10010000 *
b110 (
b110 )
1"
#350000
0"
b11111 %
#355000
1&
b101 (
b101 )
b100001 '
b100001 *
1"
#360000
0"
b100000 %
#365000
1!
b1000010 '
b1000010 *
b10 (
b10 )
1"
#370000
0"
b100001 %
#375000
b100 (
b100 )
b10000101 '
b10000101 *
1"
#380000
0"
b100010 %
#385000
0&
b1010 '
b1010 *
b1 (
b1 )
1"
#390000
0"
b100011 %
#395000
b11 (
b11 )
b10100 '
b10100 *
0!
1"
#400000
0"
b100100 %
#405000
b101001 '
b101001 *
b111 (
b111 )
1"
#410000
0"
b100101 %
#415000
1&
b110 (
b110 )
b1010011 '
b1010011 *
1"
#420000
0"
b100110 %
#425000
0&
1!
b10100111 '
b10100111 *
b101 (
b101 )
1"
#430000
0"
b100111 %
#435000
1&
b10 (
b10 )
b1001111 '
b1001111 *
0!
1"
#440000
0"
b101000 %
#445000
0&
1!
b10011111 '
b10011111 *
b100 (
b100 )
1"
#450000
0"
b101001 %
#455000
1&
b1 (
b1 )
b111110 '
b111110 *
0!
1"
#460000
0"
b101010 %
#465000
0&
1!
b1111101 '
b1111101 *
b11 (
b11 )
1"
#470000
0"
b101011 %
#475000
1&
b111 (
b111 )
b11111010 '
b11111010 *
0!
1"
#480000
0"
b101100 %
#485000
0&
1!
b11110101 '
b11110101 *
b110 (
b110 )
1"
#490000
0"
b101101 %
#495000
1&
b101 (
b101 )
b11101010 '
b11101010 *
0!
1"
#500000
0"
b101110 %
#505000
0&
1!
b11010101 '
b11010101 *
b10 (
b10 )
1"
#510000
0"
b101111 %
#515000
b100 (
b100 )
b10101010 '
b10101010 *
0!
1"
#520000
0"
b110000 %
#525000
b1010101 '
b1010101 *
b1 (
b1 )
1"
#530000
0"
b110001 %
#535000
1&
b11 (
b11 )
b10101011 '
b10101011 *
1"
#540000
0"
b110010 %
#545000
1!
b1010111 '
b1010111 *
b111 (
b111 )
1"
#550000
0"
b110011 %
#555000
b110 (
b110 )
b10101110 '
b10101110 *
1"
#560000
0"
b110100 %
#565000
b1011100 '
b1011100 *
b101 (
b101 )
1"
#570000
0"
b110101 %
#575000
b10 (
b10 )
b10111000 '
b10111000 *
1"
#580000
0"
b110110 %
#585000
0&
b1110000 '
b1110000 *
b100 (
b100 )
1"
#590000
0"
b110111 %
#595000
b1 (
b1 )
b11100000 '
b11100000 *
0!
1"
#600000
0"
b111000 %
#605000
b11000001 '
b11000001 *
b11 (
b11 )
1"
#610000
0"
b111001 %
#615000
1&
b111 (
b111 )
b10000011 '
b10000011 *
1"
#620000
0"
b111010 %
#625000
1!
b110 '
b110 *
b110 (
b110 )
1"
#630000
0"
b111011 %
#635000
b101 (
b101 )
b1100 '
b1100 *
1"
#640000
0"
b111100 %
#645000
b11000 '
b11000 *
b10 (
b10 )
1"
#650000
0"
b111101 %
#655000
0&
b100 (
b100 )
b110001 '
b110001 *
1"
#660000
0"
b111110 %
#665000
1&
0!
b1100010 '
b1100010 *
b1 (
b1 )
1"
#670000
0"
b111111 %
#675000
b11 (
b11 )
b11000101 '
b11000101 *
1!
1"
#680000
0"
b1000000 %
#685000
0&
b10001010 '
b10001010 *
b111 (
b111 )
1"
#690000
0"
b1000001 %
#695000
b110 (
b110 )
b10101 '
b10101 *
0!
1"
#700000
0"
b1000010 %
#705000
1&
b101011 '
b101011 *
b101 (
b101 )
1"
#710000
0"
b1000011 %
#715000
0&
b10 (
b10 )
b1010110 '
b1010110 *
1!
1"
#720000
0"
b1000100 %
#725000
0!
b10101100 '
b10101100 *
b100 (
b100 )
1"
#730000
0"
b1000101 %
#735000
b1 (
b1 )
b1011001 '
b1011001 *
1"
#740000
0"
b1000110 %
#745000
b10110011 '
b10110011 *
b11 (
b11 )
1"
#750000
0"
b1000111 %
#755000
b111 (
b111 )
b1100110 '
b1100110 *
1"
#760000
0"
b1001000 %
#765000
1&
b11001100 '
b11001100 *
b110 (
b110 )
1"
#770000
0"
b1001001 %
#775000
b101 (
b101 )
b10011001 '
b10011001 *
1!
1"
#780000
0"
b1001010 %
#785000
b110010 '
b110010 *
b10 (
b10 )
1"
#790000
0"
b1001011 %
#795000
b100 (
b100 )
b1100101 '
b1100101 *
1"
#800000
0"
b1001100 %
#805000
0&
b11001011 '
b11001011 *
b1 (
b1 )
1"
#810000
0"
b1001101 %
#815000
b11 (
b11 )
b10010111 '
b10010111 *
0!
1"
#820000
0"
b1001110 %
#825000
b101111 '
b101111 *
b111 (
b111 )
1"
#830000
0"
b1001111 %
#835000
1&
b110 (
b110 )
b1011111 '
b1011111 *
1"
#840000
0"
b1010000 %
#845000
0&
1!
b10111111 '
b10111111 *
b101 (
b101 )
1"
#850000
0"
b1010001 %
#855000
1&
b10 (
b10 )
b1111110 '
b1111110 *
0!
1"
#860000
0"
b1010010 %
#865000
0&
1!
b11111101 '
b11111101 *
b100 (
b100 )
1"
#870000
0"
b1010011 %
#875000
1&
b1 (
b1 )
b11111011 '
b11111011 *
0!
1"
#880000
0"
b1010100 %
#885000
1!
b11110111 '
b11110111 *
b11 (
b11 )
1"
#890000
0"
b1010101 %
#895000
0&
b111 (
b111 )
b11101111 '
b11101111 *
1"
#900000
0"
b1010110 %
#905000
1&
0!
b11011110 '
b11011110 *
b110 (
b110 )
1"
#910000
0"
b1010111 %
#915000
0&
b101 (
b101 )
b10111100 '
b10111100 *
1!
1"
#920000
0"
b1011000 %
#925000
0!
b1111001 '
b1111001 *
b10 (
b10 )
1"
#930000
0"
b1011001 %
#935000
1&
b100 (
b100 )
b11110011 '
b11110011 *
1"
#940000
0"
b1011010 %
#945000
0&
1!
b11100110 '
b11100110 *
b1 (
b1 )
1"
#950000
0"
b1011011 %
#955000
1&
b11 (
b11 )
b11001101 '
b11001101 *
0!
1"
#960000
0"
b1011100 %
#965000
0&
1!
b10011011 '
b10011011 *
b111 (
b111 )
1"
#970000
0"
b1011101 %
#975000
b110 (
b110 )
b110111 '
b110111 *
0!
1"
#980000
0"
b1011110 %
#985000
1&
b1101110 '
b1101110 *
b101 (
b101 )
1"
#990000
0"
b1011111 %
#995000
0&
b10 (
b10 )
b11011101 '
b11011101 *
1!
1"
#1000000
0"
b1100000 %
#1005000
1&
0!
b10111011 '
b10111011 *
b100 (
b100 )
1"
#1010000
0"
b1100001 %
#1015000
0&
b1 (
b1 )
b1110111 '
b1110111 *
1!
1"
#1020000
0"
b1100010 %
#1025000
1&
0!
b11101110 '
b11101110 *
b11 (
b11 )
1"
#1030000
0"
b1100011 %
#1035000
0&
b111 (
b111 )
b11011100 '
b11011100 *
1!
1"
#1040000
0"
b1100100 %
#1045000
0!
b10111001 '
b10111001 *
b110 (
b110 )
1"
#1050000
0"
b1100101 %
#1055000
1&
b101 (
b101 )
b1110010 '
b1110010 *
1"
#1060000
0"
b1100110 %
#1065000
0&
1!
b11100101 '
b11100101 *
b10 (
b10 )
1"
#1070000
0"
b1100111 %
#1075000
b100 (
b100 )
b11001010 '
b11001010 *
0!
1"
#1080000
0"
b1101000 %
#1085000
b10010101 '
b10010101 *
b1 (
b1 )
1"
#1090000
0"
b1101001 %
#1095000
1&
b11 (
b11 )
b101010 '
b101010 *
1"
#1100000
0"
b1101010 %
#1105000
1!
b1010100 '
b1010100 *
b111 (
b111 )
1"
#1110000
0"
b1101011 %
#1115000
b110 (
b110 )
b10101001 '
b10101001 *
1"
#1120000
0"
b1101100 %
#1125000
b1010010 '
b1010010 *
b101 (
b101 )
1"
#1130000
0"
b1101101 %
#1135000
0&
b10 (
b10 )
b10100101 '
b10100101 *
1"
#1140000
0"
b1101110 %
#1145000
0!
b1001010 '
b1001010 *
b100 (
b100 )
1"
#1150000
0"
b1101111 %
#1155000
b1 (
b1 )
b10010100 '
b10010100 *
1"
#1160000
0"
b1110000 %
#1165000
1&
b101000 '
b101000 *
b11 (
b11 )
1"
#1170000
0"
b1110001 %
#1175000
b111 (
b111 )
b1010001 '
b1010001 *
1!
1"
#1180000
0"
b1110010 %
#1185000
b10100010 '
b10100010 *
b110 (
b110 )
1"
#1190000
0"
b1110011 %
#1195000
b101 (
b101 )
b1000100 '
b1000100 *
1"
#1200000
0"
b1110100 %
#1205000
b10001001 '
b10001001 *
b10 (
b10 )
1"
#1210000
0"
b1110101 %
#1215000
0&
b100 (
b100 )
b10010 '
b10010 *
1"
#1220000
0"
b1110110 %
#1225000
0!
b100101 '
b100101 *
b1 (
b1 )
1"
#1230000
0"
b1110111 %
#1235000
1&
b11 (
b11 )
b1001011 '
b1001011 *
1"
#1240000
0"
b1111000 %
#1245000
0&
1!
b10010110 '
b10010110 *
b111 (
b111 )
1"
#1250000
0"
b1111001 %
#1255000
b110 (
b110 )
b101101 '
b101101 *
0!
1"
#1260000
0"
b1111010 %
#1265000
b1011010 '
b1011010 *
b101 (
b101 )
1"
#1270000
0"
b1111011 %
#1275000
1&
b10 (
b10 )
b10110100 '
b10110100 *
1"
#1280000
0"
b1111100 %
#1285000
1!
b1101000 '
b1101000 *
b100 (
b100 )
1"
#1290000
0"
b1111101 %
#1295000
b1 (
b1 )
b11010001 '
b11010001 *
1"
#1300000
0"
b1111110 %
#1305000
b10100011 '
b10100011 *
b11 (
b11 )
1"
#1310000
0"
b1111111 %
#1315000
b111 (
b111 )
b1000110 '
b1000110 *
1"
#1320000
0"
b10000000 %
#1325000
b10001100 '
b10001100 *
b110 (
b110 )
1"
#1330000
0"
b10000001 %
#1335000
b101 (
b101 )
b11001 '
b11001 *
1"
#1340000
0"
b10000010 %
#1345000
b110011 '
b110011 *
b10 (
b10 )
1"
#1350000
0"
b10000011 %
#1355000
b100 (
b100 )
b1100111 '
b1100111 *
1"
#1360000
0"
b10000100 %
#1365000
0&
b11001110 '
b11001110 *
b1 (
b1 )
1"
#1370000
0"
b10000101 %
#1375000
1&
b11 (
b11 )
b10011100 '
b10011100 *
0!
1"
#1380000
0"
b10000110 %
#1385000
1!
b111001 '
b111001 *
b111 (
b111 )
1"
#1390000
0"
b10000111 %
#1395000
0&
b110 (
b110 )
b1110011 '
b1110011 *
1"
#1400000
0"
b10001000 %
#1405000
1&
0!
b11100111 '
b11100111 *
b101 (
b101 )
1"
#1410000
0"
b10001001 %
#1415000
0&
b10 (
b10 )
b11001111 '
b11001111 *
1!
1"
#1420000
0"
b10001010 %
#1425000
1&
0!
b10011110 '
b10011110 *
b100 (
b100 )
1"
#1430000
0"
b10001011 %
#1435000
b1 (
b1 )
b111100 '
b111100 *
1!
1"
#1440000
0"
b10001100 %
#1445000
0&
b1111000 '
b1111000 *
b11 (
b11 )
1"
#1450000
0"
b10001101 %
#1455000
1&
b111 (
b111 )
b11110001 '
b11110001 *
0!
1"
#1460000
0"
b10001110 %
#1465000
0&
1!
b11100011 '
b11100011 *
b110 (
b110 )
1"
#1470000
0"
b10001111 %
#1475000
b101 (
b101 )
b11000110 '
b11000110 *
0!
1"
#1480000
0"
b10010000 %
#1485000
1&
b10001101 '
b10001101 *
b10 (
b10 )
1"
#1490000
0"
b10010001 %
#1495000
0&
b100 (
b100 )
b11011 '
b11011 *
1!
1"
#1500000
0"
b10010010 %
#1505000
1&
0!
b110110 '
b110110 *
b1 (
b1 )
1"
#1510000
0"
b10010011 %
#1515000
0&
b11 (
b11 )
b1101100 '
b1101100 *
1!
1"
#1520000
0"
b10010100 %
#1525000
1&
0!
b11011000 '
b11011000 *
b111 (
b111 )
1"
#1530000
0"
b10010101 %
#1535000
b110 (
b110 )
b10110000 '
b10110000 *
1!
1"
#1540000
0"
b10010110 %
#1545000
0&
b1100001 '
b1100001 *
b101 (
b101 )
1"
#1550000
0"
b10010111 %
#1555000
b10 (
b10 )
b11000010 '
b11000010 *
0!
1"
#1560000
0"
b10011000 %
#1565000
b10000100 '
b10000100 *
b100 (
b100 )
1"
#1570000
0"
b10011001 %
#1575000
b1 (
b1 )
b1000 '
b1000 *
1"
#1580000
0"
b10011010 %
#1585000
b10001 '
b10001 *
b11 (
b11 )
1"
#1590000
0"
b10011011 %
#1595000
b111 (
b111 )
b100010 '
b100010 *
1"
#1600000
0"
b10011100 %
#1605000
1&
b1000101 '
b1000101 *
b110 (
b110 )
1"
#1610000
0"
b10011101 %
#1615000
b101 (
b101 )
b10001011 '
b10001011 *
1!
1"
#1620000
0"
b10011110 %
#1625000
0&
b10111 '
b10111 *
b10 (
b10 )
1"
#1630000
0"
b10011111 %
#1635000
b100 (
b100 )
b101110 '
b101110 *
0!
1"
#1640000
0"
b10100000 %
#1645000
b1011101 '
b1011101 *
b1 (
b1 )
1"
#1650000
0"
b10100001 %
#1655000
1&
b11 (
b11 )
b10111010 '
b10111010 *
1"
#1660000
0"
b10100010 %
#1665000
1!
b1110101 '
b1110101 *
b111 (
b111 )
1"
#1670000
0"
b10100011 %
#1675000
0&
b110 (
b110 )
b11101011 '
b11101011 *
1"
#1680000
0"
b10100100 %
#1685000
0!
b11010111 '
b11010111 *
b101 (
b101 )
1"
#1690000
0"
b10100101 %
#1695000
1&
b10 (
b10 )
b10101111 '
b10101111 *
1"
#1700000
0"
b10100110 %
#1705000
0&
1!
b1011110 '
b1011110 *
b100 (
b100 )
1"
#1710000
0"
b10100111 %
#1715000
b1 (
b1 )
b10111101 '
b10111101 *
0!
1"
#1720000
0"
b10101000 %
#1725000
1&
b1111011 '
b1111011 *
b11 (
b11 )
1"
#1730000
0"
b10101001 %
#1735000
0&
b111 (
b111 )
b11110110 '
b11110110 *
1!
1"
#1740000
0"
b10101010 %
#1745000
1&
0!
b11101101 '
b11101101 *
b110 (
b110 )
1"
#1750000
0"
b10101011 %
#1755000
b101 (
b101 )
b11011011 '
b11011011 *
1!
1"
#1760000
0"
b10101100 %
#1765000
0&
b10110111 '
b10110111 *
b10 (
b10 )
1"
#1770000
0"
b10101101 %
#1775000
b100 (
b100 )
b1101111 '
b1101111 *
0!
1"
#1780000
0"
b10101110 %
#1785000
1&
b11011111 '
b11011111 *
b1 (
b1 )
1"
#1790000
0"
b10101111 %
#1795000
0&
b11 (
b11 )
b10111110 '
b10111110 *
1!
1"
#1800000
0"
b10110000 %
#1805000
0!
b1111100 '
b1111100 *
b111 (
b111 )
1"
#1810000
0"
b10110001 %
#1815000
1&
b110 (
b110 )
b11111000 '
b11111000 *
1"
#1820000
0"
b10110010 %
#1825000
0&
1!
b11110000 '
b11110000 *
b101 (
b101 )
1"
#1830000
0"
b10110011 %
#1835000
b10 (
b10 )
b11100001 '
b11100001 *
0!
1"
#1840000
0"
b10110100 %
#1845000
b11000011 '
b11000011 *
b100 (
b100 )
1"
#1850000
0"
b10110101 %
#1855000
1&
b1 (
b1 )
b10000110 '
b10000110 *
1"
#1860000
0"
b10110110 %
#1865000
0&
1!
b1101 '
b1101 *
b11 (
b11 )
1"
#1870000
0"
b10110111 %
#1875000
b111 (
b111 )
b11010 '
b11010 *
0!
1"
#1880000
0"
b10111000 %
#1885000
b110100 '
b110100 *
b110 (
b110 )
1"
#1890000
0"
b10111001 %
#1895000
1&
b101 (
b101 )
b1101001 '
b1101001 *
1"
#1900000
0"
b10111010 %
#1905000
1!
b11010011 '
b11010011 *
b10 (
b10 )
1"
#1910000
0"
b10111011 %
#1915000
b100 (
b100 )
b10100110 '
b10100110 *
1"
#1920000
0"
b10111100 %
#1925000
b1001101 '
b1001101 *
b1 (
b1 )
1"
#1930000
0"
b10111101 %
#1935000
0&
b11 (
b11 )
b10011010 '
b10011010 *
1"
#1940000
0"
b10111110 %
#1945000
0!
b110101 '
b110101 *
b111 (
b111 )
1"
#1950000
0"
b10111111 %
#1955000
1&
b110 (
b110 )
b1101011 '
b1101011 *
1"
#1960000
0"
b11000000 %
#1965000
1!
b11010110 '
b11010110 *
b101 (
b101 )
1"
#1970000
0"
b11000001 %
#1975000
0&
b10 (
b10 )
b10101101 '
b10101101 *
1"
#1980000
0"
b11000010 %
#1985000
1&
0!
b1011011 '
b1011011 *
b100 (
b100 )
1"
#1990000
0"
b11000011 %
#1995000
0&
b1 (
b1 )
b10110110 '
b10110110 *
1!
1"
#2000000
0"
b11000100 %
#2005000
1&
0!
b1101101 '
b1101101 *
b11 (
b11 )
1"
#2010000
0"
b11000101 %
#2015000
0&
b111 (
b111 )
b11011010 '
b11011010 *
1!
1"
#2020000
0"
b11000110 %
#2025000
0!
b10110101 '
b10110101 *
b110 (
b110 )
1"
#2030000
0"
b11000111 %
#2035000
1&
b101 (
b101 )
b1101010 '
b1101010 *
1"
#2040000
0"
b11001000 %
#2045000
0&
1!
b11010100 '
b11010100 *
b10 (
b10 )
1"
#2050000
0"
b11001001 %
#2055000
b100 (
b100 )
b10101000 '
b10101000 *
0!
1"
#2060000
0"
b11001010 %
#2065000
b1010000 '
b1010000 *
b1 (
b1 )
1"
#2070000
0"
b11001011 %
#2075000
b11 (
b11 )
b10100000 '
b10100000 *
1"
#2080000
0"
b11001100 %
#2085000
b1000001 '
b1000001 *
b111 (
b111 )
1"
#2090000
0"
b11001101 %
#2095000
b110 (
b110 )
b10000010 '
b10000010 *
1"
#2100000
0"
b11001110 %
#2105000
b100 '
b100 *
b101 (
b101 )
1"
#2110000
0"
b11001111 %
#2115000
b10 (
b10 )
b1001 '
b1001 *
1"
#2120000
0"
b11010000 %
#2125000
1&
b10011 '
b10011 *
b100 (
b100 )
1"
#2130000
0"
b11010001 %
#2135000
0&
b1 (
b1 )
b100111 '
b100111 *
1!
1"
#2140000
0"
b11010010 %
#2145000
1&
0!
b1001110 '
b1001110 *
b11 (
b11 )
1"
#2150000
0"
b11010011 %
#2155000
0&
b111 (
b111 )
b10011101 '
b10011101 *
1!
1"
#2160000
0"
b11010100 %
#2165000
0!
b111011 '
b111011 *
b110 (
b110 )
1"
#2170000
0"
b11010101 %
#2175000
1&
b101 (
b101 )
b1110110 '
b1110110 *
1"
#2180000
0"
b11010110 %
#2185000
0&
1!
b11101100 '
b11101100 *
b10 (
b10 )
1"
#2190000
0"
b11010111 %
#2195000
1&
b100 (
b100 )
b11011001 '
b11011001 *
0!
1"
#2200000
0"
b11011000 %
#2205000
0&
1!
b10110010 '
b10110010 *
b1 (
b1 )
1"
#2210000
0"
b11011001 %
#2215000
b11 (
b11 )
b1100100 '
b1100100 *
0!
1"
#2220000
0"
b11011010 %
#2225000
1&
b11001001 '
b11001001 *
b111 (
b111 )
1"
#2230000
0"
b11011011 %
#2235000
b110 (
b110 )
b10010010 '
b10010010 *
1!
1"
#2240000
0"
b11011100 %
#2245000
0&
b100100 '
b100100 *
b101 (
b101 )
1"
#2250000
0"
b11011101 %
#2255000
b10 (
b10 )
b1001001 '
b1001001 *
0!
1"
#2260000
0"
b11011110 %
#2265000
1&
b10010011 '
b10010011 *
b100 (
b100 )
1"
#2270000
0"
b11011111 %
#2275000
0&
b1 (
b1 )
b100110 '
b100110 *
1!
1"
#2280000
0"
b11100000 %
#2285000
1&
0!
b1001100 '
b1001100 *
b11 (
b11 )
1"
#2290000
0"
b11100001 %
#2295000
0&
b111 (
b111 )
b10011000 '
b10011000 *
1!
1"
#2300000
0"
b11100010 %
#2305000
0!
b110000 '
b110000 *
b110 (
b110 )
1"
#2310000
0"
b11100011 %
#2315000
1&
b101 (
b101 )
b1100000 '
b1100000 *
1"
#2320000
0"
b11100100 %
#2325000
1!
b11000000 '
b11000000 *
b10 (
b10 )
1"
#2330000
0"
b11100101 %
#2335000
b100 (
b100 )
b10000001 '
b10000001 *
1"
#2340000
0"
b11100110 %
#2345000
0&
b11 '
b11 *
b1 (
b1 )
1"
#2350000
0"
b11100111 %
#2355000
b11 (
b11 )
b111 '
b111 *
0!
1"
#2360000
0"
b11101000 %
#2365000
b1110 '
b1110 *
b111 (
b111 )
1"
#2370000
0"
b11101001 %
#2375000
b110 (
b110 )
b11101 '
b11101 *
1"
#2380000
0"
b11101010 %
#2385000
1&
b111010 '
b111010 *
b101 (
b101 )
1"
#2390000
0"
b11101011 %
#2395000
0&
b10 (
b10 )
b1110100 '
b1110100 *
1!
1"
#2400000
0"
b11101100 %
#2405000
0!
b11101001 '
b11101001 *
b100 (
b100 )
1"
#2410000
0"
b11101101 %
#2415000
1&
b1 (
b1 )
b11010010 '
b11010010 *
1"
#2420000
0"
b11101110 %
#2425000
1!
b10100100 '
b10100100 *
b11 (
b11 )
1"
#2430000
0"
b11101111 %
#2435000
b111 (
b111 )
b1001000 '
b1001000 *
1"
#2440000
0"
b11110000 %
#2445000
b10010001 '
b10010001 *
b110 (
b110 )
1"
#2450000
0"
b11110001 %
#2455000
0&
b101 (
b101 )
b100011 '
b100011 *
1"
#2460000
0"
b11110010 %
#2465000
1&
0!
b1000111 '
b1000111 *
b10 (
b10 )
1"
#2470000
0"
b11110011 %
#2475000
b100 (
b100 )
b10001110 '
b10001110 *
1!
1"
#2480000
0"
b11110100 %
#2485000
b11100 '
b11100 *
b1 (
b1 )
1"
#2490000
0"
b11110101 %
#2495000
0&
b11 (
b11 )
b111000 '
b111000 *
1"
#2500000
0"
b11110110 %
#2505000
0!
b1110001 '
b1110001 *
b111 (
b111 )
1"
#2510000
0"
b11110111 %
#2515000
1&
b110 (
b110 )
b11100010 '
b11100010 *
1"
#2520000
0"
b11111000 %
#2525000
1!
b11000100 '
b11000100 *
b101 (
b101 )
1"
#2530000
0"
b11111001 %
#2535000
b10 (
b10 )
b10001000 '
b10001000 *
1"
#2540000
0"
b11111010 %
#2545000
0&
b10000 '
b10000 *
b100 (
b100 )
1"
#2550000
0"
b11111011 %
