RV32I/core/common/riscv_regfile.v
// ==================================================
//	[ VLSISYS Lab. ]
//	* Author		: Woong Choi (woongchoi@sm.ac.kr)
//	* Filename		: riscv_regfile.v
//	* Description	: 
// ==================================================

`ifndef	XLEN
`define	XLEN		32
`endif

module riscv_regfile
(
	output		[`XLEN-1:0]		o_regfile_rs1_data,
	output		[`XLEN-1:0]		o_regfile_rs2_data,
	input		[      4:0]		i_regfile_rs1_addr,
	input		[      4:0]		i_regfile_rs2_addr,
	input		[`XLEN-1:0]		i_regfile_rd_data,
	input		[      4:0]		i_regfile_rd_addr,
	input						i_regfile_rd_wen,
	input						i_clk
);

	// 32 base registers
	reg			[`XLEN-1:0]	registers[0:31];

	// Read ports for rs1 & rs2
	assign		o_regfile_rs1_data = registers[i_regfile_rs1_addr];
	assign		o_regfile_rs2_data = registers[i_regfile_rs2_addr];

	// Hardwired X0
	initial		registers[0] = `XLEN'b0;

	always @(posedge i_clk) begin
		//	"Write Enabled" and  "Write Address != 0"
		if (i_regfile_rd_wen && (i_regfile_rd_addr != 0)) begin
			registers[i_regfile_rd_addr] <= i_regfile_rd_data;
		//	Hold Data
		end else begin
			registers[i_regfile_rd_addr] <= registers[i_regfile_rd_addr];
		end
	end

endmodule

RV32I/core/common/riscv_regfile_tb.v
// ==================================================
//	[ VLSISYS Lab. ]
//	* Author		: Woong Choi (woongchoi@sm.ac.kr)
//	* Filename		: riscv_regfile_tb.v
//	* Description	: 
// ==================================================

// --------------------------------------------------
//	Define Global Variables
// --------------------------------------------------
`define	XLEN		32
`define	CLKFREQ		100			// Clock Freq. (Unit: MHz)
`define	SIMCYCLE	32			// Sim. Cycles

`include	"riscv_regfile.v"

module	riscv_regfile_tb;
// --------------------------------------------------
//	DUT Signals & Instantiate
// --------------------------------------------------
	wire	[`XLEN-1:0]		o_regfile_rs1_data ;
	wire	[`XLEN-1:0]		o_regfile_rs2_data ;
	reg		[      4:0]		i_regfile_rs1_addr ;
	reg		[      4:0]		i_regfile_rs2_addr ;
	reg		[`XLEN-1:0]		i_regfile_rd_data  ;
	reg		[      4:0]		i_regfile_rd_addr  ;
	reg						i_regfile_rd_wen   ;
	reg						i_clk              ;

	riscv_regfile
	u_riscv_regfile(
		.o_regfile_rs1_data	(o_regfile_rs1_data	),
		.o_regfile_rs2_data	(o_regfile_rs2_data	),
		.i_regfile_rs1_addr	(i_regfile_rs1_addr	),
		.i_regfile_rs2_addr	(i_regfile_rs2_addr	),
		.i_regfile_rd_data	(i_regfile_rd_data	),
		.i_regfile_rd_addr	(i_regfile_rd_addr	),
		.i_regfile_rd_wen	(i_regfile_rd_wen	),
		.i_clk				(i_clk				)
	);


// --------------------------------------------------
//	Clock
// --------------------------------------------------
	always	#(500/`CLKFREQ)	i_clk = ~i_clk;

// --------------------------------------------------
//	Tasks
// --------------------------------------------------
	reg		[8*32-1:0] taskState;	// Length is limitted to 32

	task init;
		begin
			i_regfile_rs1_addr  = 0;
			i_regfile_rs2_addr  = 0;
			i_regfile_rd_data   = 0;
			i_regfile_rd_addr   = 0;
			i_regfile_rd_wen    = 0;
			i_clk				= 0;              
		end
	endtask

	task regWR;
		input	[      4:0]		ti_regfile_rd_addr;
		input	[`XLEN-1:0]		ti_regfile_rd_data;
		begin
			taskState			= "WR";
			i_regfile_rd_data	= ti_regfile_rd_data;
			i_regfile_rd_addr	= ti_regfile_rd_addr;
			i_regfile_rd_wen	= 1;
		end
	endtask

	task regRD;
		input	[      4:0]		ti_regfile_rs1_addr;
		input	[`XLEN-1:0]		ti_regfile_rs2_addr;
		begin
			taskState			= "RD";
			i_regfile_rs1_addr	= ti_regfile_rs1_addr;
			i_regfile_rs2_addr	= ti_regfile_rs2_addr;
			i_regfile_rd_wen	= 0;
		end
	endtask

// --------------------------------------------------
//	Test Stimulus
// --------------------------------------------------
	integer		i = 0;
	initial begin
		init();
		#(1000/`CLKFREQ);
		for (i=0; i<`SIMCYCLE; i++) begin
			regWR(i, i);
			#(1000/`CLKFREQ);
		end

		for (i=0; i<`SIMCYCLE; i++) begin
			regRD(i, i);
			#(1000/`CLKFREQ);
		end

		for (i=0; i<`SIMCYCLE; i++) begin
			regWR(i, $urandom_range(0, 2**31-1));	// 2**32 is not supported
			#(1000/`CLKFREQ);
			regRD(i, i);
			#(1000/`CLKFREQ);
		end
		$finish;
	end

// --------------------------------------------------
//	Dump VCD
// --------------------------------------------------
	reg	[8*32-1:0]	vcd_file;
	initial begin
		if ($value$plusargs("vcd_file=%s", vcd_file)) begin
			$dumpfile(vcd_file);
			$dumpvars;
			for (i=0; i<32; i++) begin
				$dumpvars(0, u_riscv_regfile.registers[i]);
			end
			$dumpvars;
		end else begin
			$dumpfile("regfile_tb.vcd");
			$dumpvars;
		end
	end

endmodule

RV32I/core/common/vcd/riscv_regfile.vcd
$date
	Mon Jul 15 23:18:39 2024
$end
$version
	Icarus Verilog
$end
$timescale
	1ps
$end
$scope module riscv_regfile_tb $end
$var wire 32 ! o_regfile_rs2_data [31:0] $end
$var wire 32 " o_regfile_rs1_data [31:0] $end
$var reg 1 # i_clk $end
$var reg 5 $ i_regfile_rd_addr [4:0] $end
$var reg 32 % i_regfile_rd_data [31:0] $end
$var reg 1 & i_regfile_rd_wen $end
$var reg 5 ' i_regfile_rs1_addr [4:0] $end
$var reg 5 ( i_regfile_rs2_addr [4:0] $end
$var reg 256 ) taskState [255:0] $end
$var reg 256 * vcd_file [255:0] $end
$var integer 32 + i [31:0] $end
$scope module u_riscv_regfile $end
$var wire 1 # i_clk $end
$var wire 5 , i_regfile_rd_addr [4:0] $end
$var wire 32 - i_regfile_rd_data [31:0] $end
$var wire 1 & i_regfile_rd_wen $end
$var wire 5 . i_regfile_rs1_addr [4:0] $end
$var wire 5 / i_regfile_rs2_addr [4:0] $end
$var wire 32 0 o_regfile_rs1_data [31:0] $end
$var wire 32 1 o_regfile_rs2_data [31:0] $end
$upscope $end
$scope task init $end
$upscope $end
$scope task regRD $end
$var reg 5 2 ti_regfile_rs1_addr [4:0] $end
$var reg 32 3 ti_regfile_rs2_addr [31:0] $end
$upscope $end
$scope task regWR $end
$var reg 5 4 ti_regfile_rd_addr [4:0] $end
$var reg 32 5 ti_regfile_rd_data [31:0] $end
$upscope $end
$upscope $end
$scope module riscv_regfile_tb $end
$scope module u_riscv_regfile $end
$var reg 32 6 \registers[0] [31:0] $end
$upscope $end
$upscope $end
$scope module riscv_regfile_tb $end
$scope module u_riscv_regfile $end
$var reg 32 7 \registers[1] [31:0] $end
$upscope $end
$upscope $end
$scope module riscv_regfile_tb $end
$scope module u_riscv_regfile $end
$var reg 32 8 \registers[2] [31:0] $end
$upscope $end
$upscope $end
$scope module riscv_regfile_tb $end
$scope module u_riscv_regfile $end
$var reg 32 9 \registers[3] [31:0] $end
$upscope $end
$upscope $end
$scope module riscv_regfile_tb $end
$scope module u_riscv_regfile $end
$var reg 32 : \registers[4] [31:0] $end
$upscope $end
$upscope $end
$scope module riscv_regfile_tb $end
$scope module u_riscv_regfile $end
$var reg 32 ; \registers[5] [31:0] $end
$upscope $end
$upscope $end
$scope module riscv_regfile_tb $end
$scope module u_riscv_regfile $end
$var reg 32 < \registers[6] [31:0] $end
$upscope $end
$upscope $end
$scope module riscv_regfile_tb $end
$scope module u_riscv_regfile $end
$var reg 32 = \registers[7] [31:0] $end
$upscope $end
$upscope $end
$scope module riscv_regfile_tb $end
$scope module u_riscv_regfile $end
$var reg 32 > \registers[8] [31:0] $end
$upscope $end
$upscope $end
$scope module riscv_regfile_tb $end
$scope module u_riscv_regfile $end
$var reg 32 ? \registers[9] [31:0] $end
$upscope $end
$upscope $end
$scope module riscv_regfile_tb $end
$scope module u_riscv_regfile $end
$var reg 32 @ \registers[10] [31:0] $end
$upscope $end
$upscope $end
$scope module riscv_regfile_tb $end
$scope module u_riscv_regfile $end
$var reg 32 A \registers[11] [31:0] $end
$upscope $end
$upscope $end
$scope module riscv_regfile_tb $end
$scope module u_riscv_regfile $end
$var reg 32 B \registers[12] [31:0] $end
$upscope $end
$upscope $end
$scope module riscv_regfile_tb $end
$scope module u_riscv_regfile $end
$var reg 32 C \registers[13] [31:0] $end
$upscope $end
$upscope $end
$scope module riscv_regfile_tb $end
$scope module u_riscv_regfile $end
$var reg 32 D \registers[14] [31:0] $end
$upscope $end
$upscope $end
$scope module riscv_regfile_tb $end
$scope module u_riscv_regfile $end
$var reg 32 E \registers[15] [31:0] $end
$upscope $end
$upscope $end
$scope module riscv_regfile_tb $end
$scope module u_riscv_regfile $end
$var reg 32 F \registers[16] [31:0] $end
$upscope $end
$upscope $end
$scope module riscv_regfile_tb $end
$scope module u_riscv_regfile $end
$var reg 32 G \registers[17] [31:0] $end
$upscope $end
$upscope $end
$scope module riscv_regfile_tb $end
$scope module u_riscv_regfile $end
$var reg 32 H \registers[18] [31:0] $end
$upscope $end
$upscope $end
$scope module riscv_regfile_tb $end
$scope module u_riscv_regfile $end
$var reg 32 I \registers[19] [31:0] $end
$upscope $end
$upscope $end
$scope module riscv_regfile_tb $end
$scope module u_riscv_regfile $end
$var reg 32 J \registers[20] [31:0] $end
$upscope $end
$upscope $end
$scope module riscv_regfile_tb $end
$scope module u_riscv_regfile $end
$var reg 32 K \registers[21] [31:0] $end
$upscope $end
$upscope $end
$scope module riscv_regfile_tb $end
$scope module u_riscv_regfile $end
$var reg 32 L \registers[22] [31:0] $end
$upscope $end
$upscope $end
$scope module riscv_regfile_tb $end
$scope module u_riscv_regfile $end
$var reg 32 M \registers[23] [31:0] $end
$upscope $end
$upscope $end
$scope module riscv_regfile_tb $end
$scope module u_riscv_regfile $end
$var reg 32 N \registers[24] [31:0] $end
$upscope $end
$upscope $end
$scope module riscv_regfile_tb $end
$scope module u_riscv_regfile $end
$var reg 32 O \registers[25] [31:0] $end
$upscope $end
$upscope $end
$scope module riscv_regfile_tb $end
$scope module u_riscv_regfile $end
$var reg 32 P \registers[26] [31:0] $end
$upscope $end
$upscope $end
$scope module riscv_regfile_tb $end
$scope module u_riscv_regfile $end
$var reg 32 Q \registers[27] [31:0] $end
$upscope $end
$upscope $end
$scope module riscv_regfile_tb $end
$scope module u_riscv_regfile $end
$var reg 32 R \registers[28] [31:0] $end
$upscope $end
$upscope $end
$scope module riscv_regfile_tb $end
$scope module u_riscv_regfile $end
$var reg 32 S \registers[29] [31:0] $end
$upscope $end
$upscope $end
$scope module riscv_regfile_tb $end
$scope module u_riscv_regfile $end
$var reg 32 T \registers[30] [31:0] $end
$upscope $end
$upscope $end
$scope module riscv_regfile_tb $end
$scope module u_riscv_regfile $end
$var reg 32 U \registers[31] [31:0] $end
$upscope $end
$upscope $end
$scope module riscv_regfile_tb $end
$scope module u_riscv_regfile $end
$upscope $end
$scope task init $end
$upscope $end
$scope task regRD $end
$upscope $end
$scope task regWR $end
$upscope $end
$upscope $end
$enddefinitions $end
#0
$dumpvars
bx U
bx T
bx S
bx R
bx Q
bx P
bx O
bx N
bx M
bx L
bx K
bx J
bx I
bx H
bx G
bx F
bx E
bx D
bx C
bx B
bx A
bx @
bx ?
bx >
bx =
bx <
bx ;
bx :
bx 9
bx 8
bx 7
b0 6
bx 5
bx 4
bx 3
bx 2
b0 1
b0 0
b0 /
b0 .
b0 -
b0 ,
b100000 +
b10111000101111011101100110001101100100001011110111001001101001011100110110001101110110010111110111001001100101011001110110011001101001011011000110010100101110011101100110001101100100 *
bx )
b0 (
b0 '
0&
b0 %
b0 $
0#
b0 "
b0 !
$end
#5000
b0 6
1#
#10000
0#
1&
b101011101010010 )
b0 5
b0 4
b0 +
#15000
b0 6
1#
#20000
0#
b1 $
b1 ,
b1 %
b1 -
b1 5
b1 4
b1 +
#25000
b1 7
1#
#30000
0#
b10 $
b10 ,
b10 %
b10 -
b10 5
b10 4
b10 +
#35000
b10 8
1#
#40000
0#
b11 $
b11 ,
b11 %
b11 -
b11 5
b11 4
b11 +
#45000
b11 9
1#
#50000
0#
b100 $
b100 ,
b100 %
b100 -
b100 5
b100 4
b100 +
#55000
b100 :
1#
#60000
0#
b101 $
b101 ,
b101 %
b101 -
b101 5
b101 4
b101 +
#65000
b101 ;
1#
#70000
0#
b110 $
b110 ,
b110 %
b110 -
b110 5
b110 4
b110 +
#75000
b110 <
1#
#80000
0#
b111 $
b111 ,
b111 %
b111 -
b111 5
b111 4
b111 +
#85000
b111 =
1#
#90000
0#
b1000 $
b1000 ,
b1000 %
b1000 -
b1000 5
b1000 4
b1000 +
#95000
b1000 >
1#
#100000
0#
b1001 $
b1001 ,
b1001 %
b1001 -
b1001 5
b1001 4
b1001 +
#105000
b1001 ?
1#
#110000
0#
b1010 $
b1010 ,
b1010 %
b1010 -
b1010 5
b1010 4
b1010 +
#115000
b1010 @
1#
#120000
0#
b1011 $
b1011 ,
b1011 %
b1011 -
b1011 5
b1011 4
b1011 +
#125000
b1011 A
1#
#130000
0#
b1100 $
b1100 ,
b1100 %
b1100 -
b1100 5
b1100 4
b1100 +
#135000
b1100 B
1#
#140000
0#
b1101 $
b1101 ,
b1101 %
b1101 -
b1101 5
b1101 4
b1101 +
#145000
b1101 C
1#
#150000
0#
b1110 $
b1110 ,
b1110 %
b1110 -
b1110 5
b1110 4
b1110 +
#155000
b1110 D
1#
#160000
0#
b1111 $
b1111 ,
b1111 %
b1111 -
b1111 5
b1111 4
b1111 +
#165000
b1111 E
1#
#170000
0#
b10000 $
b10000 ,
b10000 %
b10000 -
b10000 5
b10000 4
b10000 +
#175000
b10000 F
1#
#180000
0#
b10001 $
b10001 ,
b10001 %
b10001 -
b10001 5
b10001 4
b10001 +
#185000
b10001 G
1#
#190000
0#
b10010 $
b10010 ,
b10010 %
b10010 -
b10010 5
b10010 4
b10010 +
#195000
b10010 H
1#
#200000
0#
b10011 $
b10011 ,
b10011 %
b10011 -
b10011 5
b10011 4
b10011 +
#205000
b10011 I
1#
#210000
0#
b10100 $
b10100 ,
b10100 %
b10100 -
b10100 5
b10100 4
b10100 +
#215000
b10100 J
1#
#220000
0#
b10101 $
b10101 ,
b10101 %
b10101 -
b10101 5
b10101 4
b10101 +
#225000
b10101 K
1#
#230000
0#
b10110 $
b10110 ,
b10110 %
b10110 -
b10110 5
b10110 4
b10110 +
#235000
b10110 L
1#
#240000
0#
b10111 $
b10111 ,
b10111 %
b10111 -
b10111 5
b10111 4
b10111 +
#245000
b10111 M
1#
#250000
0#
b11000 $
b11000 ,
b11000 %
b11000 -
b11000 5
b11000 4
b11000 +
#255000
b11000 N
1#
#260000
0#
b11001 $
b11001 ,
b11001 %
b11001 -
b11001 5
b11001 4
b11001 +
#265000
b11001 O
1#
#270000
0#
b11010 $
b11010 ,
b11010 %
b11010 -
b11010 5
b11010 4
b11010 +
#275000
b11010 P
1#
#280000
0#
b11011 $
b11011 ,
b11011 %
b11011 -
b11011 5
b11011 4
b11011 +
#285000
b11011 Q
1#
#290000
0#
b11100 $
b11100 ,
b11100 %
b11100 -
b11100 5
b11100 4
b11100 +
#295000
b11100 R
1#
#300000
0#
b11101 $
b11101 ,
b11101 %
b11101 -
b11101 5
b11101 4
b11101 +
#305000
b11101 S
1#
#310000
0#
b11110 $
b11110 ,
b11110 %
b11110 -
b11110 5
b11110 4
b11110 +
#315000
b11110 T
1#
#320000
0#
b11111 $
b11111 ,
b11111 %
b11111 -
b11111 5
b11111 4
b11111 +
#325000
b11111 U
1#
#330000
0#
0&
b101001001000100 )
b0 3
b0 2
b0 +
#335000
b11111 U
1#
#340000
0#
b1 !
b1 1
b1 (
b1 /
b1 "
b1 0
b1 '
b1 .
b1 3
b1 2
b1 +
#345000
b11111 U
1#
#350000
0#
b10 !
b10 1
b10 (
b10 /
b10 "
b10 0
b10 '
b10 .
b10 3
b10 2
b10 +
#355000
b11111 U
1#
#360000
0#
b11 !
b11 1
b11 (
b11 /
b11 "
b11 0
b11 '
b11 .
b11 3
b11 2
b11 +
#365000
b11111 U
1#
#370000
0#
b100 !
b100 1
b100 (
b100 /
b100 "
b100 0
b100 '
b100 .
b100 3
b100 2
b100 +
#375000
b11111 U
1#
#380000
0#
b101 !
b101 1
b101 (
b101 /
b101 "
b101 0
b101 '
b101 .
b101 3
b101 2
b101 +
#385000
b11111 U
1#
#390000
0#
b110 !
b110 1
b110 (
b110 /
b110 "
b110 0
b110 '
b110 .
b110 3
b110 2
b110 +
#395000
b11111 U
1#
#400000
0#
b111 !
b111 1
b111 (
b111 /
b111 "
b111 0
b111 '
b111 .
b111 3
b111 2
b111 +
#405000
b11111 U
1#
#410000
0#
b1000 !
b1000 1
b1000 (
b1000 /
b1000 "
b1000 0
b1000 '
b1000 .
b1000 3
b1000 2
b1000 +
#415000
b11111 U
1#
#420000
0#
b1001 !
b1001 1
b1001 (
b1001 /
b1001 "
b1001 0
b1001 '
b1001 .
b1001 3
b1001 2
b1001 +
#425000
b11111 U
1#
#430000
0#
b1010 !
b1010 1
b1010 (
b1010 /
b1010 "
b1010 0
b1010 '
b1010 .
b1010 3
b1010 2
b1010 +
#435000
b11111 U
1#
#440000
0#
b1011 !
b1011 1
b1011 (
b1011 /
b1011 "
b1011 0
b1011 '
b1011 .
b1011 3
b1011 2
b1011 +
#445000
b11111 U
1#
#450000
0#
b1100 !
b1100 1
b1100 (
b1100 /
b1100 "
b1100 0
b1100 '
b1100 .
b1100 3
b1100 2
b1100 +
#455000
b11111 U
1#
#460000
0#
b1101 !
b1101 1
b1101 (
b1101 /
b1101 "
b1101 0
b1101 '
b1101 .
b1101 3
b1101 2
b1101 +
#465000
b11111 U
1#
#470000
0#
b1110 !
b1110 1
b1110 (
b1110 /
b1110 "
b1110 0
b1110 '
b1110 .
b1110 3
b1110 2
b1110 +
#475000
b11111 U
1#
#480000
0#
b1111 !
b1111 1
b1111 (
b1111 /
b1111 "
b1111 0
b1111 '
b1111 .
b1111 3
b1111 2
b1111 +
#485000
b11111 U
1#
#490000
0#
b10000 !
b10000 1
b10000 (
b10000 /
b10000 "
b10000 0
b10000 '
b10000 .
b10000 3
b10000 2
b10000 +
#495000
b11111 U
1#
#500000
0#
b10001 !
b10001 1
b10001 (
b10001 /
b10001 "
b10001 0
b10001 '
b10001 .
b10001 3
b10001 2
b10001 +
#505000
b11111 U
1#
#510000
0#
b10010 !
b10010 1
b10010 (
b10010 /
b10010 "
b10010 0
b10010 '
b10010 .
b10010 3
b10010 2
b10010 +
#515000
b11111 U
1#
#520000
0#
b10011 !
b10011 1
b10011 (
b10011 /
b10011 "
b10011 0
b10011 '
b10011 .
b10011 3
b10011 2
b10011 +
#525000
b11111 U
1#
#530000
0#
b10100 !
b10100 1
b10100 (
b10100 /
b10100 "
b10100 0
b10100 '
b10100 .
b10100 3
b10100 2
b10100 +
#535000
b11111 U
1#
#540000
0#
b10101 !
b10101 1
b10101 (
b10101 /
b10101 "
b10101 0
b10101 '
b10101 .
b10101 3
b10101 2
b10101 +
#545000
b11111 U
1#
#550000
0#
b10110 !
b10110 1
b10110 (
b10110 /
b10110 "
b10110 0
b10110 '
b10110 .
b10110 3
b10110 2
b10110 +
#555000
b11111 U
1#
#560000
0#
b10111 !
b10111 1
b10111 (
b10111 /
b10111 "
b10111 0
b10111 '
b10111 .
b10111 3
b10111 2
b10111 +
#565000
b11111 U
1#
#570000
0#
b11000 !
b11000 1
b11000 (
b11000 /
b11000 "
b11000 0
b11000 '
b11000 .
b11000 3
b11000 2
b11000 +
#575000
b11111 U
1#
#580000
0#
b11001 !
b11001 1
b11001 (
b11001 /
b11001 "
b11001 0
b11001 '
b11001 .
b11001 3
b11001 2
b11001 +
#585000
b11111 U
1#
#590000
0#
b11010 !
b11010 1
b11010 (
b11010 /
b11010 "
b11010 0
b11010 '
b11010 .
b11010 3
b11010 2
b11010 +
#595000
b11111 U
1#
#600000
0#
b11011 !
b11011 1
b11011 (
b11011 /
b11011 "
b11011 0
b11011 '
b11011 .
b11011 3
b11011 2
b11011 +
#605000
b11111 U
1#
#610000
0#
b11100 !
b11100 1
b11100 (
b11100 /
b11100 "
b11100 0
b11100 '
b11100 .
b11100 3
b11100 2
b11100 +
#615000
b11111 U
1#
#620000
0#
b11101 !
b11101 1
b11101 (
b11101 /
b11101 "
b11101 0
b11101 '
b11101 .
b11101 3
b11101 2
b11101 +
#625000
b11111 U
1#
#630000
0#
b11110 !
b11110 1
b11110 (
b11110 /
b11110 "
b11110 0
b11110 '
b11110 .
b11110 3
b11110 2
b11110 +
#635000
b11111 U
1#
#640000
0#
b11111 !
b11111 1
b11111 (
b11111 /
b11111 "
b11111 0
b11111 '
b11111 .
b11111 3
b11111 2
b11111 +
#645000
b11111 U
1#
#650000
0#
1&
b0 $
b0 ,
b1001001000010101001101010010010 %
b1001001000010101001101010010010 -
b101011101010010 )
b1001001000010101001101010010010 5
b0 4
b0 +
#655000
b0 6
1#
#660000
0#
0&
b0 !
b0 1
b0 (
b0 /
b0 "
b0 0
b0 '
b0 .
b101001001000100 )
b0 3
b0 2
#665000
b0 6
1#
#670000
0#
1&
b1 $
b1 ,
b100000010001001010111101000000 %
b100000010001001010111101000000 -
b101011101010010 )
b100000010001001010111101000000 5
b1 4
b1 +
#675000
b100000010001001010111101000000 7
1#
#680000
0#
0&
b100000010001001010111101000000 !
b100000010001001010111101000000 1
b1 (
b1 /
b100000010001001010111101000000 "
b100000010001001010111101000000 0
b1 '
b1 .
b101001001000100 )
b1 3
b1 2
#685000
b100000010001001010111101000000 7
1#
#690000
0#
1&
b10 $
b10 ,
b10010000100110101100000100 %
b10010000100110101100000100 -
b101011101010010 )
b10010000100110101100000100 5
b10 4
b10 +
#695000
b10010000100110101100000100 8
1#
#700000
0#
0&
b10010000100110101100000100 !
b10010000100110101100000100 1
b10 (
b10 /
b10010000100110101100000100 "
b10010000100110101100000100 0
b10 '
b10 .
b101001001000100 )
b10 3
b10 2
#705000
b10010000100110101100000100 8
1#
#710000
0#
1&
b11 $
b11 ,
b11000111110000010101100110001 %
b11000111110000010101100110001 -
b101011101010010 )
b11000111110000010101100110001 5
b11 4
b11 +
#715000
b11000111110000010101100110001 9
1#
#720000
0#
0&
b11000111110000010101100110001 !
b11000111110000010101100110001 1
b11 (
b11 /
b11000111110000010101100110001 "
b11000111110000010101100110001 0
b11 '
b11 .
b101001001000100 )
b11 3
b11 2
#725000
b11000111110000010101100110001 9
1#
#730000
0#
1&
b100 $
b100 ,
b1000011010111001011110110000110 %
b1000011010111001011110110000110 -
b101011101010010 )
b1000011010111001011110110000110 5
b100 4
b100 +
#735000
b1000011010111001011110110000110 :
1#
#740000
0#
0&
b1000011010111001011110110000110 !
b1000011010111001011110110000110 1
b100 (
b100 /
b1000011010111001011110110000110 "
b1000011010111001011110110000110 0
b100 '
b100 .
b101001001000100 )
b100 3
b100 2
#745000
b1000011010111001011110110000110 :
1#
#750000
0#
1&
b101 $
b101 ,
b1100011011011111100110011000110 %
b1100011011011111100110011000110 -
b101011101010010 )
b1100011011011111100110011000110 5
b101 4
b101 +
#755000
b1100011011011111100110011000110 ;
1#
#760000
0#
0&
b1100011011011111100110011000110 !
b1100011011011111100110011000110 1
b101 (
b101 /
b1100011011011111100110011000110 "
b1100011011011111100110011000110 0
b101 '
b101 .
b101001001000100 )
b101 3
b101 2
#765000
b1100011011011111100110011000110 ;
1#
#770000
0#
1&
b110 $
b110 ,
b11001011000010100001000110010 %
b11001011000010100001000110010 -
b101011101010010 )
b11001011000010100001000110010 5
b110 4
b110 +
#775000
b11001011000010100001000110010 <
1#
#780000
0#
0&
b11001011000010100001000110010 !
b11001011000010100001000110010 1
b110 (
b110 /
b11001011000010100001000110010 "
b11001011000010100001000110010 0
b110 '
b110 .
b101001001000100 )
b110 3
b110 2
#785000
b11001011000010100001000110010 <
1#
#790000
0#
1&
b111 $
b111 ,
b100100110111010100100001001 %
b100100110111010100100001001 -
b101011101010010 )
b100100110111010100100001001 5
b111 4
b111 +
#795000
b100100110111010100100001001 =
1#
#800000
0#
0&
b100100110111010100100001001 !
b100100110111010100100001001 1
b111 (
b111 /
b100100110111010100100001001 "
b100100110111010100100001001 0
b111 '
b111 .
b101001001000100 )
b111 3
b111 2
#805000
b100100110111010100100001001 =
1#
#810000
0#
1&
b1000 $
b1000 ,
b1000000011110011111000110000000 %
b1000000011110011111000110000000 -
b101011101010010 )
b1000000011110011111000110000000 5
b1000 4
b1000 +
#815000
b1000000011110011111000110000000 >
1#
#820000
0#
0&
b1000000011110011111000110000000 !
b1000000011110011111000110000000 1
b1000 (
b1000 /
b1000000011110011111000110000000 "
b1000000011110011111000110000000 0
b1000 '
b1000 .
b101001001000100 )
b1000 3
b1000 2
#825000
b1000000011110011111000110000000 >
1#
#830000
0#
1&
b1001 $
b1001 ,
b1000011011010111110011010000110 %
b1000011011010111110011010000110 -
b101011101010010 )
b1000011011010111110011010000110 5
b1001 4
b1001 +
#835000
b1000011011010111110011010000110 ?
1#
#840000
0#
0&
b1000011011010111110011010000110 !
b1000011011010111110011010000110 1
b1001 (
b1001 /
b1000011011010111110011010000110 "
b1000011011010111110011010000110 0
b1001 '
b1001 .
b101001001000100 )
b1001 3
b1001 2
#845000
b1000011011010111110011010000110 ?
1#
#850000
0#
1&
b1010 $
b1010 ,
b1011101100100011111100010111011 %
b1011101100100011111100010111011 -
b101011101010010 )
b1011101100100011111100010111011 5
b1010 4
b1010 +
#855000
b1011101100100011111100010111011 @
1#
#860000
0#
0&
b1011101100100011111100010111011 !
b1011101100100011111100010111011 1
b1010 (
b1010 /
b1011101100100011111100010111011 "
b1011101100100011111100010111011 0
b1010 '
b1010 .
b101001001000100 )
b1010 3
b1010 2
#865000
b1011101100100011111100010111011 @
1#
#870000
0#
1&
b1011 $
b1011 ,
b1001111010001101110011010011110 %
b1001111010001101110011010011110 -
b101011101010010 )
b1001111010001101110011010011110 5
b1011 4
b1011 +
#875000
b1001111010001101110011010011110 A
1#
#880000
0#
0&
b1001111010001101110011010011110 !
b1001111010001101110011010011110 1
b1011 (
b1011 /
b1001111010001101110011010011110 "
b1001111010001101110011010011110 0
b1011 '
b1011 .
b101001001000100 )
b1011 3
b1011 2
#885000
b1001111010001101110011010011110 A
1#
#890000
0#
1&
b1100 $
b1100 ,
b1111011011010100010101111110110 %
b1111011011010100010101111110110 -
b101011101010010 )
b1111011011010100010101111110110 5
b1100 4
b1100 +
#895000
b1111011011010100010101111110110 B
1#
#900000
0#
0&
b1111011011010100010101111110110 !
b1111011011010100010101111110110 1
b1100 (
b1100 /
b1111011011010100010101111110110 "
b1111011011010100010101111110110 0
b1100 '
b1100 .
b101001001000100 )
b1100 3
b1100 2
#905000
b1111011011010100010101111110110 B
1#
#910000
0#
1&
b1101 $
b1101 ,
b1100011000101101111101111000110 %
b1100011000101101111101111000110 -
b101011101010010 )
b1100011000101101111101111000110 5
b1101 4
b1101 +
#915000
b1100011000101101111101111000110 C
1#
#920000
0#
0&
b1100011000101101111101111000110 !
b1100011000101101111101111000110 1
b1101 (
b1101 /
b1100011000101101111101111000110 "
b1100011000101101111101111000110 0
b1101 '
b1101 .
b101001001000100 )
b1101 3
b1101 2
#925000
b1100011000101101111101111000110 C
1#
#930000
0#
1&
b1110 $
b1110 ,
b1111110011111101111010011111100 %
b1111110011111101111010011111100 -
b101011101010010 )
b1111110011111101111010011111100 5
b1110 4
b1110 +
#935000
b1111110011111101111010011111100 D
1#
#940000
0#
0&
b1111110011111101111010011111100 !
b1111110011111101111010011111100 1
b1110 (
b1110 /
b1111110011111101111010011111100 "
b1111110011111101111010011111100 0
b1110 '
b1110 .
b101001001000100 )
b1110 3
b1110 2
#945000
b1111110011111101111010011111100 D
1#
#950000
0#
1&
b1111 $
b1111 ,
b110001100110111001001001100011 %
b110001100110111001001001100011 -
b101011101010010 )
b110001100110111001001001100011 5
b1111 4
b1111 +
#955000
b110001100110111001001001100011 E
1#
#960000
0#
0&
b110001100110111001001001100011 !
b110001100110111001001001100011 1
b1111 (
b1111 /
b110001100110111001001001100011 "
b110001100110111001001001100011 0
b1111 '
b1111 .
b101001001000100 )
b1111 3
b1111 2
#965000
b110001100110111001001001100011 E
1#
#970000
0#
1&
b10000 $
b10000 ,
b110001011110111100001001100010 %
b110001011110111100001001100010 -
b101011101010010 )
b110001011110111100001001100010 5
b10000 4
b10000 +
#975000
b110001011110111100001001100010 F
1#
#980000
0#
0&
b110001011110111100001001100010 !
b110001011110111100001001100010 1
b10000 (
b10000 /
b110001011110111100001001100010 "
b110001011110111100001001100010 0
b10000 '
b10000 .
b101001001000100 )
b10000 3
b10000 2
#985000
b110001011110111100001001100010 F
1#
#990000
0#
1&
b10001 $
b10001 ,
b101010100010011110100101010101 %
b101010100010011110100101010101 -
b101011101010010 )
b101010100010011110100101010101 5
b10001 4
b10001 +
#995000
b101010100010011110100101010101 G
1#
#1000000
0#
0&
b101010100010011110100101010101 !
b101010100010011110100101010101 1
b10001 (
b10001 /
b101010100010011110100101010101 "
b101010100010011110100101010101 0
b10001 '
b10001 .
b101001001000100 )
b10001 3
b10001 2
#1005000
b101010100010011110100101010101 G
1#
#1010000
0#
1&
b10010 $
b10010 ,
b1111001010101111111101111110010 %
b1111001010101111111101111110010 -
b101011101010010 )
b1111001010101111111101111110010 5
b10010 4
b10010 +
#1015000
b1111001010101111111101111110010 H
1#
#1020000
0#
0&
b1111001010101111111101111110010 !
b1111001010101111111101111110010 1
b10010 (
b10010 /
b1111001010101111111101111110010 "
b1111001010101111111101111110010 0
b10010 '
b10010 .
b101001001000100 )
b10010 3
b10010 2
#1025000
b1111001010101111111101111110010 H
1#
#1030000
0#
1&
b10011 $
b10011 ,
b11101111010010011100100111011 %
b11101111010010011100100111011 -
b101011101010010 )
b11101111010010011100100111011 5
b10011 4
b10011 +
#1035000
b11101111010010011100100111011 I
1#
