02_labs/example.v
// ==================================================
//	[ VLSISYS Lab. ]
//	* Author		: Woong Choi (woongchoi@sm.ac.kr)
//	* Filename		: example.v
//	* Description	: 
// ==================================================

module example
(	
	output		y,
	input		a, 
	input		b, 
	input		c
);

	wire		ab, bb, cb, n1, n2, n3;
	wire		n4;

	assign	#1	{ab, bb, cb}	=	~{a, b,	c};
	assign	#2				n1	=	ab	&	bb	&	cb;
	assign	#2				n2	=	a	&	bb	&	cb;
	assign	#2				n3	=	a	&	bb	&	c;
	assign	#2				n4	=	a	|	bb	&	cb;
	assign	#4				y	=	n1	|	n2	|	n3;

endmodule

02_labs/example_tb.v
// ==================================================
//	[ VLSISYS Lab. ]
//	* Author		: Woong Choi (woongchoi@sm.ac.kr)
//	* Filename		: example_tb.v
//	* Description	: 
// ==================================================

// --------------------------------------------------
//	Define Global Variables
// --------------------------------------------------
`define	CLKFREQ		100		// Clock Freq. (Unit: MHz)
`define	SIMCYCLE	4		// Sim. Cycles

// --------------------------------------------------
//	Includes
// --------------------------------------------------
`include	"example.v"

module example_tb;
// --------------------------------------------------
//	DUT Signals & Instantiate
// --------------------------------------------------
	wire	y;
	reg		a; 
	reg		b; 
	reg		c;

	example
	u_example(
		.y		(y		),
		.a		(a		),
		.b		(b		),
		.c		(c		)
	);

// --------------------------------------------------
//	Tasks
// --------------------------------------------------
	reg		[4*32-1:0]	taskState;
	integer				err	= 0;

	task init;
		begin
			taskState		= "Init";
			a					= 0;
			b					= 0;
			c					= 0;
		end
	endtask
	
// --------------------------------------------------
//	Test Stimulus
// --------------------------------------------------
	integer		i, j;
	initial begin
		init();
		for (i=0; i<`SIMCYCLE; i++) begin
			#(1000/`CLKFREQ);
		end
		$finish;
	end

// --------------------------------------------------
//	Dump VCD
// --------------------------------------------------
	reg	[8*32-1:0]	vcd_file;
	initial begin
		if ($value$plusargs("vcd_file=%s", vcd_file)) begin
			$dumpfile(vcd_file);
			$dumpvars;
		end else begin
			$dumpfile("example_tb.vcd");
			$dumpvars;
		end
	end

endmodule

02_labs/vcd/example.vcd
$date
	Tue May 28 15:47:49 2024
$end
$version
	Icarus Verilog
$end
$timescale
	1ps
$end
$scope module example_tb $end
$var wire 1 ! y $end
$var reg 1 " a $end
$var reg 1 # b $end
$var reg 1 $ c $end
$var reg 128 % taskState [127:0] $end
$var reg 256 & vcd_file [255:0] $end
$var integer 32 ' err [31:0] $end
$var integer 32 ( i [31:0] $end
$scope module u_example $end
$var wire 1 " a $end
$var wire 1 # b $end
$var wire 1 $ c $end
$var wire 1 ) n1 $end
$var wire 1 * n2 $end
$var wire 1 + n3 $end
$var wire 1 , n4 $end
$var wire 1 ! y $end
$var wire 1 - cb $end
$var wire 1 . bb $end
$var wire 1 / ab $end
$upscope $end
$scope task init $end
$upscope $end
$upscope $end
$enddefinitions $end
#0
$dumpvars
x/
x.
x-
x,
x+
x*
x)
b0 (
b0 '
b10111000101111011101100110001101100100001011110110010101111000011000010110110101110000011011000110010100101110011101100110001101100100 &
b1001001011011100110100101110100 %
0$
0#
0"
x!
$end
#1000
1/
1.
1-
#2000
0+
0*
#3000
1)
1,
#7000
1!
#10000
b1 (
#20000
b10 (
#30000
b11 (
#40000
b100 (
